{"cv_id": "01888170110d1ccf", "target_role": "Business Analyst", "score": 5, "cv_text": "John Wood Senior Business Analyst: Analytical Decision-Making & Growth \\ +1-925-885-5155 help@enhancv.com SUMMARY Senior Business Analyst with 12+ years of experience in using various business intelligence and modelling tools to assess companies' needs and determine sustainable and effective course of action. Trusted by key stakeholders to analyze business problems and opportunities, as a result have increased profit margins by 56%. Ability to analyze day-to-day operations within the big picture of things with a focus on not only achieving individual vision, but forecasting positive outcomes aiming to achieve overall business growth. EXPERIENCE Senior Business Analyst Torphy 8 2017- Ongoing 9 Luling, LA Torphy is a global IT service provider, focused on providing manufacturers with sustainable software to enhance their productivity. + Supported 12+ senior stakeholders in the decision-making process by investigating specific business problems and advising them with flexible, holistic solutions to meet individual business needs + Prepared various risk assessments during M&A negotiations to protect business interests and assure company growth by a 35% AVG + Assessing business model functions with a focus on processes and structures; HR and capital; information and technology to provide solutions to cut back LEAN waste by $450K/ year Business Analyst Dufour &3 2014-2017 9 Baltimore, MD Dufour is one of the largest distributors of digital content, delivering premium content internationally and in multiple formats. + Managed financial forecasts for ten engineering groups with more than $2 million per group + Developed analytical framework to forecast, plan, and model resource allocations across a multi-region call centers resulting in cost savings 20+% - Used various models to forecast revenue and provide solutions to decrease losses and cut LEAN waste by 25% Financial Consultant Lessard 63 2010-2014 9 Boca Raton, LA Lessard offers SMEs financial consultations to help them achieve sustainability and growth with external funding. + Increased company clientele by 6 persons and raised company revenue by over $20,000 in a two-month period + Specialized in designing portfolios for high net worth clients on a team that managed $6 billion in assets - Provided tailored investment advice for clients across 15 states LANGUAGES English Native eeeee Swedish Proficient eeee Japanese enee Proficient www.enhancv.com >linkedin.com =& Luling, LA SKILLS Business Analysis Techniques © MSO Google Analytics Salesforce Miro EDUCATION BS in Investment Management Lynn University @3 2006-2010 9 Boca Raton, LA STRENGTHS Decision-Making Focused on understanding business needs, key stakeholder requirements, and growth demands, to systematize data and navigate the best course ahead. This has impacted business growth with a +$1M in annual revenue. & Information Modelling Tools Using various tools (financial models, product roadmaps, mind maps, UI, SWOT, etc.) to better understand business-crucial data and offer working solutions to problems. » Business Proposals Apt at presenting solutions with detailed documentation at each stage of the process from business case, RFP, ITT, and requirements statements. Transparency and clarity of written statements has assisted decision- making to be quicker and more effective. v CERTIFICATION Professional in Business Analysis (PMI- PBA)® PMI Certified Business Analysis Professional (CBAP®) IIBA Professional Certificate in Business Analysis BCS Powered by (XZ Enhancy", "metadata": {"filename": "01888170110d1ccf.pdf", "original_category": "Business Analyst", "extraction_method": "ocr"}, "parsed_education": [{"degree": "BS", "institution": null, "years": "2006-2010", "field_of_study": "Investment Management"}], "extracted_skills": ["Google Analytics", "SWOT", "Decision-Making", "Business Analysis", "Salesforce", "Miro", "LEAN", "decision-making"], "parsed_summary": " Senior Business Analyst with 12+ years of", "personal_info": {"phone": "+1-925-885-5155", "first_name": "John", "last_name": "Wood"}}
{"cv_id": "01888170110d1ccf", "target_role": "Data Scientist", "score": 1, "cv_text": "John Wood Senior Business Analyst: Analytical Decision-Making & Growth \\ +1-925-885-5155 help@enhancv.com SUMMARY Senior Business Analyst with 12+ years of experience in using various business intelligence and modelling tools to assess companies' needs and determine sustainable and effective course of action. Trusted by key stakeholders to analyze business problems and opportunities, as a result have increased profit margins by 56%. Ability to analyze day-to-day operations within the big picture of things with a focus on not only achieving individual vision, but forecasting positive outcomes aiming to achieve overall business growth. EXPERIENCE Senior Business Analyst Torphy 8 2017- Ongoing 9 Luling, LA Torphy is a global IT service provider, focused on providing manufacturers with sustainable software to enhance their productivity. + Supported 12+ senior stakeholders in the decision-making process by investigating specific business problems and advising them with flexible, holistic solutions to meet individual business needs + Prepared various risk assessments during M&A negotiations to protect business interests and assure company growth by a 35% AVG + Assessing business model functions with a focus on processes and structures; HR and capital; information and technology to provide solutions to cut back LEAN waste by $450K/ year Business Analyst Dufour &3 2014-2017 9 Baltimore, MD Dufour is one of the largest distributors of digital content, delivering premium content internationally and in multiple formats. + Managed financial forecasts for ten engineering groups with more than $2 million per group + Developed analytical framework to forecast, plan, and model resource allocations across a multi-region call centers resulting in cost savings 20+% - Used various models to forecast revenue and provide solutions to decrease losses and cut LEAN waste by 25% Financial Consultant Lessard 63 2010-2014 9 Boca Raton, LA Lessard offers SMEs financial consultations to help them achieve sustainability and growth with external funding. + Increased company clientele by 6 persons and raised company revenue by over $20,000 in a two-month period + Specialized in designing portfolios for high net worth clients on a team that managed $6 billion in assets - Provided tailored investment advice for clients across 15 states LANGUAGES English Native eeeee Swedish Proficient eeee Japanese enee Proficient www.enhancv.com >linkedin.com =& Luling, LA SKILLS Business Analysis Techniques © MSO Google Analytics Salesforce Miro EDUCATION BS in Investment Management Lynn University @3 2006-2010 9 Boca Raton, LA STRENGTHS Decision-Making Focused on understanding business needs, key stakeholder requirements, and growth demands, to systematize data and navigate the best course ahead. This has impacted business growth with a +$1M in annual revenue. & Information Modelling Tools Using various tools (financial models, product roadmaps, mind maps, UI, SWOT, etc.) to better understand business-crucial data and offer working solutions to problems. » Business Proposals Apt at presenting solutions with detailed documentation at each stage of the process from business case, RFP, ITT, and requirements statements. Transparency and clarity of written statements has assisted decision- making to be quicker and more effective. v CERTIFICATION Professional in Business Analysis (PMI- PBA)® PMI Certified Business Analysis Professional (CBAP®) IIBA Professional Certificate in Business Analysis BCS Powered by (XZ Enhancy", "metadata": {"filename": "01888170110d1ccf.pdf", "original_category": "Business Analyst", "extraction_method": "ocr"}, "parsed_education": [{"degree": "BS", "institution": null, "years": "2006-2010", "field_of_study": "Investment Management"}], "extracted_skills": ["Google Analytics", "SWOT", "Decision-Making", "Business Analysis", "Salesforce", "Miro", "LEAN", "decision-making"], "parsed_summary": " Senior Business Analyst with 12+ years of", "personal_info": {"phone": "+1-925-885-5155", "first_name": "John", "last_name": "Wood"}}
{"cv_id": "01888170110d1ccf", "target_role": "DevOps Engineer", "score": 0, "cv_text": "John Wood Senior Business Analyst: Analytical Decision-Making & Growth \\ +1-925-885-5155 help@enhancv.com SUMMARY Senior Business Analyst with 12+ years of experience in using various business intelligence and modelling tools to assess companies' needs and determine sustainable and effective course of action. Trusted by key stakeholders to analyze business problems and opportunities, as a result have increased profit margins by 56%. Ability to analyze day-to-day operations within the big picture of things with a focus on not only achieving individual vision, but forecasting positive outcomes aiming to achieve overall business growth. EXPERIENCE Senior Business Analyst Torphy 8 2017- Ongoing 9 Luling, LA Torphy is a global IT service provider, focused on providing manufacturers with sustainable software to enhance their productivity. + Supported 12+ senior stakeholders in the decision-making process by investigating specific business problems and advising them with flexible, holistic solutions to meet individual business needs + Prepared various risk assessments during M&A negotiations to protect business interests and assure company growth by a 35% AVG + Assessing business model functions with a focus on processes and structures; HR and capital; information and technology to provide solutions to cut back LEAN waste by $450K/ year Business Analyst Dufour &3 2014-2017 9 Baltimore, MD Dufour is one of the largest distributors of digital content, delivering premium content internationally and in multiple formats. + Managed financial forecasts for ten engineering groups with more than $2 million per group + Developed analytical framework to forecast, plan, and model resource allocations across a multi-region call centers resulting in cost savings 20+% - Used various models to forecast revenue and provide solutions to decrease losses and cut LEAN waste by 25% Financial Consultant Lessard 63 2010-2014 9 Boca Raton, LA Lessard offers SMEs financial consultations to help them achieve sustainability and growth with external funding. + Increased company clientele by 6 persons and raised company revenue by over $20,000 in a two-month period + Specialized in designing portfolios for high net worth clients on a team that managed $6 billion in assets - Provided tailored investment advice for clients across 15 states LANGUAGES English Native eeeee Swedish Proficient eeee Japanese enee Proficient www.enhancv.com >linkedin.com =& Luling, LA SKILLS Business Analysis Techniques © MSO Google Analytics Salesforce Miro EDUCATION BS in Investment Management Lynn University @3 2006-2010 9 Boca Raton, LA STRENGTHS Decision-Making Focused on understanding business needs, key stakeholder requirements, and growth demands, to systematize data and navigate the best course ahead. This has impacted business growth with a +$1M in annual revenue. & Information Modelling Tools Using various tools (financial models, product roadmaps, mind maps, UI, SWOT, etc.) to better understand business-crucial data and offer working solutions to problems. » Business Proposals Apt at presenting solutions with detailed documentation at each stage of the process from business case, RFP, ITT, and requirements statements. Transparency and clarity of written statements has assisted decision- making to be quicker and more effective. v CERTIFICATION Professional in Business Analysis (PMI- PBA)® PMI Certified Business Analysis Professional (CBAP®) IIBA Professional Certificate in Business Analysis BCS Powered by (XZ Enhancy", "metadata": {"filename": "01888170110d1ccf.pdf", "original_category": "Business Analyst", "extraction_method": "ocr"}, "parsed_education": [{"degree": "BS", "institution": null, "years": "2006-2010", "field_of_study": "Investment Management"}], "extracted_skills": ["Google Analytics", "SWOT", "Decision-Making", "Business Analysis", "Salesforce", "Miro", "LEAN", "decision-making"], "parsed_summary": " Senior Business Analyst with 12+ years of", "personal_info": {"phone": "+1-925-885-5155", "first_name": "John", "last_name": "Wood"}}
{"cv_id": "01888170110d1ccf", "target_role": "ETL Developer", "score": 0, "cv_text": "John Wood Senior Business Analyst: Analytical Decision-Making & Growth \\ +1-925-885-5155 help@enhancv.com SUMMARY Senior Business Analyst with 12+ years of experience in using various business intelligence and modelling tools to assess companies' needs and determine sustainable and effective course of action. Trusted by key stakeholders to analyze business problems and opportunities, as a result have increased profit margins by 56%. Ability to analyze day-to-day operations within the big picture of things with a focus on not only achieving individual vision, but forecasting positive outcomes aiming to achieve overall business growth. EXPERIENCE Senior Business Analyst Torphy 8 2017- Ongoing 9 Luling, LA Torphy is a global IT service provider, focused on providing manufacturers with sustainable software to enhance their productivity. + Supported 12+ senior stakeholders in the decision-making process by investigating specific business problems and advising them with flexible, holistic solutions to meet individual business needs + Prepared various risk assessments during M&A negotiations to protect business interests and assure company growth by a 35% AVG + Assessing business model functions with a focus on processes and structures; HR and capital; information and technology to provide solutions to cut back LEAN waste by $450K/ year Business Analyst Dufour &3 2014-2017 9 Baltimore, MD Dufour is one of the largest distributors of digital content, delivering premium content internationally and in multiple formats. + Managed financial forecasts for ten engineering groups with more than $2 million per group + Developed analytical framework to forecast, plan, and model resource allocations across a multi-region call centers resulting in cost savings 20+% - Used various models to forecast revenue and provide solutions to decrease losses and cut LEAN waste by 25% Financial Consultant Lessard 63 2010-2014 9 Boca Raton, LA Lessard offers SMEs financial consultations to help them achieve sustainability and growth with external funding. + Increased company clientele by 6 persons and raised company revenue by over $20,000 in a two-month period + Specialized in designing portfolios for high net worth clients on a team that managed $6 billion in assets - Provided tailored investment advice for clients across 15 states LANGUAGES English Native eeeee Swedish Proficient eeee Japanese enee Proficient www.enhancv.com >linkedin.com =& Luling, LA SKILLS Business Analysis Techniques © MSO Google Analytics Salesforce Miro EDUCATION BS in Investment Management Lynn University @3 2006-2010 9 Boca Raton, LA STRENGTHS Decision-Making Focused on understanding business needs, key stakeholder requirements, and growth demands, to systematize data and navigate the best course ahead. This has impacted business growth with a +$1M in annual revenue. & Information Modelling Tools Using various tools (financial models, product roadmaps, mind maps, UI, SWOT, etc.) to better understand business-crucial data and offer working solutions to problems. » Business Proposals Apt at presenting solutions with detailed documentation at each stage of the process from business case, RFP, ITT, and requirements statements. Transparency and clarity of written statements has assisted decision- making to be quicker and more effective. v CERTIFICATION Professional in Business Analysis (PMI- PBA)® PMI Certified Business Analysis Professional (CBAP®) IIBA Professional Certificate in Business Analysis BCS Powered by (XZ Enhancy", "metadata": {"filename": "01888170110d1ccf.pdf", "original_category": "Business Analyst", "extraction_method": "ocr"}, "parsed_education": [{"degree": "BS", "institution": null, "years": "2006-2010", "field_of_study": "Investment Management"}], "extracted_skills": ["Google Analytics", "SWOT", "Decision-Making", "Business Analysis", "Salesforce", "Miro", "LEAN", "decision-making"], "parsed_summary": " Senior Business Analyst with 12+ years of", "personal_info": {"phone": "+1-925-885-5155", "first_name": "John", "last_name": "Wood"}}
{"cv_id": "01888170110d1ccf", "target_role": "Java Developer", "score": 0, "cv_text": "John Wood Senior Business Analyst: Analytical Decision-Making & Growth \\ +1-925-885-5155 help@enhancv.com SUMMARY Senior Business Analyst with 12+ years of experience in using various business intelligence and modelling tools to assess companies' needs and determine sustainable and effective course of action. Trusted by key stakeholders to analyze business problems and opportunities, as a result have increased profit margins by 56%. Ability to analyze day-to-day operations within the big picture of things with a focus on not only achieving individual vision, but forecasting positive outcomes aiming to achieve overall business growth. EXPERIENCE Senior Business Analyst Torphy 8 2017- Ongoing 9 Luling, LA Torphy is a global IT service provider, focused on providing manufacturers with sustainable software to enhance their productivity. + Supported 12+ senior stakeholders in the decision-making process by investigating specific business problems and advising them with flexible, holistic solutions to meet individual business needs + Prepared various risk assessments during M&A negotiations to protect business interests and assure company growth by a 35% AVG + Assessing business model functions with a focus on processes and structures; HR and capital; information and technology to provide solutions to cut back LEAN waste by $450K/ year Business Analyst Dufour &3 2014-2017 9 Baltimore, MD Dufour is one of the largest distributors of digital content, delivering premium content internationally and in multiple formats. + Managed financial forecasts for ten engineering groups with more than $2 million per group + Developed analytical framework to forecast, plan, and model resource allocations across a multi-region call centers resulting in cost savings 20+% - Used various models to forecast revenue and provide solutions to decrease losses and cut LEAN waste by 25% Financial Consultant Lessard 63 2010-2014 9 Boca Raton, LA Lessard offers SMEs financial consultations to help them achieve sustainability and growth with external funding. + Increased company clientele by 6 persons and raised company revenue by over $20,000 in a two-month period + Specialized in designing portfolios for high net worth clients on a team that managed $6 billion in assets - Provided tailored investment advice for clients across 15 states LANGUAGES English Native eeeee Swedish Proficient eeee Japanese enee Proficient www.enhancv.com >linkedin.com =& Luling, LA SKILLS Business Analysis Techniques © MSO Google Analytics Salesforce Miro EDUCATION BS in Investment Management Lynn University @3 2006-2010 9 Boca Raton, LA STRENGTHS Decision-Making Focused on understanding business needs, key stakeholder requirements, and growth demands, to systematize data and navigate the best course ahead. This has impacted business growth with a +$1M in annual revenue. & Information Modelling Tools Using various tools (financial models, product roadmaps, mind maps, UI, SWOT, etc.) to better understand business-crucial data and offer working solutions to problems. » Business Proposals Apt at presenting solutions with detailed documentation at each stage of the process from business case, RFP, ITT, and requirements statements. Transparency and clarity of written statements has assisted decision- making to be quicker and more effective. v CERTIFICATION Professional in Business Analysis (PMI- PBA)® PMI Certified Business Analysis Professional (CBAP®) IIBA Professional Certificate in Business Analysis BCS Powered by (XZ Enhancy", "metadata": {"filename": "01888170110d1ccf.pdf", "original_category": "Business Analyst", "extraction_method": "ocr"}, "parsed_education": [{"degree": "BS", "institution": null, "years": "2006-2010", "field_of_study": "Investment Management"}], "extracted_skills": ["Google Analytics", "SWOT", "Decision-Making", "Business Analysis", "Salesforce", "Miro", "LEAN", "decision-making"], "parsed_summary": " Senior Business Analyst with 12+ years of", "personal_info": {"phone": "+1-925-885-5155", "first_name": "John", "last_name": "Wood"}}
{"cv_id": "01888170110d1ccf", "target_role": "Python Developer", "score": 0, "cv_text": "John Wood Senior Business Analyst: Analytical Decision-Making & Growth \\ +1-925-885-5155 help@enhancv.com SUMMARY Senior Business Analyst with 12+ years of experience in using various business intelligence and modelling tools to assess companies' needs and determine sustainable and effective course of action. Trusted by key stakeholders to analyze business problems and opportunities, as a result have increased profit margins by 56%. Ability to analyze day-to-day operations within the big picture of things with a focus on not only achieving individual vision, but forecasting positive outcomes aiming to achieve overall business growth. EXPERIENCE Senior Business Analyst Torphy 8 2017- Ongoing 9 Luling, LA Torphy is a global IT service provider, focused on providing manufacturers with sustainable software to enhance their productivity. + Supported 12+ senior stakeholders in the decision-making process by investigating specific business problems and advising them with flexible, holistic solutions to meet individual business needs + Prepared various risk assessments during M&A negotiations to protect business interests and assure company growth by a 35% AVG + Assessing business model functions with a focus on processes and structures; HR and capital; information and technology to provide solutions to cut back LEAN waste by $450K/ year Business Analyst Dufour &3 2014-2017 9 Baltimore, MD Dufour is one of the largest distributors of digital content, delivering premium content internationally and in multiple formats. + Managed financial forecasts for ten engineering groups with more than $2 million per group + Developed analytical framework to forecast, plan, and model resource allocations across a multi-region call centers resulting in cost savings 20+% - Used various models to forecast revenue and provide solutions to decrease losses and cut LEAN waste by 25% Financial Consultant Lessard 63 2010-2014 9 Boca Raton, LA Lessard offers SMEs financial consultations to help them achieve sustainability and growth with external funding. + Increased company clientele by 6 persons and raised company revenue by over $20,000 in a two-month period + Specialized in designing portfolios for high net worth clients on a team that managed $6 billion in assets - Provided tailored investment advice for clients across 15 states LANGUAGES English Native eeeee Swedish Proficient eeee Japanese enee Proficient www.enhancv.com >linkedin.com =& Luling, LA SKILLS Business Analysis Techniques © MSO Google Analytics Salesforce Miro EDUCATION BS in Investment Management Lynn University @3 2006-2010 9 Boca Raton, LA STRENGTHS Decision-Making Focused on understanding business needs, key stakeholder requirements, and growth demands, to systematize data and navigate the best course ahead. This has impacted business growth with a +$1M in annual revenue. & Information Modelling Tools Using various tools (financial models, product roadmaps, mind maps, UI, SWOT, etc.) to better understand business-crucial data and offer working solutions to problems. » Business Proposals Apt at presenting solutions with detailed documentation at each stage of the process from business case, RFP, ITT, and requirements statements. Transparency and clarity of written statements has assisted decision- making to be quicker and more effective. v CERTIFICATION Professional in Business Analysis (PMI- PBA)® PMI Certified Business Analysis Professional (CBAP®) IIBA Professional Certificate in Business Analysis BCS Powered by (XZ Enhancy", "metadata": {"filename": "01888170110d1ccf.pdf", "original_category": "Business Analyst", "extraction_method": "ocr"}, "parsed_education": [{"degree": "BS", "institution": null, "years": "2006-2010", "field_of_study": "Investment Management"}], "extracted_skills": ["Google Analytics", "SWOT", "Decision-Making", "Business Analysis", "Salesforce", "Miro", "LEAN", "decision-making"], "parsed_summary": " Senior Business Analyst with 12+ years of", "personal_info": {"phone": "+1-925-885-5155", "first_name": "John", "last_name": "Wood"}}
{"cv_id": "01888170110d1ccf", "target_role": "React Developer", "score": 0, "cv_text": "John Wood Senior Business Analyst: Analytical Decision-Making & Growth \\ +1-925-885-5155 help@enhancv.com SUMMARY Senior Business Analyst with 12+ years of experience in using various business intelligence and modelling tools to assess companies' needs and determine sustainable and effective course of action. Trusted by key stakeholders to analyze business problems and opportunities, as a result have increased profit margins by 56%. Ability to analyze day-to-day operations within the big picture of things with a focus on not only achieving individual vision, but forecasting positive outcomes aiming to achieve overall business growth. EXPERIENCE Senior Business Analyst Torphy 8 2017- Ongoing 9 Luling, LA Torphy is a global IT service provider, focused on providing manufacturers with sustainable software to enhance their productivity. + Supported 12+ senior stakeholders in the decision-making process by investigating specific business problems and advising them with flexible, holistic solutions to meet individual business needs + Prepared various risk assessments during M&A negotiations to protect business interests and assure company growth by a 35% AVG + Assessing business model functions with a focus on processes and structures; HR and capital; information and technology to provide solutions to cut back LEAN waste by $450K/ year Business Analyst Dufour &3 2014-2017 9 Baltimore, MD Dufour is one of the largest distributors of digital content, delivering premium content internationally and in multiple formats. + Managed financial forecasts for ten engineering groups with more than $2 million per group + Developed analytical framework to forecast, plan, and model resource allocations across a multi-region call centers resulting in cost savings 20+% - Used various models to forecast revenue and provide solutions to decrease losses and cut LEAN waste by 25% Financial Consultant Lessard 63 2010-2014 9 Boca Raton, LA Lessard offers SMEs financial consultations to help them achieve sustainability and growth with external funding. + Increased company clientele by 6 persons and raised company revenue by over $20,000 in a two-month period + Specialized in designing portfolios for high net worth clients on a team that managed $6 billion in assets - Provided tailored investment advice for clients across 15 states LANGUAGES English Native eeeee Swedish Proficient eeee Japanese enee Proficient www.enhancv.com >linkedin.com =& Luling, LA SKILLS Business Analysis Techniques © MSO Google Analytics Salesforce Miro EDUCATION BS in Investment Management Lynn University @3 2006-2010 9 Boca Raton, LA STRENGTHS Decision-Making Focused on understanding business needs, key stakeholder requirements, and growth demands, to systematize data and navigate the best course ahead. This has impacted business growth with a +$1M in annual revenue. & Information Modelling Tools Using various tools (financial models, product roadmaps, mind maps, UI, SWOT, etc.) to better understand business-crucial data and offer working solutions to problems. » Business Proposals Apt at presenting solutions with detailed documentation at each stage of the process from business case, RFP, ITT, and requirements statements. Transparency and clarity of written statements has assisted decision- making to be quicker and more effective. v CERTIFICATION Professional in Business Analysis (PMI- PBA)® PMI Certified Business Analysis Professional (CBAP®) IIBA Professional Certificate in Business Analysis BCS Powered by (XZ Enhancy", "metadata": {"filename": "01888170110d1ccf.pdf", "original_category": "Business Analyst", "extraction_method": "ocr"}, "parsed_education": [{"degree": "BS", "institution": null, "years": "2006-2010", "field_of_study": "Investment Management"}], "extracted_skills": ["Google Analytics", "SWOT", "Decision-Making", "Business Analysis", "Salesforce", "Miro", "LEAN", "decision-making"], "parsed_summary": " Senior Business Analyst with 12+ years of", "personal_info": {"phone": "+1-925-885-5155", "first_name": "John", "last_name": "Wood"}}
{"cv_id": "01888170110d1ccf", "target_role": "SQL Developer", "score": 2, "cv_text": "John Wood Senior Business Analyst: Analytical Decision-Making & Growth \\ +1-925-885-5155 help@enhancv.com SUMMARY Senior Business Analyst with 12+ years of experience in using various business intelligence and modelling tools to assess companies' needs and determine sustainable and effective course of action. Trusted by key stakeholders to analyze business problems and opportunities, as a result have increased profit margins by 56%. Ability to analyze day-to-day operations within the big picture of things with a focus on not only achieving individual vision, but forecasting positive outcomes aiming to achieve overall business growth. EXPERIENCE Senior Business Analyst Torphy 8 2017- Ongoing 9 Luling, LA Torphy is a global IT service provider, focused on providing manufacturers with sustainable software to enhance their productivity. + Supported 12+ senior stakeholders in the decision-making process by investigating specific business problems and advising them with flexible, holistic solutions to meet individual business needs + Prepared various risk assessments during M&A negotiations to protect business interests and assure company growth by a 35% AVG + Assessing business model functions with a focus on processes and structures; HR and capital; information and technology to provide solutions to cut back LEAN waste by $450K/ year Business Analyst Dufour &3 2014-2017 9 Baltimore, MD Dufour is one of the largest distributors of digital content, delivering premium content internationally and in multiple formats. + Managed financial forecasts for ten engineering groups with more than $2 million per group + Developed analytical framework to forecast, plan, and model resource allocations across a multi-region call centers resulting in cost savings 20+% - Used various models to forecast revenue and provide solutions to decrease losses and cut LEAN waste by 25% Financial Consultant Lessard 63 2010-2014 9 Boca Raton, LA Lessard offers SMEs financial consultations to help them achieve sustainability and growth with external funding. + Increased company clientele by 6 persons and raised company revenue by over $20,000 in a two-month period + Specialized in designing portfolios for high net worth clients on a team that managed $6 billion in assets - Provided tailored investment advice for clients across 15 states LANGUAGES English Native eeeee Swedish Proficient eeee Japanese enee Proficient www.enhancv.com >linkedin.com =& Luling, LA SKILLS Business Analysis Techniques © MSO Google Analytics Salesforce Miro EDUCATION BS in Investment Management Lynn University @3 2006-2010 9 Boca Raton, LA STRENGTHS Decision-Making Focused on understanding business needs, key stakeholder requirements, and growth demands, to systematize data and navigate the best course ahead. This has impacted business growth with a +$1M in annual revenue. & Information Modelling Tools Using various tools (financial models, product roadmaps, mind maps, UI, SWOT, etc.) to better understand business-crucial data and offer working solutions to problems. » Business Proposals Apt at presenting solutions with detailed documentation at each stage of the process from business case, RFP, ITT, and requirements statements. Transparency and clarity of written statements has assisted decision- making to be quicker and more effective. v CERTIFICATION Professional in Business Analysis (PMI- PBA)® PMI Certified Business Analysis Professional (CBAP®) IIBA Professional Certificate in Business Analysis BCS Powered by (XZ Enhancy", "metadata": {"filename": "01888170110d1ccf.pdf", "original_category": "Business Analyst", "extraction_method": "ocr"}, "parsed_education": [{"degree": "BS", "institution": null, "years": "2006-2010", "field_of_study": "Investment Management"}], "extracted_skills": ["Google Analytics", "SWOT", "Decision-Making", "Business Analysis", "Salesforce", "Miro", "LEAN", "decision-making"], "parsed_summary": " Senior Business Analyst with 12+ years of", "personal_info": {"phone": "+1-925-885-5155", "first_name": "John", "last_name": "Wood"}}
{"cv_id": "01888170110d1ccf", "target_role": "Web Developer", "score": 0, "cv_text": "John Wood Senior Business Analyst: Analytical Decision-Making & Growth \\ +1-925-885-5155 help@enhancv.com SUMMARY Senior Business Analyst with 12+ years of experience in using various business intelligence and modelling tools to assess companies' needs and determine sustainable and effective course of action. Trusted by key stakeholders to analyze business problems and opportunities, as a result have increased profit margins by 56%. Ability to analyze day-to-day operations within the big picture of things with a focus on not only achieving individual vision, but forecasting positive outcomes aiming to achieve overall business growth. EXPERIENCE Senior Business Analyst Torphy 8 2017- Ongoing 9 Luling, LA Torphy is a global IT service provider, focused on providing manufacturers with sustainable software to enhance their productivity. + Supported 12+ senior stakeholders in the decision-making process by investigating specific business problems and advising them with flexible, holistic solutions to meet individual business needs + Prepared various risk assessments during M&A negotiations to protect business interests and assure company growth by a 35% AVG + Assessing business model functions with a focus on processes and structures; HR and capital; information and technology to provide solutions to cut back LEAN waste by $450K/ year Business Analyst Dufour &3 2014-2017 9 Baltimore, MD Dufour is one of the largest distributors of digital content, delivering premium content internationally and in multiple formats. + Managed financial forecasts for ten engineering groups with more than $2 million per group + Developed analytical framework to forecast, plan, and model resource allocations across a multi-region call centers resulting in cost savings 20+% - Used various models to forecast revenue and provide solutions to decrease losses and cut LEAN waste by 25% Financial Consultant Lessard 63 2010-2014 9 Boca Raton, LA Lessard offers SMEs financial consultations to help them achieve sustainability and growth with external funding. + Increased company clientele by 6 persons and raised company revenue by over $20,000 in a two-month period + Specialized in designing portfolios for high net worth clients on a team that managed $6 billion in assets - Provided tailored investment advice for clients across 15 states LANGUAGES English Native eeeee Swedish Proficient eeee Japanese enee Proficient www.enhancv.com >linkedin.com =& Luling, LA SKILLS Business Analysis Techniques © MSO Google Analytics Salesforce Miro EDUCATION BS in Investment Management Lynn University @3 2006-2010 9 Boca Raton, LA STRENGTHS Decision-Making Focused on understanding business needs, key stakeholder requirements, and growth demands, to systematize data and navigate the best course ahead. This has impacted business growth with a +$1M in annual revenue. & Information Modelling Tools Using various tools (financial models, product roadmaps, mind maps, UI, SWOT, etc.) to better understand business-crucial data and offer working solutions to problems. » Business Proposals Apt at presenting solutions with detailed documentation at each stage of the process from business case, RFP, ITT, and requirements statements. Transparency and clarity of written statements has assisted decision- making to be quicker and more effective. v CERTIFICATION Professional in Business Analysis (PMI- PBA)® PMI Certified Business Analysis Professional (CBAP®) IIBA Professional Certificate in Business Analysis BCS Powered by (XZ Enhancy", "metadata": {"filename": "01888170110d1ccf.pdf", "original_category": "Business Analyst", "extraction_method": "ocr"}, "parsed_education": [{"degree": "BS", "institution": null, "years": "2006-2010", "field_of_study": "Investment Management"}], "extracted_skills": ["Google Analytics", "SWOT", "Decision-Making", "Business Analysis", "Salesforce", "Miro", "LEAN", "decision-making"], "parsed_summary": " Senior Business Analyst with 12+ years of", "personal_info": {"phone": "+1-925-885-5155", "first_name": "John", "last_name": "Wood"}}
{"cv_id": "01888170110d1ccf", "target_role": "SAP Developer", "score": 2, "cv_text": "John Wood Senior Business Analyst: Analytical Decision-Making & Growth \\ +1-925-885-5155 help@enhancv.com SUMMARY Senior Business Analyst with 12+ years of experience in using various business intelligence and modelling tools to assess companies' needs and determine sustainable and effective course of action. Trusted by key stakeholders to analyze business problems and opportunities, as a result have increased profit margins by 56%. Ability to analyze day-to-day operations within the big picture of things with a focus on not only achieving individual vision, but forecasting positive outcomes aiming to achieve overall business growth. EXPERIENCE Senior Business Analyst Torphy 8 2017- Ongoing 9 Luling, LA Torphy is a global IT service provider, focused on providing manufacturers with sustainable software to enhance their productivity. + Supported 12+ senior stakeholders in the decision-making process by investigating specific business problems and advising them with flexible, holistic solutions to meet individual business needs + Prepared various risk assessments during M&A negotiations to protect business interests and assure company growth by a 35% AVG + Assessing business model functions with a focus on processes and structures; HR and capital; information and technology to provide solutions to cut back LEAN waste by $450K/ year Business Analyst Dufour &3 2014-2017 9 Baltimore, MD Dufour is one of the largest distributors of digital content, delivering premium content internationally and in multiple formats. + Managed financial forecasts for ten engineering groups with more than $2 million per group + Developed analytical framework to forecast, plan, and model resource allocations across a multi-region call centers resulting in cost savings 20+% - Used various models to forecast revenue and provide solutions to decrease losses and cut LEAN waste by 25% Financial Consultant Lessard 63 2010-2014 9 Boca Raton, LA Lessard offers SMEs financial consultations to help them achieve sustainability and growth with external funding. + Increased company clientele by 6 persons and raised company revenue by over $20,000 in a two-month period + Specialized in designing portfolios for high net worth clients on a team that managed $6 billion in assets - Provided tailored investment advice for clients across 15 states LANGUAGES English Native eeeee Swedish Proficient eeee Japanese enee Proficient www.enhancv.com >linkedin.com =& Luling, LA SKILLS Business Analysis Techniques © MSO Google Analytics Salesforce Miro EDUCATION BS in Investment Management Lynn University @3 2006-2010 9 Boca Raton, LA STRENGTHS Decision-Making Focused on understanding business needs, key stakeholder requirements, and growth demands, to systematize data and navigate the best course ahead. This has impacted business growth with a +$1M in annual revenue. & Information Modelling Tools Using various tools (financial models, product roadmaps, mind maps, UI, SWOT, etc.) to better understand business-crucial data and offer working solutions to problems. » Business Proposals Apt at presenting solutions with detailed documentation at each stage of the process from business case, RFP, ITT, and requirements statements. Transparency and clarity of written statements has assisted decision- making to be quicker and more effective. v CERTIFICATION Professional in Business Analysis (PMI- PBA)® PMI Certified Business Analysis Professional (CBAP®) IIBA Professional Certificate in Business Analysis BCS Powered by (XZ Enhancy", "metadata": {"filename": "01888170110d1ccf.pdf", "original_category": "Business Analyst", "extraction_method": "ocr"}, "parsed_education": [{"degree": "BS", "institution": null, "years": "2006-2010", "field_of_study": "Investment Management"}], "extracted_skills": ["Google Analytics", "SWOT", "Decision-Making", "Business Analysis", "Salesforce", "Miro", "LEAN", "decision-making"], "parsed_summary": " Senior Business Analyst with 12+ years of", "personal_info": {"phone": "+1-925-885-5155", "first_name": "John", "last_name": "Wood"}}
{"cv_id": "01888170110d1ccf", "target_role": "Tester", "score": 0, "cv_text": "John Wood Senior Business Analyst: Analytical Decision-Making & Growth \\ +1-925-885-5155 help@enhancv.com SUMMARY Senior Business Analyst with 12+ years of experience in using various business intelligence and modelling tools to assess companies' needs and determine sustainable and effective course of action. Trusted by key stakeholders to analyze business problems and opportunities, as a result have increased profit margins by 56%. Ability to analyze day-to-day operations within the big picture of things with a focus on not only achieving individual vision, but forecasting positive outcomes aiming to achieve overall business growth. EXPERIENCE Senior Business Analyst Torphy 8 2017- Ongoing 9 Luling, LA Torphy is a global IT service provider, focused on providing manufacturers with sustainable software to enhance their productivity. + Supported 12+ senior stakeholders in the decision-making process by investigating specific business problems and advising them with flexible, holistic solutions to meet individual business needs + Prepared various risk assessments during M&A negotiations to protect business interests and assure company growth by a 35% AVG + Assessing business model functions with a focus on processes and structures; HR and capital; information and technology to provide solutions to cut back LEAN waste by $450K/ year Business Analyst Dufour &3 2014-2017 9 Baltimore, MD Dufour is one of the largest distributors of digital content, delivering premium content internationally and in multiple formats. + Managed financial forecasts for ten engineering groups with more than $2 million per group + Developed analytical framework to forecast, plan, and model resource allocations across a multi-region call centers resulting in cost savings 20+% - Used various models to forecast revenue and provide solutions to decrease losses and cut LEAN waste by 25% Financial Consultant Lessard 63 2010-2014 9 Boca Raton, LA Lessard offers SMEs financial consultations to help them achieve sustainability and growth with external funding. + Increased company clientele by 6 persons and raised company revenue by over $20,000 in a two-month period + Specialized in designing portfolios for high net worth clients on a team that managed $6 billion in assets - Provided tailored investment advice for clients across 15 states LANGUAGES English Native eeeee Swedish Proficient eeee Japanese enee Proficient www.enhancv.com >linkedin.com =& Luling, LA SKILLS Business Analysis Techniques © MSO Google Analytics Salesforce Miro EDUCATION BS in Investment Management Lynn University @3 2006-2010 9 Boca Raton, LA STRENGTHS Decision-Making Focused on understanding business needs, key stakeholder requirements, and growth demands, to systematize data and navigate the best course ahead. This has impacted business growth with a +$1M in annual revenue. & Information Modelling Tools Using various tools (financial models, product roadmaps, mind maps, UI, SWOT, etc.) to better understand business-crucial data and offer working solutions to problems. » Business Proposals Apt at presenting solutions with detailed documentation at each stage of the process from business case, RFP, ITT, and requirements statements. Transparency and clarity of written statements has assisted decision- making to be quicker and more effective. v CERTIFICATION Professional in Business Analysis (PMI- PBA)® PMI Certified Business Analysis Professional (CBAP®) IIBA Professional Certificate in Business Analysis BCS Powered by (XZ Enhancy", "metadata": {"filename": "01888170110d1ccf.pdf", "original_category": "Business Analyst", "extraction_method": "ocr"}, "parsed_education": [{"degree": "BS", "institution": null, "years": "2006-2010", "field_of_study": "Investment Management"}], "extracted_skills": ["Google Analytics", "SWOT", "Decision-Making", "Business Analysis", "Salesforce", "Miro", "LEAN", "decision-making"], "parsed_summary": " Senior Business Analyst with 12+ years of", "personal_info": {"phone": "+1-925-885-5155", "first_name": "John", "last_name": "Wood"}}
{"cv_id": "01946c56a6f1a9d5", "target_role": "Business Analyst", "score": 5, "cv_text": "ORLANDO CAMPA Entry Level Business Analyst: Analyzing Data to Discover Business-Savvy Opportuntiies &% +1-762-136-6290 @help@enhancv.com @ linkedin.com 9 Portland, OR SUMMARY Entry Level Business Analyst making profitable impact by assisting through the whole operational lifecycle - from documentation and analysis to strategizing and decision-making. Customer always comes first mindset to help portfolio clients take the most profitable decisions based on data. Team player, passionate about reaching targets and making a difference in the B2B space. EXPERIENCE Entry Level Business Analyst Nader 2022-Ongoing Portland, OR Nader offers Decentralized Finance B2B solutions across the US. - Helping compliance department with new customer onboarding by verifying that all relevant documents have been submitted for assessment + Supporting the functions of 5 senior business analysts by gathering and organizing customer data in Excel + Participated through the whole operational lifecycle: from planning and strategizing to setting KPIs and analyzing results to ensure profitability of the client investment Sales Team Leader Lessard 2020-2022 Murfreesboro, TN Lessard is one of the largest distributors of digital content, delivering premium content internationally and in multiple formats. + Helped a team of 12 sales professionals always surpass their company targets through the past three years + Monitored up to 20 individual sales calls per day to assess performance and gather customer data in accordance with regulations and policies - Wrote sales scripts to target specific niches, which enhanced the team's performance by 25% Customer Support Representative Rau-Ward 2018-2020 Murfreesboro, TN Rau-Ward is a technology startup, specialized in at-home solutions. + Answered 600+ customer queries by telephone to provide them with helpful information regarding new products + Set up email list with greetings for loyal customers - thus building closer rapport and respecting individual traditions and special days - Had shifts at the complaints department - listened carefully and patiently to all incoming calls (up to 35/day) and tried resolving the client problems TRAINING / COURSES Certified Customer Certified Client Service Experience Professional Specialist Service Institute CSPN Creative Writing Udemy www.enhancv.com SKILLS Administration Powerpoint Business Objectives Strategy MSO Statistics Veracity Consistency EDUCATION Master of Science in Business Oregon State University 2022 - Ongoing Portland, OR BS in Media Management Middle Tennessee State University 2018-2022 Murfreesboro, TN STRENGTHS @ Analytical Decision Making Assisting portfolio clients with investment decisions by creating in-depth analysis of the risk and how it could be minimized. |“ Increased profit margins Within the first six months of my role, assisted the business with data to take crucial decisions regarding portfolio clients. Business profit margins were increased by 45%. \\ Customer Communication Have a strict policy when it comes to working with clients to always respect their individuality, needs and bring full attention to their queries. Focused on always helping them resolve their problems. PASSIONS @ Videography As a media study graduate, video content stayed with me. In my free time, | like to create short- form video content from my travels abroad. & Ardent Reader Have set out to read 365 books through the year - 75% of the task complete. @ Creative Writing Inspired my a course in creative writing, currently halfway through writing my very first detective novel. Powered by (XZ Enhancy", "metadata": {"filename": "01946c56a6f1a9d5.pdf", "original_category": "Business Analyst", "extraction_method": "ocr"}, "parsed_education": [{"degree": "MASTER", "institution": null, "years": "2022", "field_of_study": "Unknown"}, {"degree": "BS", "institution": "Media Management Middle Tennessee State University", "years": "2018-2022", "field_of_study": "Unknown"}], "extracted_skills": ["decision-making", "Powerpoint", "Communication", "Excel"], "parsed_summary": " Entry Level Business Analyst making profitable impact by assisting through the whole operational lifecycle - from documentation and analysis to strategizing and decision-making. Customer always comes first mindset to help portfolio clients take the most profitable decisions based on data. Team player, passionate about reaching targets and making a difference in the B2B space.", "personal_info": {"phone": "+1-762-136-6290", "first_name": null, "last_name": null}}
{"cv_id": "01946c56a6f1a9d5", "target_role": "Data Scientist", "score": 1, "cv_text": "ORLANDO CAMPA Entry Level Business Analyst: Analyzing Data to Discover Business-Savvy Opportuntiies &% +1-762-136-6290 @help@enhancv.com @ linkedin.com 9 Portland, OR SUMMARY Entry Level Business Analyst making profitable impact by assisting through the whole operational lifecycle - from documentation and analysis to strategizing and decision-making. Customer always comes first mindset to help portfolio clients take the most profitable decisions based on data. Team player, passionate about reaching targets and making a difference in the B2B space. EXPERIENCE Entry Level Business Analyst Nader 2022-Ongoing Portland, OR Nader offers Decentralized Finance B2B solutions across the US. - Helping compliance department with new customer onboarding by verifying that all relevant documents have been submitted for assessment + Supporting the functions of 5 senior business analysts by gathering and organizing customer data in Excel + Participated through the whole operational lifecycle: from planning and strategizing to setting KPIs and analyzing results to ensure profitability of the client investment Sales Team Leader Lessard 2020-2022 Murfreesboro, TN Lessard is one of the largest distributors of digital content, delivering premium content internationally and in multiple formats. + Helped a team of 12 sales professionals always surpass their company targets through the past three years + Monitored up to 20 individual sales calls per day to assess performance and gather customer data in accordance with regulations and policies - Wrote sales scripts to target specific niches, which enhanced the team's performance by 25% Customer Support Representative Rau-Ward 2018-2020 Murfreesboro, TN Rau-Ward is a technology startup, specialized in at-home solutions. + Answered 600+ customer queries by telephone to provide them with helpful information regarding new products + Set up email list with greetings for loyal customers - thus building closer rapport and respecting individual traditions and special days - Had shifts at the complaints department - listened carefully and patiently to all incoming calls (up to 35/day) and tried resolving the client problems TRAINING / COURSES Certified Customer Certified Client Service Experience Professional Specialist Service Institute CSPN Creative Writing Udemy www.enhancv.com SKILLS Administration Powerpoint Business Objectives Strategy MSO Statistics Veracity Consistency EDUCATION Master of Science in Business Oregon State University 2022 - Ongoing Portland, OR BS in Media Management Middle Tennessee State University 2018-2022 Murfreesboro, TN STRENGTHS @ Analytical Decision Making Assisting portfolio clients with investment decisions by creating in-depth analysis of the risk and how it could be minimized. |“ Increased profit margins Within the first six months of my role, assisted the business with data to take crucial decisions regarding portfolio clients. Business profit margins were increased by 45%. \\ Customer Communication Have a strict policy when it comes to working with clients to always respect their individuality, needs and bring full attention to their queries. Focused on always helping them resolve their problems. PASSIONS @ Videography As a media study graduate, video content stayed with me. In my free time, | like to create short- form video content from my travels abroad. & Ardent Reader Have set out to read 365 books through the year - 75% of the task complete. @ Creative Writing Inspired my a course in creative writing, currently halfway through writing my very first detective novel. Powered by (XZ Enhancy", "metadata": {"filename": "01946c56a6f1a9d5.pdf", "original_category": "Business Analyst", "extraction_method": "ocr"}, "parsed_education": [{"degree": "MASTER", "institution": null, "years": "2022", "field_of_study": "Unknown"}, {"degree": "BS", "institution": "Media Management Middle Tennessee State University", "years": "2018-2022", "field_of_study": "Unknown"}], "extracted_skills": ["decision-making", "Powerpoint", "Communication", "Excel"], "parsed_summary": " Entry Level Business Analyst making profitable impact by assisting through the whole operational lifecycle - from documentation and analysis to strategizing and decision-making. Customer always comes first mindset to help portfolio clients take the most profitable decisions based on data. Team player, passionate about reaching targets and making a difference in the B2B space.", "personal_info": {"phone": "+1-762-136-6290", "first_name": null, "last_name": null}}
{"cv_id": "01946c56a6f1a9d5", "target_role": "DevOps Engineer", "score": 0, "cv_text": "ORLANDO CAMPA Entry Level Business Analyst: Analyzing Data to Discover Business-Savvy Opportuntiies &% +1-762-136-6290 @help@enhancv.com @ linkedin.com 9 Portland, OR SUMMARY Entry Level Business Analyst making profitable impact by assisting through the whole operational lifecycle - from documentation and analysis to strategizing and decision-making. Customer always comes first mindset to help portfolio clients take the most profitable decisions based on data. Team player, passionate about reaching targets and making a difference in the B2B space. EXPERIENCE Entry Level Business Analyst Nader 2022-Ongoing Portland, OR Nader offers Decentralized Finance B2B solutions across the US. - Helping compliance department with new customer onboarding by verifying that all relevant documents have been submitted for assessment + Supporting the functions of 5 senior business analysts by gathering and organizing customer data in Excel + Participated through the whole operational lifecycle: from planning and strategizing to setting KPIs and analyzing results to ensure profitability of the client investment Sales Team Leader Lessard 2020-2022 Murfreesboro, TN Lessard is one of the largest distributors of digital content, delivering premium content internationally and in multiple formats. + Helped a team of 12 sales professionals always surpass their company targets through the past three years + Monitored up to 20 individual sales calls per day to assess performance and gather customer data in accordance with regulations and policies - Wrote sales scripts to target specific niches, which enhanced the team's performance by 25% Customer Support Representative Rau-Ward 2018-2020 Murfreesboro, TN Rau-Ward is a technology startup, specialized in at-home solutions. + Answered 600+ customer queries by telephone to provide them with helpful information regarding new products + Set up email list with greetings for loyal customers - thus building closer rapport and respecting individual traditions and special days - Had shifts at the complaints department - listened carefully and patiently to all incoming calls (up to 35/day) and tried resolving the client problems TRAINING / COURSES Certified Customer Certified Client Service Experience Professional Specialist Service Institute CSPN Creative Writing Udemy www.enhancv.com SKILLS Administration Powerpoint Business Objectives Strategy MSO Statistics Veracity Consistency EDUCATION Master of Science in Business Oregon State University 2022 - Ongoing Portland, OR BS in Media Management Middle Tennessee State University 2018-2022 Murfreesboro, TN STRENGTHS @ Analytical Decision Making Assisting portfolio clients with investment decisions by creating in-depth analysis of the risk and how it could be minimized. |“ Increased profit margins Within the first six months of my role, assisted the business with data to take crucial decisions regarding portfolio clients. Business profit margins were increased by 45%. \\ Customer Communication Have a strict policy when it comes to working with clients to always respect their individuality, needs and bring full attention to their queries. Focused on always helping them resolve their problems. PASSIONS @ Videography As a media study graduate, video content stayed with me. In my free time, | like to create short- form video content from my travels abroad. & Ardent Reader Have set out to read 365 books through the year - 75% of the task complete. @ Creative Writing Inspired my a course in creative writing, currently halfway through writing my very first detective novel. Powered by (XZ Enhancy", "metadata": {"filename": "01946c56a6f1a9d5.pdf", "original_category": "Business Analyst", "extraction_method": "ocr"}, "parsed_education": [{"degree": "MASTER", "institution": null, "years": "2022", "field_of_study": "Unknown"}, {"degree": "BS", "institution": "Media Management Middle Tennessee State University", "years": "2018-2022", "field_of_study": "Unknown"}], "extracted_skills": ["decision-making", "Powerpoint", "Communication", "Excel"], "parsed_summary": " Entry Level Business Analyst making profitable impact by assisting through the whole operational lifecycle - from documentation and analysis to strategizing and decision-making. Customer always comes first mindset to help portfolio clients take the most profitable decisions based on data. Team player, passionate about reaching targets and making a difference in the B2B space.", "personal_info": {"phone": "+1-762-136-6290", "first_name": null, "last_name": null}}
{"cv_id": "01946c56a6f1a9d5", "target_role": "ETL Developer", "score": 0, "cv_text": "ORLANDO CAMPA Entry Level Business Analyst: Analyzing Data to Discover Business-Savvy Opportuntiies &% +1-762-136-6290 @help@enhancv.com @ linkedin.com 9 Portland, OR SUMMARY Entry Level Business Analyst making profitable impact by assisting through the whole operational lifecycle - from documentation and analysis to strategizing and decision-making. Customer always comes first mindset to help portfolio clients take the most profitable decisions based on data. Team player, passionate about reaching targets and making a difference in the B2B space. EXPERIENCE Entry Level Business Analyst Nader 2022-Ongoing Portland, OR Nader offers Decentralized Finance B2B solutions across the US. - Helping compliance department with new customer onboarding by verifying that all relevant documents have been submitted for assessment + Supporting the functions of 5 senior business analysts by gathering and organizing customer data in Excel + Participated through the whole operational lifecycle: from planning and strategizing to setting KPIs and analyzing results to ensure profitability of the client investment Sales Team Leader Lessard 2020-2022 Murfreesboro, TN Lessard is one of the largest distributors of digital content, delivering premium content internationally and in multiple formats. + Helped a team of 12 sales professionals always surpass their company targets through the past three years + Monitored up to 20 individual sales calls per day to assess performance and gather customer data in accordance with regulations and policies - Wrote sales scripts to target specific niches, which enhanced the team's performance by 25% Customer Support Representative Rau-Ward 2018-2020 Murfreesboro, TN Rau-Ward is a technology startup, specialized in at-home solutions. + Answered 600+ customer queries by telephone to provide them with helpful information regarding new products + Set up email list with greetings for loyal customers - thus building closer rapport and respecting individual traditions and special days - Had shifts at the complaints department - listened carefully and patiently to all incoming calls (up to 35/day) and tried resolving the client problems TRAINING / COURSES Certified Customer Certified Client Service Experience Professional Specialist Service Institute CSPN Creative Writing Udemy www.enhancv.com SKILLS Administration Powerpoint Business Objectives Strategy MSO Statistics Veracity Consistency EDUCATION Master of Science in Business Oregon State University 2022 - Ongoing Portland, OR BS in Media Management Middle Tennessee State University 2018-2022 Murfreesboro, TN STRENGTHS @ Analytical Decision Making Assisting portfolio clients with investment decisions by creating in-depth analysis of the risk and how it could be minimized. |“ Increased profit margins Within the first six months of my role, assisted the business with data to take crucial decisions regarding portfolio clients. Business profit margins were increased by 45%. \\ Customer Communication Have a strict policy when it comes to working with clients to always respect their individuality, needs and bring full attention to their queries. Focused on always helping them resolve their problems. PASSIONS @ Videography As a media study graduate, video content stayed with me. In my free time, | like to create short- form video content from my travels abroad. & Ardent Reader Have set out to read 365 books through the year - 75% of the task complete. @ Creative Writing Inspired my a course in creative writing, currently halfway through writing my very first detective novel. Powered by (XZ Enhancy", "metadata": {"filename": "01946c56a6f1a9d5.pdf", "original_category": "Business Analyst", "extraction_method": "ocr"}, "parsed_education": [{"degree": "MASTER", "institution": null, "years": "2022", "field_of_study": "Unknown"}, {"degree": "BS", "institution": "Media Management Middle Tennessee State University", "years": "2018-2022", "field_of_study": "Unknown"}], "extracted_skills": ["decision-making", "Powerpoint", "Communication", "Excel"], "parsed_summary": " Entry Level Business Analyst making profitable impact by assisting through the whole operational lifecycle - from documentation and analysis to strategizing and decision-making. Customer always comes first mindset to help portfolio clients take the most profitable decisions based on data. Team player, passionate about reaching targets and making a difference in the B2B space.", "personal_info": {"phone": "+1-762-136-6290", "first_name": null, "last_name": null}}
{"cv_id": "01946c56a6f1a9d5", "target_role": "Java Developer", "score": 0, "cv_text": "ORLANDO CAMPA Entry Level Business Analyst: Analyzing Data to Discover Business-Savvy Opportuntiies &% +1-762-136-6290 @help@enhancv.com @ linkedin.com 9 Portland, OR SUMMARY Entry Level Business Analyst making profitable impact by assisting through the whole operational lifecycle - from documentation and analysis to strategizing and decision-making. Customer always comes first mindset to help portfolio clients take the most profitable decisions based on data. Team player, passionate about reaching targets and making a difference in the B2B space. EXPERIENCE Entry Level Business Analyst Nader 2022-Ongoing Portland, OR Nader offers Decentralized Finance B2B solutions across the US. - Helping compliance department with new customer onboarding by verifying that all relevant documents have been submitted for assessment + Supporting the functions of 5 senior business analysts by gathering and organizing customer data in Excel + Participated through the whole operational lifecycle: from planning and strategizing to setting KPIs and analyzing results to ensure profitability of the client investment Sales Team Leader Lessard 2020-2022 Murfreesboro, TN Lessard is one of the largest distributors of digital content, delivering premium content internationally and in multiple formats. + Helped a team of 12 sales professionals always surpass their company targets through the past three years + Monitored up to 20 individual sales calls per day to assess performance and gather customer data in accordance with regulations and policies - Wrote sales scripts to target specific niches, which enhanced the team's performance by 25% Customer Support Representative Rau-Ward 2018-2020 Murfreesboro, TN Rau-Ward is a technology startup, specialized in at-home solutions. + Answered 600+ customer queries by telephone to provide them with helpful information regarding new products + Set up email list with greetings for loyal customers - thus building closer rapport and respecting individual traditions and special days - Had shifts at the complaints department - listened carefully and patiently to all incoming calls (up to 35/day) and tried resolving the client problems TRAINING / COURSES Certified Customer Certified Client Service Experience Professional Specialist Service Institute CSPN Creative Writing Udemy www.enhancv.com SKILLS Administration Powerpoint Business Objectives Strategy MSO Statistics Veracity Consistency EDUCATION Master of Science in Business Oregon State University 2022 - Ongoing Portland, OR BS in Media Management Middle Tennessee State University 2018-2022 Murfreesboro, TN STRENGTHS @ Analytical Decision Making Assisting portfolio clients with investment decisions by creating in-depth analysis of the risk and how it could be minimized. |“ Increased profit margins Within the first six months of my role, assisted the business with data to take crucial decisions regarding portfolio clients. Business profit margins were increased by 45%. \\ Customer Communication Have a strict policy when it comes to working with clients to always respect their individuality, needs and bring full attention to their queries. Focused on always helping them resolve their problems. PASSIONS @ Videography As a media study graduate, video content stayed with me. In my free time, | like to create short- form video content from my travels abroad. & Ardent Reader Have set out to read 365 books through the year - 75% of the task complete. @ Creative Writing Inspired my a course in creative writing, currently halfway through writing my very first detective novel. Powered by (XZ Enhancy", "metadata": {"filename": "01946c56a6f1a9d5.pdf", "original_category": "Business Analyst", "extraction_method": "ocr"}, "parsed_education": [{"degree": "MASTER", "institution": null, "years": "2022", "field_of_study": "Unknown"}, {"degree": "BS", "institution": "Media Management Middle Tennessee State University", "years": "2018-2022", "field_of_study": "Unknown"}], "extracted_skills": ["decision-making", "Powerpoint", "Communication", "Excel"], "parsed_summary": " Entry Level Business Analyst making profitable impact by assisting through the whole operational lifecycle - from documentation and analysis to strategizing and decision-making. Customer always comes first mindset to help portfolio clients take the most profitable decisions based on data. Team player, passionate about reaching targets and making a difference in the B2B space.", "personal_info": {"phone": "+1-762-136-6290", "first_name": null, "last_name": null}}
{"cv_id": "01946c56a6f1a9d5", "target_role": "Python Developer", "score": 0, "cv_text": "ORLANDO CAMPA Entry Level Business Analyst: Analyzing Data to Discover Business-Savvy Opportuntiies &% +1-762-136-6290 @help@enhancv.com @ linkedin.com 9 Portland, OR SUMMARY Entry Level Business Analyst making profitable impact by assisting through the whole operational lifecycle - from documentation and analysis to strategizing and decision-making. Customer always comes first mindset to help portfolio clients take the most profitable decisions based on data. Team player, passionate about reaching targets and making a difference in the B2B space. EXPERIENCE Entry Level Business Analyst Nader 2022-Ongoing Portland, OR Nader offers Decentralized Finance B2B solutions across the US. - Helping compliance department with new customer onboarding by verifying that all relevant documents have been submitted for assessment + Supporting the functions of 5 senior business analysts by gathering and organizing customer data in Excel + Participated through the whole operational lifecycle: from planning and strategizing to setting KPIs and analyzing results to ensure profitability of the client investment Sales Team Leader Lessard 2020-2022 Murfreesboro, TN Lessard is one of the largest distributors of digital content, delivering premium content internationally and in multiple formats. + Helped a team of 12 sales professionals always surpass their company targets through the past three years + Monitored up to 20 individual sales calls per day to assess performance and gather customer data in accordance with regulations and policies - Wrote sales scripts to target specific niches, which enhanced the team's performance by 25% Customer Support Representative Rau-Ward 2018-2020 Murfreesboro, TN Rau-Ward is a technology startup, specialized in at-home solutions. + Answered 600+ customer queries by telephone to provide them with helpful information regarding new products + Set up email list with greetings for loyal customers - thus building closer rapport and respecting individual traditions and special days - Had shifts at the complaints department - listened carefully and patiently to all incoming calls (up to 35/day) and tried resolving the client problems TRAINING / COURSES Certified Customer Certified Client Service Experience Professional Specialist Service Institute CSPN Creative Writing Udemy www.enhancv.com SKILLS Administration Powerpoint Business Objectives Strategy MSO Statistics Veracity Consistency EDUCATION Master of Science in Business Oregon State University 2022 - Ongoing Portland, OR BS in Media Management Middle Tennessee State University 2018-2022 Murfreesboro, TN STRENGTHS @ Analytical Decision Making Assisting portfolio clients with investment decisions by creating in-depth analysis of the risk and how it could be minimized. |“ Increased profit margins Within the first six months of my role, assisted the business with data to take crucial decisions regarding portfolio clients. Business profit margins were increased by 45%. \\ Customer Communication Have a strict policy when it comes to working with clients to always respect their individuality, needs and bring full attention to their queries. Focused on always helping them resolve their problems. PASSIONS @ Videography As a media study graduate, video content stayed with me. In my free time, | like to create short- form video content from my travels abroad. & Ardent Reader Have set out to read 365 books through the year - 75% of the task complete. @ Creative Writing Inspired my a course in creative writing, currently halfway through writing my very first detective novel. Powered by (XZ Enhancy", "metadata": {"filename": "01946c56a6f1a9d5.pdf", "original_category": "Business Analyst", "extraction_method": "ocr"}, "parsed_education": [{"degree": "MASTER", "institution": null, "years": "2022", "field_of_study": "Unknown"}, {"degree": "BS", "institution": "Media Management Middle Tennessee State University", "years": "2018-2022", "field_of_study": "Unknown"}], "extracted_skills": ["decision-making", "Powerpoint", "Communication", "Excel"], "parsed_summary": " Entry Level Business Analyst making profitable impact by assisting through the whole operational lifecycle - from documentation and analysis to strategizing and decision-making. Customer always comes first mindset to help portfolio clients take the most profitable decisions based on data. Team player, passionate about reaching targets and making a difference in the B2B space.", "personal_info": {"phone": "+1-762-136-6290", "first_name": null, "last_name": null}}
{"cv_id": "01946c56a6f1a9d5", "target_role": "React Developer", "score": 0, "cv_text": "ORLANDO CAMPA Entry Level Business Analyst: Analyzing Data to Discover Business-Savvy Opportuntiies &% +1-762-136-6290 @help@enhancv.com @ linkedin.com 9 Portland, OR SUMMARY Entry Level Business Analyst making profitable impact by assisting through the whole operational lifecycle - from documentation and analysis to strategizing and decision-making. Customer always comes first mindset to help portfolio clients take the most profitable decisions based on data. Team player, passionate about reaching targets and making a difference in the B2B space. EXPERIENCE Entry Level Business Analyst Nader 2022-Ongoing Portland, OR Nader offers Decentralized Finance B2B solutions across the US. - Helping compliance department with new customer onboarding by verifying that all relevant documents have been submitted for assessment + Supporting the functions of 5 senior business analysts by gathering and organizing customer data in Excel + Participated through the whole operational lifecycle: from planning and strategizing to setting KPIs and analyzing results to ensure profitability of the client investment Sales Team Leader Lessard 2020-2022 Murfreesboro, TN Lessard is one of the largest distributors of digital content, delivering premium content internationally and in multiple formats. + Helped a team of 12 sales professionals always surpass their company targets through the past three years + Monitored up to 20 individual sales calls per day to assess performance and gather customer data in accordance with regulations and policies - Wrote sales scripts to target specific niches, which enhanced the team's performance by 25% Customer Support Representative Rau-Ward 2018-2020 Murfreesboro, TN Rau-Ward is a technology startup, specialized in at-home solutions. + Answered 600+ customer queries by telephone to provide them with helpful information regarding new products + Set up email list with greetings for loyal customers - thus building closer rapport and respecting individual traditions and special days - Had shifts at the complaints department - listened carefully and patiently to all incoming calls (up to 35/day) and tried resolving the client problems TRAINING / COURSES Certified Customer Certified Client Service Experience Professional Specialist Service Institute CSPN Creative Writing Udemy www.enhancv.com SKILLS Administration Powerpoint Business Objectives Strategy MSO Statistics Veracity Consistency EDUCATION Master of Science in Business Oregon State University 2022 - Ongoing Portland, OR BS in Media Management Middle Tennessee State University 2018-2022 Murfreesboro, TN STRENGTHS @ Analytical Decision Making Assisting portfolio clients with investment decisions by creating in-depth analysis of the risk and how it could be minimized. |“ Increased profit margins Within the first six months of my role, assisted the business with data to take crucial decisions regarding portfolio clients. Business profit margins were increased by 45%. \\ Customer Communication Have a strict policy when it comes to working with clients to always respect their individuality, needs and bring full attention to their queries. Focused on always helping them resolve their problems. PASSIONS @ Videography As a media study graduate, video content stayed with me. In my free time, | like to create short- form video content from my travels abroad. & Ardent Reader Have set out to read 365 books through the year - 75% of the task complete. @ Creative Writing Inspired my a course in creative writing, currently halfway through writing my very first detective novel. Powered by (XZ Enhancy", "metadata": {"filename": "01946c56a6f1a9d5.pdf", "original_category": "Business Analyst", "extraction_method": "ocr"}, "parsed_education": [{"degree": "MASTER", "institution": null, "years": "2022", "field_of_study": "Unknown"}, {"degree": "BS", "institution": "Media Management Middle Tennessee State University", "years": "2018-2022", "field_of_study": "Unknown"}], "extracted_skills": ["decision-making", "Powerpoint", "Communication", "Excel"], "parsed_summary": " Entry Level Business Analyst making profitable impact by assisting through the whole operational lifecycle - from documentation and analysis to strategizing and decision-making. Customer always comes first mindset to help portfolio clients take the most profitable decisions based on data. Team player, passionate about reaching targets and making a difference in the B2B space.", "personal_info": {"phone": "+1-762-136-6290", "first_name": null, "last_name": null}}
{"cv_id": "01946c56a6f1a9d5", "target_role": "SQL Developer", "score": 2, "cv_text": "ORLANDO CAMPA Entry Level Business Analyst: Analyzing Data to Discover Business-Savvy Opportuntiies &% +1-762-136-6290 @help@enhancv.com @ linkedin.com 9 Portland, OR SUMMARY Entry Level Business Analyst making profitable impact by assisting through the whole operational lifecycle - from documentation and analysis to strategizing and decision-making. Customer always comes first mindset to help portfolio clients take the most profitable decisions based on data. Team player, passionate about reaching targets and making a difference in the B2B space. EXPERIENCE Entry Level Business Analyst Nader 2022-Ongoing Portland, OR Nader offers Decentralized Finance B2B solutions across the US. - Helping compliance department with new customer onboarding by verifying that all relevant documents have been submitted for assessment + Supporting the functions of 5 senior business analysts by gathering and organizing customer data in Excel + Participated through the whole operational lifecycle: from planning and strategizing to setting KPIs and analyzing results to ensure profitability of the client investment Sales Team Leader Lessard 2020-2022 Murfreesboro, TN Lessard is one of the largest distributors of digital content, delivering premium content internationally and in multiple formats. + Helped a team of 12 sales professionals always surpass their company targets through the past three years + Monitored up to 20 individual sales calls per day to assess performance and gather customer data in accordance with regulations and policies - Wrote sales scripts to target specific niches, which enhanced the team's performance by 25% Customer Support Representative Rau-Ward 2018-2020 Murfreesboro, TN Rau-Ward is a technology startup, specialized in at-home solutions. + Answered 600+ customer queries by telephone to provide them with helpful information regarding new products + Set up email list with greetings for loyal customers - thus building closer rapport and respecting individual traditions and special days - Had shifts at the complaints department - listened carefully and patiently to all incoming calls (up to 35/day) and tried resolving the client problems TRAINING / COURSES Certified Customer Certified Client Service Experience Professional Specialist Service Institute CSPN Creative Writing Udemy www.enhancv.com SKILLS Administration Powerpoint Business Objectives Strategy MSO Statistics Veracity Consistency EDUCATION Master of Science in Business Oregon State University 2022 - Ongoing Portland, OR BS in Media Management Middle Tennessee State University 2018-2022 Murfreesboro, TN STRENGTHS @ Analytical Decision Making Assisting portfolio clients with investment decisions by creating in-depth analysis of the risk and how it could be minimized. |“ Increased profit margins Within the first six months of my role, assisted the business with data to take crucial decisions regarding portfolio clients. Business profit margins were increased by 45%. \\ Customer Communication Have a strict policy when it comes to working with clients to always respect their individuality, needs and bring full attention to their queries. Focused on always helping them resolve their problems. PASSIONS @ Videography As a media study graduate, video content stayed with me. In my free time, | like to create short- form video content from my travels abroad. & Ardent Reader Have set out to read 365 books through the year - 75% of the task complete. @ Creative Writing Inspired my a course in creative writing, currently halfway through writing my very first detective novel. Powered by (XZ Enhancy", "metadata": {"filename": "01946c56a6f1a9d5.pdf", "original_category": "Business Analyst", "extraction_method": "ocr"}, "parsed_education": [{"degree": "MASTER", "institution": null, "years": "2022", "field_of_study": "Unknown"}, {"degree": "BS", "institution": "Media Management Middle Tennessee State University", "years": "2018-2022", "field_of_study": "Unknown"}], "extracted_skills": ["decision-making", "Powerpoint", "Communication", "Excel"], "parsed_summary": " Entry Level Business Analyst making profitable impact by assisting through the whole operational lifecycle - from documentation and analysis to strategizing and decision-making. Customer always comes first mindset to help portfolio clients take the most profitable decisions based on data. Team player, passionate about reaching targets and making a difference in the B2B space.", "personal_info": {"phone": "+1-762-136-6290", "first_name": null, "last_name": null}}
{"cv_id": "01946c56a6f1a9d5", "target_role": "Web Developer", "score": 0, "cv_text": "ORLANDO CAMPA Entry Level Business Analyst: Analyzing Data to Discover Business-Savvy Opportuntiies &% +1-762-136-6290 @help@enhancv.com @ linkedin.com 9 Portland, OR SUMMARY Entry Level Business Analyst making profitable impact by assisting through the whole operational lifecycle - from documentation and analysis to strategizing and decision-making. Customer always comes first mindset to help portfolio clients take the most profitable decisions based on data. Team player, passionate about reaching targets and making a difference in the B2B space. EXPERIENCE Entry Level Business Analyst Nader 2022-Ongoing Portland, OR Nader offers Decentralized Finance B2B solutions across the US. - Helping compliance department with new customer onboarding by verifying that all relevant documents have been submitted for assessment + Supporting the functions of 5 senior business analysts by gathering and organizing customer data in Excel + Participated through the whole operational lifecycle: from planning and strategizing to setting KPIs and analyzing results to ensure profitability of the client investment Sales Team Leader Lessard 2020-2022 Murfreesboro, TN Lessard is one of the largest distributors of digital content, delivering premium content internationally and in multiple formats. + Helped a team of 12 sales professionals always surpass their company targets through the past three years + Monitored up to 20 individual sales calls per day to assess performance and gather customer data in accordance with regulations and policies - Wrote sales scripts to target specific niches, which enhanced the team's performance by 25% Customer Support Representative Rau-Ward 2018-2020 Murfreesboro, TN Rau-Ward is a technology startup, specialized in at-home solutions. + Answered 600+ customer queries by telephone to provide them with helpful information regarding new products + Set up email list with greetings for loyal customers - thus building closer rapport and respecting individual traditions and special days - Had shifts at the complaints department - listened carefully and patiently to all incoming calls (up to 35/day) and tried resolving the client problems TRAINING / COURSES Certified Customer Certified Client Service Experience Professional Specialist Service Institute CSPN Creative Writing Udemy www.enhancv.com SKILLS Administration Powerpoint Business Objectives Strategy MSO Statistics Veracity Consistency EDUCATION Master of Science in Business Oregon State University 2022 - Ongoing Portland, OR BS in Media Management Middle Tennessee State University 2018-2022 Murfreesboro, TN STRENGTHS @ Analytical Decision Making Assisting portfolio clients with investment decisions by creating in-depth analysis of the risk and how it could be minimized. |“ Increased profit margins Within the first six months of my role, assisted the business with data to take crucial decisions regarding portfolio clients. Business profit margins were increased by 45%. \\ Customer Communication Have a strict policy when it comes to working with clients to always respect their individuality, needs and bring full attention to their queries. Focused on always helping them resolve their problems. PASSIONS @ Videography As a media study graduate, video content stayed with me. In my free time, | like to create short- form video content from my travels abroad. & Ardent Reader Have set out to read 365 books through the year - 75% of the task complete. @ Creative Writing Inspired my a course in creative writing, currently halfway through writing my very first detective novel. Powered by (XZ Enhancy", "metadata": {"filename": "01946c56a6f1a9d5.pdf", "original_category": "Business Analyst", "extraction_method": "ocr"}, "parsed_education": [{"degree": "MASTER", "institution": null, "years": "2022", "field_of_study": "Unknown"}, {"degree": "BS", "institution": "Media Management Middle Tennessee State University", "years": "2018-2022", "field_of_study": "Unknown"}], "extracted_skills": ["decision-making", "Powerpoint", "Communication", "Excel"], "parsed_summary": " Entry Level Business Analyst making profitable impact by assisting through the whole operational lifecycle - from documentation and analysis to strategizing and decision-making. Customer always comes first mindset to help portfolio clients take the most profitable decisions based on data. Team player, passionate about reaching targets and making a difference in the B2B space.", "personal_info": {"phone": "+1-762-136-6290", "first_name": null, "last_name": null}}
{"cv_id": "01946c56a6f1a9d5", "target_role": "SAP Developer", "score": 2, "cv_text": "ORLANDO CAMPA Entry Level Business Analyst: Analyzing Data to Discover Business-Savvy Opportuntiies &% +1-762-136-6290 @help@enhancv.com @ linkedin.com 9 Portland, OR SUMMARY Entry Level Business Analyst making profitable impact by assisting through the whole operational lifecycle - from documentation and analysis to strategizing and decision-making. Customer always comes first mindset to help portfolio clients take the most profitable decisions based on data. Team player, passionate about reaching targets and making a difference in the B2B space. EXPERIENCE Entry Level Business Analyst Nader 2022-Ongoing Portland, OR Nader offers Decentralized Finance B2B solutions across the US. - Helping compliance department with new customer onboarding by verifying that all relevant documents have been submitted for assessment + Supporting the functions of 5 senior business analysts by gathering and organizing customer data in Excel + Participated through the whole operational lifecycle: from planning and strategizing to setting KPIs and analyzing results to ensure profitability of the client investment Sales Team Leader Lessard 2020-2022 Murfreesboro, TN Lessard is one of the largest distributors of digital content, delivering premium content internationally and in multiple formats. + Helped a team of 12 sales professionals always surpass their company targets through the past three years + Monitored up to 20 individual sales calls per day to assess performance and gather customer data in accordance with regulations and policies - Wrote sales scripts to target specific niches, which enhanced the team's performance by 25% Customer Support Representative Rau-Ward 2018-2020 Murfreesboro, TN Rau-Ward is a technology startup, specialized in at-home solutions. + Answered 600+ customer queries by telephone to provide them with helpful information regarding new products + Set up email list with greetings for loyal customers - thus building closer rapport and respecting individual traditions and special days - Had shifts at the complaints department - listened carefully and patiently to all incoming calls (up to 35/day) and tried resolving the client problems TRAINING / COURSES Certified Customer Certified Client Service Experience Professional Specialist Service Institute CSPN Creative Writing Udemy www.enhancv.com SKILLS Administration Powerpoint Business Objectives Strategy MSO Statistics Veracity Consistency EDUCATION Master of Science in Business Oregon State University 2022 - Ongoing Portland, OR BS in Media Management Middle Tennessee State University 2018-2022 Murfreesboro, TN STRENGTHS @ Analytical Decision Making Assisting portfolio clients with investment decisions by creating in-depth analysis of the risk and how it could be minimized. |“ Increased profit margins Within the first six months of my role, assisted the business with data to take crucial decisions regarding portfolio clients. Business profit margins were increased by 45%. \\ Customer Communication Have a strict policy when it comes to working with clients to always respect their individuality, needs and bring full attention to their queries. Focused on always helping them resolve their problems. PASSIONS @ Videography As a media study graduate, video content stayed with me. In my free time, | like to create short- form video content from my travels abroad. & Ardent Reader Have set out to read 365 books through the year - 75% of the task complete. @ Creative Writing Inspired my a course in creative writing, currently halfway through writing my very first detective novel. Powered by (XZ Enhancy", "metadata": {"filename": "01946c56a6f1a9d5.pdf", "original_category": "Business Analyst", "extraction_method": "ocr"}, "parsed_education": [{"degree": "MASTER", "institution": null, "years": "2022", "field_of_study": "Unknown"}, {"degree": "BS", "institution": "Media Management Middle Tennessee State University", "years": "2018-2022", "field_of_study": "Unknown"}], "extracted_skills": ["decision-making", "Powerpoint", "Communication", "Excel"], "parsed_summary": " Entry Level Business Analyst making profitable impact by assisting through the whole operational lifecycle - from documentation and analysis to strategizing and decision-making. Customer always comes first mindset to help portfolio clients take the most profitable decisions based on data. Team player, passionate about reaching targets and making a difference in the B2B space.", "personal_info": {"phone": "+1-762-136-6290", "first_name": null, "last_name": null}}
{"cv_id": "01946c56a6f1a9d5", "target_role": "Tester", "score": 0, "cv_text": "ORLANDO CAMPA Entry Level Business Analyst: Analyzing Data to Discover Business-Savvy Opportuntiies &% +1-762-136-6290 @help@enhancv.com @ linkedin.com 9 Portland, OR SUMMARY Entry Level Business Analyst making profitable impact by assisting through the whole operational lifecycle - from documentation and analysis to strategizing and decision-making. Customer always comes first mindset to help portfolio clients take the most profitable decisions based on data. Team player, passionate about reaching targets and making a difference in the B2B space. EXPERIENCE Entry Level Business Analyst Nader 2022-Ongoing Portland, OR Nader offers Decentralized Finance B2B solutions across the US. - Helping compliance department with new customer onboarding by verifying that all relevant documents have been submitted for assessment + Supporting the functions of 5 senior business analysts by gathering and organizing customer data in Excel + Participated through the whole operational lifecycle: from planning and strategizing to setting KPIs and analyzing results to ensure profitability of the client investment Sales Team Leader Lessard 2020-2022 Murfreesboro, TN Lessard is one of the largest distributors of digital content, delivering premium content internationally and in multiple formats. + Helped a team of 12 sales professionals always surpass their company targets through the past three years + Monitored up to 20 individual sales calls per day to assess performance and gather customer data in accordance with regulations and policies - Wrote sales scripts to target specific niches, which enhanced the team's performance by 25% Customer Support Representative Rau-Ward 2018-2020 Murfreesboro, TN Rau-Ward is a technology startup, specialized in at-home solutions. + Answered 600+ customer queries by telephone to provide them with helpful information regarding new products + Set up email list with greetings for loyal customers - thus building closer rapport and respecting individual traditions and special days - Had shifts at the complaints department - listened carefully and patiently to all incoming calls (up to 35/day) and tried resolving the client problems TRAINING / COURSES Certified Customer Certified Client Service Experience Professional Specialist Service Institute CSPN Creative Writing Udemy www.enhancv.com SKILLS Administration Powerpoint Business Objectives Strategy MSO Statistics Veracity Consistency EDUCATION Master of Science in Business Oregon State University 2022 - Ongoing Portland, OR BS in Media Management Middle Tennessee State University 2018-2022 Murfreesboro, TN STRENGTHS @ Analytical Decision Making Assisting portfolio clients with investment decisions by creating in-depth analysis of the risk and how it could be minimized. |“ Increased profit margins Within the first six months of my role, assisted the business with data to take crucial decisions regarding portfolio clients. Business profit margins were increased by 45%. \\ Customer Communication Have a strict policy when it comes to working with clients to always respect their individuality, needs and bring full attention to their queries. Focused on always helping them resolve their problems. PASSIONS @ Videography As a media study graduate, video content stayed with me. In my free time, | like to create short- form video content from my travels abroad. & Ardent Reader Have set out to read 365 books through the year - 75% of the task complete. @ Creative Writing Inspired my a course in creative writing, currently halfway through writing my very first detective novel. Powered by (XZ Enhancy", "metadata": {"filename": "01946c56a6f1a9d5.pdf", "original_category": "Business Analyst", "extraction_method": "ocr"}, "parsed_education": [{"degree": "MASTER", "institution": null, "years": "2022", "field_of_study": "Unknown"}, {"degree": "BS", "institution": "Media Management Middle Tennessee State University", "years": "2018-2022", "field_of_study": "Unknown"}], "extracted_skills": ["decision-making", "Powerpoint", "Communication", "Excel"], "parsed_summary": " Entry Level Business Analyst making profitable impact by assisting through the whole operational lifecycle - from documentation and analysis to strategizing and decision-making. Customer always comes first mindset to help portfolio clients take the most profitable decisions based on data. Team player, passionate about reaching targets and making a difference in the B2B space.", "personal_info": {"phone": "+1-762-136-6290", "first_name": null, "last_name": null}}
{"cv_id": "02a87605b8841c0f", "target_role": "Business Analyst", "score": 5, "cv_text": "Summary Business Analyst experienced in supporting analytical needs of organizations with prior project/product management experience. Result- oriented individual recognized for effectively resolving challenging issues aspiring to become an Analytics expert. Work Experience = ANALYST [| Extracted data from Sabre, Duetto, and Google Analytics into MS Excel, implemented advanced functionalities like Pivot Tables, VLOOKUP, and Macros to perform data analysis for business; impacting insights & making recommendations. Used predictive analysis to predict the number of guests for any given night to maximize occupancy and increase revenue. Documented monthly e-commerce performance reports in MS Word and created MS PowerPoint presentations for higher management. * Defined KPI and metrics to measure business's success. © Part of diverse, cross-functional teams working towards fulfillment of corporate goals and productivity. Implemented SQL queries using joins and sub queries to retrieve data from the database. prowect MANAGER-INTERN | © = =Managed project requirements using JIRA and Confluence. © = Collected, cleaned, and analyzed data using IFTTT, WeWiredWeb, and MS Excel using functions like Pivot Tables and graphs. © Created mockups and wireframes; documented use cases, activity diagrams, sequence diagrams, and workflow. © = Analyzed and reviewed developer Python and HTML codes. © =©Prepared and executed test plans including documenting and resolving issues. . Documented Business Requirement Documents (BRDs) and Functional Requirement Documents (FRDs). atcat MANAGER-INTERN | Implemented advanced MS Excel functionalities like VLOOKUP, Pivot Tables to forecast revenue based on historical data. © Analyzed old detection cases using JIRA tickets and Salesforce to determine which products have maximum False/True Positives and False/True Negatives. Conducted market analysis and research on other threat intelligence companies to see how they differ from each other. Created innovation games to help engineers decide product features. Coordinated with Product Manager to gather requirements and make modifications and corrections to the product specific documents. Certifications * Scrum Fundamentals Certified (April, 2016) © Microsoft Project 2016: Essential Training (February, 2016) * Hootsuite Certificate Courseware (October, 2015) * IBM DB2 Database and Application Fundamentals (October, 2013) Technical Skills * Database: Oracle 91, MySOL * Software/Tools: VB, MS Visio, Tableau, MS Project Professional, Salesforce, SharePoint Education (MAY, 2016) MS INFORMATION SYSTEMS-BUSINESS ANALYTICS (AUGUST, 2013) BE INFORMATION TECHNOLOGY Academic Projects ANALYTICS PROJECT (2016) e Used regression analysis, Tableau, and forecasting to conclude which states in US should stop the production of GE crops, soil damage, and which crops can be excluded from being produced genetically. DATA WAREHOUSING FOR (2015) © Offered a system design solution to a start-up based on requirements of and data provided by the company. Proposed a data warehouse management plan to manage inventory, sales, and customer data in order to help in day-to-day operations. The plan included gathering requirements, choosing KPI, data quality and data sources analysis, dimensional modeling, ETL system requirements, and budgeting. SUPPLY CHAIN MANAGEMENT FOR [J CONSTRUCTIONS PVT. LTD. (2015) * Analyzed operations data to propose a business plan using advanced MS Excel functions like VLOOKUP, Pivot tables, and linear regression. Aimed at improving overhead costs and improved the profit margin of the company by 1.5% per project.", "metadata": {"filename": "02a87605b8841c0f.pdf", "original_category": "Business Analyst", "extraction_method": "ocr"}, "parsed_education": [{"degree": "MS", "institution": null, "years": "2016", "field_of_study": "Information Systems"}, {"degree": "MS", "institution": null, "years": "2015", "field_of_study": "Unknown"}], "extracted_skills": ["Confluence", "Python", "SQL", "Google Analytics", "JIRA", "Excel", "PowerPoint", "Visio", "SharePoint", "Salesforce", "Scrum", "teams", "HTML", "Tableau", "Word", "Oracle"], "parsed_summary": " Business Analyst experienced in supporting analytical needs of organizations with prior project/product management", "personal_info": {"phone": null, "first_name": "Pivot", "last_name": "Tables"}}
{"cv_id": "02a87605b8841c0f", "target_role": "Data Scientist", "score": 1, "cv_text": "Summary Business Analyst experienced in supporting analytical needs of organizations with prior project/product management experience. Result- oriented individual recognized for effectively resolving challenging issues aspiring to become an Analytics expert. Work Experience = ANALYST [| Extracted data from Sabre, Duetto, and Google Analytics into MS Excel, implemented advanced functionalities like Pivot Tables, VLOOKUP, and Macros to perform data analysis for business; impacting insights & making recommendations. Used predictive analysis to predict the number of guests for any given night to maximize occupancy and increase revenue. Documented monthly e-commerce performance reports in MS Word and created MS PowerPoint presentations for higher management. * Defined KPI and metrics to measure business's success. © Part of diverse, cross-functional teams working towards fulfillment of corporate goals and productivity. Implemented SQL queries using joins and sub queries to retrieve data from the database. prowect MANAGER-INTERN | © = =Managed project requirements using JIRA and Confluence. © = Collected, cleaned, and analyzed data using IFTTT, WeWiredWeb, and MS Excel using functions like Pivot Tables and graphs. © Created mockups and wireframes; documented use cases, activity diagrams, sequence diagrams, and workflow. © = Analyzed and reviewed developer Python and HTML codes. © =©Prepared and executed test plans including documenting and resolving issues. . Documented Business Requirement Documents (BRDs) and Functional Requirement Documents (FRDs). atcat MANAGER-INTERN | Implemented advanced MS Excel functionalities like VLOOKUP, Pivot Tables to forecast revenue based on historical data. © Analyzed old detection cases using JIRA tickets and Salesforce to determine which products have maximum False/True Positives and False/True Negatives. Conducted market analysis and research on other threat intelligence companies to see how they differ from each other. Created innovation games to help engineers decide product features. Coordinated with Product Manager to gather requirements and make modifications and corrections to the product specific documents. Certifications * Scrum Fundamentals Certified (April, 2016) © Microsoft Project 2016: Essential Training (February, 2016) * Hootsuite Certificate Courseware (October, 2015) * IBM DB2 Database and Application Fundamentals (October, 2013) Technical Skills * Database: Oracle 91, MySOL * Software/Tools: VB, MS Visio, Tableau, MS Project Professional, Salesforce, SharePoint Education (MAY, 2016) MS INFORMATION SYSTEMS-BUSINESS ANALYTICS (AUGUST, 2013) BE INFORMATION TECHNOLOGY Academic Projects ANALYTICS PROJECT (2016) e Used regression analysis, Tableau, and forecasting to conclude which states in US should stop the production of GE crops, soil damage, and which crops can be excluded from being produced genetically. DATA WAREHOUSING FOR (2015) © Offered a system design solution to a start-up based on requirements of and data provided by the company. Proposed a data warehouse management plan to manage inventory, sales, and customer data in order to help in day-to-day operations. The plan included gathering requirements, choosing KPI, data quality and data sources analysis, dimensional modeling, ETL system requirements, and budgeting. SUPPLY CHAIN MANAGEMENT FOR [J CONSTRUCTIONS PVT. LTD. (2015) * Analyzed operations data to propose a business plan using advanced MS Excel functions like VLOOKUP, Pivot tables, and linear regression. Aimed at improving overhead costs and improved the profit margin of the company by 1.5% per project.", "metadata": {"filename": "02a87605b8841c0f.pdf", "original_category": "Business Analyst", "extraction_method": "ocr"}, "parsed_education": [{"degree": "MS", "institution": null, "years": "2016", "field_of_study": "Information Systems"}, {"degree": "MS", "institution": null, "years": "2015", "field_of_study": "Unknown"}], "extracted_skills": ["Confluence", "Python", "SQL", "Google Analytics", "JIRA", "Excel", "PowerPoint", "Visio", "SharePoint", "Salesforce", "Scrum", "teams", "HTML", "Tableau", "Word", "Oracle"], "parsed_summary": " Business Analyst experienced in supporting analytical needs of organizations with prior project/product management", "personal_info": {"phone": null, "first_name": "Pivot", "last_name": "Tables"}}
{"cv_id": "02a87605b8841c0f", "target_role": "DevOps Engineer", "score": 0, "cv_text": "Summary Business Analyst experienced in supporting analytical needs of organizations with prior project/product management experience. Result- oriented individual recognized for effectively resolving challenging issues aspiring to become an Analytics expert. Work Experience = ANALYST [| Extracted data from Sabre, Duetto, and Google Analytics into MS Excel, implemented advanced functionalities like Pivot Tables, VLOOKUP, and Macros to perform data analysis for business; impacting insights & making recommendations. Used predictive analysis to predict the number of guests for any given night to maximize occupancy and increase revenue. Documented monthly e-commerce performance reports in MS Word and created MS PowerPoint presentations for higher management. * Defined KPI and metrics to measure business's success. © Part of diverse, cross-functional teams working towards fulfillment of corporate goals and productivity. Implemented SQL queries using joins and sub queries to retrieve data from the database. prowect MANAGER-INTERN | © = =Managed project requirements using JIRA and Confluence. © = Collected, cleaned, and analyzed data using IFTTT, WeWiredWeb, and MS Excel using functions like Pivot Tables and graphs. © Created mockups and wireframes; documented use cases, activity diagrams, sequence diagrams, and workflow. © = Analyzed and reviewed developer Python and HTML codes. © =©Prepared and executed test plans including documenting and resolving issues. . Documented Business Requirement Documents (BRDs) and Functional Requirement Documents (FRDs). atcat MANAGER-INTERN | Implemented advanced MS Excel functionalities like VLOOKUP, Pivot Tables to forecast revenue based on historical data. © Analyzed old detection cases using JIRA tickets and Salesforce to determine which products have maximum False/True Positives and False/True Negatives. Conducted market analysis and research on other threat intelligence companies to see how they differ from each other. Created innovation games to help engineers decide product features. Coordinated with Product Manager to gather requirements and make modifications and corrections to the product specific documents. Certifications * Scrum Fundamentals Certified (April, 2016) © Microsoft Project 2016: Essential Training (February, 2016) * Hootsuite Certificate Courseware (October, 2015) * IBM DB2 Database and Application Fundamentals (October, 2013) Technical Skills * Database: Oracle 91, MySOL * Software/Tools: VB, MS Visio, Tableau, MS Project Professional, Salesforce, SharePoint Education (MAY, 2016) MS INFORMATION SYSTEMS-BUSINESS ANALYTICS (AUGUST, 2013) BE INFORMATION TECHNOLOGY Academic Projects ANALYTICS PROJECT (2016) e Used regression analysis, Tableau, and forecasting to conclude which states in US should stop the production of GE crops, soil damage, and which crops can be excluded from being produced genetically. DATA WAREHOUSING FOR (2015) © Offered a system design solution to a start-up based on requirements of and data provided by the company. Proposed a data warehouse management plan to manage inventory, sales, and customer data in order to help in day-to-day operations. The plan included gathering requirements, choosing KPI, data quality and data sources analysis, dimensional modeling, ETL system requirements, and budgeting. SUPPLY CHAIN MANAGEMENT FOR [J CONSTRUCTIONS PVT. LTD. (2015) * Analyzed operations data to propose a business plan using advanced MS Excel functions like VLOOKUP, Pivot tables, and linear regression. Aimed at improving overhead costs and improved the profit margin of the company by 1.5% per project.", "metadata": {"filename": "02a87605b8841c0f.pdf", "original_category": "Business Analyst", "extraction_method": "ocr"}, "parsed_education": [{"degree": "MS", "institution": null, "years": "2016", "field_of_study": "Information Systems"}, {"degree": "MS", "institution": null, "years": "2015", "field_of_study": "Unknown"}], "extracted_skills": ["Confluence", "Python", "SQL", "Google Analytics", "JIRA", "Excel", "PowerPoint", "Visio", "SharePoint", "Salesforce", "Scrum", "teams", "HTML", "Tableau", "Word", "Oracle"], "parsed_summary": " Business Analyst experienced in supporting analytical needs of organizations with prior project/product management", "personal_info": {"phone": null, "first_name": "Pivot", "last_name": "Tables"}}
{"cv_id": "02a87605b8841c0f", "target_role": "ETL Developer", "score": 0, "cv_text": "Summary Business Analyst experienced in supporting analytical needs of organizations with prior project/product management experience. Result- oriented individual recognized for effectively resolving challenging issues aspiring to become an Analytics expert. Work Experience = ANALYST [| Extracted data from Sabre, Duetto, and Google Analytics into MS Excel, implemented advanced functionalities like Pivot Tables, VLOOKUP, and Macros to perform data analysis for business; impacting insights & making recommendations. Used predictive analysis to predict the number of guests for any given night to maximize occupancy and increase revenue. Documented monthly e-commerce performance reports in MS Word and created MS PowerPoint presentations for higher management. * Defined KPI and metrics to measure business's success. © Part of diverse, cross-functional teams working towards fulfillment of corporate goals and productivity. Implemented SQL queries using joins and sub queries to retrieve data from the database. prowect MANAGER-INTERN | © = =Managed project requirements using JIRA and Confluence. © = Collected, cleaned, and analyzed data using IFTTT, WeWiredWeb, and MS Excel using functions like Pivot Tables and graphs. © Created mockups and wireframes; documented use cases, activity diagrams, sequence diagrams, and workflow. © = Analyzed and reviewed developer Python and HTML codes. © =©Prepared and executed test plans including documenting and resolving issues. . Documented Business Requirement Documents (BRDs) and Functional Requirement Documents (FRDs). atcat MANAGER-INTERN | Implemented advanced MS Excel functionalities like VLOOKUP, Pivot Tables to forecast revenue based on historical data. © Analyzed old detection cases using JIRA tickets and Salesforce to determine which products have maximum False/True Positives and False/True Negatives. Conducted market analysis and research on other threat intelligence companies to see how they differ from each other. Created innovation games to help engineers decide product features. Coordinated with Product Manager to gather requirements and make modifications and corrections to the product specific documents. Certifications * Scrum Fundamentals Certified (April, 2016) © Microsoft Project 2016: Essential Training (February, 2016) * Hootsuite Certificate Courseware (October, 2015) * IBM DB2 Database and Application Fundamentals (October, 2013) Technical Skills * Database: Oracle 91, MySOL * Software/Tools: VB, MS Visio, Tableau, MS Project Professional, Salesforce, SharePoint Education (MAY, 2016) MS INFORMATION SYSTEMS-BUSINESS ANALYTICS (AUGUST, 2013) BE INFORMATION TECHNOLOGY Academic Projects ANALYTICS PROJECT (2016) e Used regression analysis, Tableau, and forecasting to conclude which states in US should stop the production of GE crops, soil damage, and which crops can be excluded from being produced genetically. DATA WAREHOUSING FOR (2015) © Offered a system design solution to a start-up based on requirements of and data provided by the company. Proposed a data warehouse management plan to manage inventory, sales, and customer data in order to help in day-to-day operations. The plan included gathering requirements, choosing KPI, data quality and data sources analysis, dimensional modeling, ETL system requirements, and budgeting. SUPPLY CHAIN MANAGEMENT FOR [J CONSTRUCTIONS PVT. LTD. (2015) * Analyzed operations data to propose a business plan using advanced MS Excel functions like VLOOKUP, Pivot tables, and linear regression. Aimed at improving overhead costs and improved the profit margin of the company by 1.5% per project.", "metadata": {"filename": "02a87605b8841c0f.pdf", "original_category": "Business Analyst", "extraction_method": "ocr"}, "parsed_education": [{"degree": "MS", "institution": null, "years": "2016", "field_of_study": "Information Systems"}, {"degree": "MS", "institution": null, "years": "2015", "field_of_study": "Unknown"}], "extracted_skills": ["Confluence", "Python", "SQL", "Google Analytics", "JIRA", "Excel", "PowerPoint", "Visio", "SharePoint", "Salesforce", "Scrum", "teams", "HTML", "Tableau", "Word", "Oracle"], "parsed_summary": " Business Analyst experienced in supporting analytical needs of organizations with prior project/product management", "personal_info": {"phone": null, "first_name": "Pivot", "last_name": "Tables"}}
{"cv_id": "02a87605b8841c0f", "target_role": "Java Developer", "score": 0, "cv_text": "Summary Business Analyst experienced in supporting analytical needs of organizations with prior project/product management experience. Result- oriented individual recognized for effectively resolving challenging issues aspiring to become an Analytics expert. Work Experience = ANALYST [| Extracted data from Sabre, Duetto, and Google Analytics into MS Excel, implemented advanced functionalities like Pivot Tables, VLOOKUP, and Macros to perform data analysis for business; impacting insights & making recommendations. Used predictive analysis to predict the number of guests for any given night to maximize occupancy and increase revenue. Documented monthly e-commerce performance reports in MS Word and created MS PowerPoint presentations for higher management. * Defined KPI and metrics to measure business's success. © Part of diverse, cross-functional teams working towards fulfillment of corporate goals and productivity. Implemented SQL queries using joins and sub queries to retrieve data from the database. prowect MANAGER-INTERN | © = =Managed project requirements using JIRA and Confluence. © = Collected, cleaned, and analyzed data using IFTTT, WeWiredWeb, and MS Excel using functions like Pivot Tables and graphs. © Created mockups and wireframes; documented use cases, activity diagrams, sequence diagrams, and workflow. © = Analyzed and reviewed developer Python and HTML codes. © =©Prepared and executed test plans including documenting and resolving issues. . Documented Business Requirement Documents (BRDs) and Functional Requirement Documents (FRDs). atcat MANAGER-INTERN | Implemented advanced MS Excel functionalities like VLOOKUP, Pivot Tables to forecast revenue based on historical data. © Analyzed old detection cases using JIRA tickets and Salesforce to determine which products have maximum False/True Positives and False/True Negatives. Conducted market analysis and research on other threat intelligence companies to see how they differ from each other. Created innovation games to help engineers decide product features. Coordinated with Product Manager to gather requirements and make modifications and corrections to the product specific documents. Certifications * Scrum Fundamentals Certified (April, 2016) © Microsoft Project 2016: Essential Training (February, 2016) * Hootsuite Certificate Courseware (October, 2015) * IBM DB2 Database and Application Fundamentals (October, 2013) Technical Skills * Database: Oracle 91, MySOL * Software/Tools: VB, MS Visio, Tableau, MS Project Professional, Salesforce, SharePoint Education (MAY, 2016) MS INFORMATION SYSTEMS-BUSINESS ANALYTICS (AUGUST, 2013) BE INFORMATION TECHNOLOGY Academic Projects ANALYTICS PROJECT (2016) e Used regression analysis, Tableau, and forecasting to conclude which states in US should stop the production of GE crops, soil damage, and which crops can be excluded from being produced genetically. DATA WAREHOUSING FOR (2015) © Offered a system design solution to a start-up based on requirements of and data provided by the company. Proposed a data warehouse management plan to manage inventory, sales, and customer data in order to help in day-to-day operations. The plan included gathering requirements, choosing KPI, data quality and data sources analysis, dimensional modeling, ETL system requirements, and budgeting. SUPPLY CHAIN MANAGEMENT FOR [J CONSTRUCTIONS PVT. LTD. (2015) * Analyzed operations data to propose a business plan using advanced MS Excel functions like VLOOKUP, Pivot tables, and linear regression. Aimed at improving overhead costs and improved the profit margin of the company by 1.5% per project.", "metadata": {"filename": "02a87605b8841c0f.pdf", "original_category": "Business Analyst", "extraction_method": "ocr"}, "parsed_education": [{"degree": "MS", "institution": null, "years": "2016", "field_of_study": "Information Systems"}, {"degree": "MS", "institution": null, "years": "2015", "field_of_study": "Unknown"}], "extracted_skills": ["Confluence", "Python", "SQL", "Google Analytics", "JIRA", "Excel", "PowerPoint", "Visio", "SharePoint", "Salesforce", "Scrum", "teams", "HTML", "Tableau", "Word", "Oracle"], "parsed_summary": " Business Analyst experienced in supporting analytical needs of organizations with prior project/product management", "personal_info": {"phone": null, "first_name": "Pivot", "last_name": "Tables"}}
{"cv_id": "02a87605b8841c0f", "target_role": "Python Developer", "score": 0, "cv_text": "Summary Business Analyst experienced in supporting analytical needs of organizations with prior project/product management experience. Result- oriented individual recognized for effectively resolving challenging issues aspiring to become an Analytics expert. Work Experience = ANALYST [| Extracted data from Sabre, Duetto, and Google Analytics into MS Excel, implemented advanced functionalities like Pivot Tables, VLOOKUP, and Macros to perform data analysis for business; impacting insights & making recommendations. Used predictive analysis to predict the number of guests for any given night to maximize occupancy and increase revenue. Documented monthly e-commerce performance reports in MS Word and created MS PowerPoint presentations for higher management. * Defined KPI and metrics to measure business's success. © Part of diverse, cross-functional teams working towards fulfillment of corporate goals and productivity. Implemented SQL queries using joins and sub queries to retrieve data from the database. prowect MANAGER-INTERN | © = =Managed project requirements using JIRA and Confluence. © = Collected, cleaned, and analyzed data using IFTTT, WeWiredWeb, and MS Excel using functions like Pivot Tables and graphs. © Created mockups and wireframes; documented use cases, activity diagrams, sequence diagrams, and workflow. © = Analyzed and reviewed developer Python and HTML codes. © =©Prepared and executed test plans including documenting and resolving issues. . Documented Business Requirement Documents (BRDs) and Functional Requirement Documents (FRDs). atcat MANAGER-INTERN | Implemented advanced MS Excel functionalities like VLOOKUP, Pivot Tables to forecast revenue based on historical data. © Analyzed old detection cases using JIRA tickets and Salesforce to determine which products have maximum False/True Positives and False/True Negatives. Conducted market analysis and research on other threat intelligence companies to see how they differ from each other. Created innovation games to help engineers decide product features. Coordinated with Product Manager to gather requirements and make modifications and corrections to the product specific documents. Certifications * Scrum Fundamentals Certified (April, 2016) © Microsoft Project 2016: Essential Training (February, 2016) * Hootsuite Certificate Courseware (October, 2015) * IBM DB2 Database and Application Fundamentals (October, 2013) Technical Skills * Database: Oracle 91, MySOL * Software/Tools: VB, MS Visio, Tableau, MS Project Professional, Salesforce, SharePoint Education (MAY, 2016) MS INFORMATION SYSTEMS-BUSINESS ANALYTICS (AUGUST, 2013) BE INFORMATION TECHNOLOGY Academic Projects ANALYTICS PROJECT (2016) e Used regression analysis, Tableau, and forecasting to conclude which states in US should stop the production of GE crops, soil damage, and which crops can be excluded from being produced genetically. DATA WAREHOUSING FOR (2015) © Offered a system design solution to a start-up based on requirements of and data provided by the company. Proposed a data warehouse management plan to manage inventory, sales, and customer data in order to help in day-to-day operations. The plan included gathering requirements, choosing KPI, data quality and data sources analysis, dimensional modeling, ETL system requirements, and budgeting. SUPPLY CHAIN MANAGEMENT FOR [J CONSTRUCTIONS PVT. LTD. (2015) * Analyzed operations data to propose a business plan using advanced MS Excel functions like VLOOKUP, Pivot tables, and linear regression. Aimed at improving overhead costs and improved the profit margin of the company by 1.5% per project.", "metadata": {"filename": "02a87605b8841c0f.pdf", "original_category": "Business Analyst", "extraction_method": "ocr"}, "parsed_education": [{"degree": "MS", "institution": null, "years": "2016", "field_of_study": "Information Systems"}, {"degree": "MS", "institution": null, "years": "2015", "field_of_study": "Unknown"}], "extracted_skills": ["Confluence", "Python", "SQL", "Google Analytics", "JIRA", "Excel", "PowerPoint", "Visio", "SharePoint", "Salesforce", "Scrum", "teams", "HTML", "Tableau", "Word", "Oracle"], "parsed_summary": " Business Analyst experienced in supporting analytical needs of organizations with prior project/product management", "personal_info": {"phone": null, "first_name": "Pivot", "last_name": "Tables"}}
{"cv_id": "02a87605b8841c0f", "target_role": "React Developer", "score": 0, "cv_text": "Summary Business Analyst experienced in supporting analytical needs of organizations with prior project/product management experience. Result- oriented individual recognized for effectively resolving challenging issues aspiring to become an Analytics expert. Work Experience = ANALYST [| Extracted data from Sabre, Duetto, and Google Analytics into MS Excel, implemented advanced functionalities like Pivot Tables, VLOOKUP, and Macros to perform data analysis for business; impacting insights & making recommendations. Used predictive analysis to predict the number of guests for any given night to maximize occupancy and increase revenue. Documented monthly e-commerce performance reports in MS Word and created MS PowerPoint presentations for higher management. * Defined KPI and metrics to measure business's success. © Part of diverse, cross-functional teams working towards fulfillment of corporate goals and productivity. Implemented SQL queries using joins and sub queries to retrieve data from the database. prowect MANAGER-INTERN | © = =Managed project requirements using JIRA and Confluence. © = Collected, cleaned, and analyzed data using IFTTT, WeWiredWeb, and MS Excel using functions like Pivot Tables and graphs. © Created mockups and wireframes; documented use cases, activity diagrams, sequence diagrams, and workflow. © = Analyzed and reviewed developer Python and HTML codes. © =©Prepared and executed test plans including documenting and resolving issues. . Documented Business Requirement Documents (BRDs) and Functional Requirement Documents (FRDs). atcat MANAGER-INTERN | Implemented advanced MS Excel functionalities like VLOOKUP, Pivot Tables to forecast revenue based on historical data. © Analyzed old detection cases using JIRA tickets and Salesforce to determine which products have maximum False/True Positives and False/True Negatives. Conducted market analysis and research on other threat intelligence companies to see how they differ from each other. Created innovation games to help engineers decide product features. Coordinated with Product Manager to gather requirements and make modifications and corrections to the product specific documents. Certifications * Scrum Fundamentals Certified (April, 2016) © Microsoft Project 2016: Essential Training (February, 2016) * Hootsuite Certificate Courseware (October, 2015) * IBM DB2 Database and Application Fundamentals (October, 2013) Technical Skills * Database: Oracle 91, MySOL * Software/Tools: VB, MS Visio, Tableau, MS Project Professional, Salesforce, SharePoint Education (MAY, 2016) MS INFORMATION SYSTEMS-BUSINESS ANALYTICS (AUGUST, 2013) BE INFORMATION TECHNOLOGY Academic Projects ANALYTICS PROJECT (2016) e Used regression analysis, Tableau, and forecasting to conclude which states in US should stop the production of GE crops, soil damage, and which crops can be excluded from being produced genetically. DATA WAREHOUSING FOR (2015) © Offered a system design solution to a start-up based on requirements of and data provided by the company. Proposed a data warehouse management plan to manage inventory, sales, and customer data in order to help in day-to-day operations. The plan included gathering requirements, choosing KPI, data quality and data sources analysis, dimensional modeling, ETL system requirements, and budgeting. SUPPLY CHAIN MANAGEMENT FOR [J CONSTRUCTIONS PVT. LTD. (2015) * Analyzed operations data to propose a business plan using advanced MS Excel functions like VLOOKUP, Pivot tables, and linear regression. Aimed at improving overhead costs and improved the profit margin of the company by 1.5% per project.", "metadata": {"filename": "02a87605b8841c0f.pdf", "original_category": "Business Analyst", "extraction_method": "ocr"}, "parsed_education": [{"degree": "MS", "institution": null, "years": "2016", "field_of_study": "Information Systems"}, {"degree": "MS", "institution": null, "years": "2015", "field_of_study": "Unknown"}], "extracted_skills": ["Confluence", "Python", "SQL", "Google Analytics", "JIRA", "Excel", "PowerPoint", "Visio", "SharePoint", "Salesforce", "Scrum", "teams", "HTML", "Tableau", "Word", "Oracle"], "parsed_summary": " Business Analyst experienced in supporting analytical needs of organizations with prior project/product management", "personal_info": {"phone": null, "first_name": "Pivot", "last_name": "Tables"}}
{"cv_id": "02a87605b8841c0f", "target_role": "SQL Developer", "score": 2, "cv_text": "Summary Business Analyst experienced in supporting analytical needs of organizations with prior project/product management experience. Result- oriented individual recognized for effectively resolving challenging issues aspiring to become an Analytics expert. Work Experience = ANALYST [| Extracted data from Sabre, Duetto, and Google Analytics into MS Excel, implemented advanced functionalities like Pivot Tables, VLOOKUP, and Macros to perform data analysis for business; impacting insights & making recommendations. Used predictive analysis to predict the number of guests for any given night to maximize occupancy and increase revenue. Documented monthly e-commerce performance reports in MS Word and created MS PowerPoint presentations for higher management. * Defined KPI and metrics to measure business's success. © Part of diverse, cross-functional teams working towards fulfillment of corporate goals and productivity. Implemented SQL queries using joins and sub queries to retrieve data from the database. prowect MANAGER-INTERN | © = =Managed project requirements using JIRA and Confluence. © = Collected, cleaned, and analyzed data using IFTTT, WeWiredWeb, and MS Excel using functions like Pivot Tables and graphs. © Created mockups and wireframes; documented use cases, activity diagrams, sequence diagrams, and workflow. © = Analyzed and reviewed developer Python and HTML codes. © =©Prepared and executed test plans including documenting and resolving issues. . Documented Business Requirement Documents (BRDs) and Functional Requirement Documents (FRDs). atcat MANAGER-INTERN | Implemented advanced MS Excel functionalities like VLOOKUP, Pivot Tables to forecast revenue based on historical data. © Analyzed old detection cases using JIRA tickets and Salesforce to determine which products have maximum False/True Positives and False/True Negatives. Conducted market analysis and research on other threat intelligence companies to see how they differ from each other. Created innovation games to help engineers decide product features. Coordinated with Product Manager to gather requirements and make modifications and corrections to the product specific documents. Certifications * Scrum Fundamentals Certified (April, 2016) © Microsoft Project 2016: Essential Training (February, 2016) * Hootsuite Certificate Courseware (October, 2015) * IBM DB2 Database and Application Fundamentals (October, 2013) Technical Skills * Database: Oracle 91, MySOL * Software/Tools: VB, MS Visio, Tableau, MS Project Professional, Salesforce, SharePoint Education (MAY, 2016) MS INFORMATION SYSTEMS-BUSINESS ANALYTICS (AUGUST, 2013) BE INFORMATION TECHNOLOGY Academic Projects ANALYTICS PROJECT (2016) e Used regression analysis, Tableau, and forecasting to conclude which states in US should stop the production of GE crops, soil damage, and which crops can be excluded from being produced genetically. DATA WAREHOUSING FOR (2015) © Offered a system design solution to a start-up based on requirements of and data provided by the company. Proposed a data warehouse management plan to manage inventory, sales, and customer data in order to help in day-to-day operations. The plan included gathering requirements, choosing KPI, data quality and data sources analysis, dimensional modeling, ETL system requirements, and budgeting. SUPPLY CHAIN MANAGEMENT FOR [J CONSTRUCTIONS PVT. LTD. (2015) * Analyzed operations data to propose a business plan using advanced MS Excel functions like VLOOKUP, Pivot tables, and linear regression. Aimed at improving overhead costs and improved the profit margin of the company by 1.5% per project.", "metadata": {"filename": "02a87605b8841c0f.pdf", "original_category": "Business Analyst", "extraction_method": "ocr"}, "parsed_education": [{"degree": "MS", "institution": null, "years": "2016", "field_of_study": "Information Systems"}, {"degree": "MS", "institution": null, "years": "2015", "field_of_study": "Unknown"}], "extracted_skills": ["Confluence", "Python", "SQL", "Google Analytics", "JIRA", "Excel", "PowerPoint", "Visio", "SharePoint", "Salesforce", "Scrum", "teams", "HTML", "Tableau", "Word", "Oracle"], "parsed_summary": " Business Analyst experienced in supporting analytical needs of organizations with prior project/product management", "personal_info": {"phone": null, "first_name": "Pivot", "last_name": "Tables"}}
{"cv_id": "02a87605b8841c0f", "target_role": "Web Developer", "score": 0, "cv_text": "Summary Business Analyst experienced in supporting analytical needs of organizations with prior project/product management experience. Result- oriented individual recognized for effectively resolving challenging issues aspiring to become an Analytics expert. Work Experience = ANALYST [| Extracted data from Sabre, Duetto, and Google Analytics into MS Excel, implemented advanced functionalities like Pivot Tables, VLOOKUP, and Macros to perform data analysis for business; impacting insights & making recommendations. Used predictive analysis to predict the number of guests for any given night to maximize occupancy and increase revenue. Documented monthly e-commerce performance reports in MS Word and created MS PowerPoint presentations for higher management. * Defined KPI and metrics to measure business's success. © Part of diverse, cross-functional teams working towards fulfillment of corporate goals and productivity. Implemented SQL queries using joins and sub queries to retrieve data from the database. prowect MANAGER-INTERN | © = =Managed project requirements using JIRA and Confluence. © = Collected, cleaned, and analyzed data using IFTTT, WeWiredWeb, and MS Excel using functions like Pivot Tables and graphs. © Created mockups and wireframes; documented use cases, activity diagrams, sequence diagrams, and workflow. © = Analyzed and reviewed developer Python and HTML codes. © =©Prepared and executed test plans including documenting and resolving issues. . Documented Business Requirement Documents (BRDs) and Functional Requirement Documents (FRDs). atcat MANAGER-INTERN | Implemented advanced MS Excel functionalities like VLOOKUP, Pivot Tables to forecast revenue based on historical data. © Analyzed old detection cases using JIRA tickets and Salesforce to determine which products have maximum False/True Positives and False/True Negatives. Conducted market analysis and research on other threat intelligence companies to see how they differ from each other. Created innovation games to help engineers decide product features. Coordinated with Product Manager to gather requirements and make modifications and corrections to the product specific documents. Certifications * Scrum Fundamentals Certified (April, 2016) © Microsoft Project 2016: Essential Training (February, 2016) * Hootsuite Certificate Courseware (October, 2015) * IBM DB2 Database and Application Fundamentals (October, 2013) Technical Skills * Database: Oracle 91, MySOL * Software/Tools: VB, MS Visio, Tableau, MS Project Professional, Salesforce, SharePoint Education (MAY, 2016) MS INFORMATION SYSTEMS-BUSINESS ANALYTICS (AUGUST, 2013) BE INFORMATION TECHNOLOGY Academic Projects ANALYTICS PROJECT (2016) e Used regression analysis, Tableau, and forecasting to conclude which states in US should stop the production of GE crops, soil damage, and which crops can be excluded from being produced genetically. DATA WAREHOUSING FOR (2015) © Offered a system design solution to a start-up based on requirements of and data provided by the company. Proposed a data warehouse management plan to manage inventory, sales, and customer data in order to help in day-to-day operations. The plan included gathering requirements, choosing KPI, data quality and data sources analysis, dimensional modeling, ETL system requirements, and budgeting. SUPPLY CHAIN MANAGEMENT FOR [J CONSTRUCTIONS PVT. LTD. (2015) * Analyzed operations data to propose a business plan using advanced MS Excel functions like VLOOKUP, Pivot tables, and linear regression. Aimed at improving overhead costs and improved the profit margin of the company by 1.5% per project.", "metadata": {"filename": "02a87605b8841c0f.pdf", "original_category": "Business Analyst", "extraction_method": "ocr"}, "parsed_education": [{"degree": "MS", "institution": null, "years": "2016", "field_of_study": "Information Systems"}, {"degree": "MS", "institution": null, "years": "2015", "field_of_study": "Unknown"}], "extracted_skills": ["Confluence", "Python", "SQL", "Google Analytics", "JIRA", "Excel", "PowerPoint", "Visio", "SharePoint", "Salesforce", "Scrum", "teams", "HTML", "Tableau", "Word", "Oracle"], "parsed_summary": " Business Analyst experienced in supporting analytical needs of organizations with prior project/product management", "personal_info": {"phone": null, "first_name": "Pivot", "last_name": "Tables"}}
{"cv_id": "02a87605b8841c0f", "target_role": "SAP Developer", "score": 2, "cv_text": "Summary Business Analyst experienced in supporting analytical needs of organizations with prior project/product management experience. Result- oriented individual recognized for effectively resolving challenging issues aspiring to become an Analytics expert. Work Experience = ANALYST [| Extracted data from Sabre, Duetto, and Google Analytics into MS Excel, implemented advanced functionalities like Pivot Tables, VLOOKUP, and Macros to perform data analysis for business; impacting insights & making recommendations. Used predictive analysis to predict the number of guests for any given night to maximize occupancy and increase revenue. Documented monthly e-commerce performance reports in MS Word and created MS PowerPoint presentations for higher management. * Defined KPI and metrics to measure business's success. © Part of diverse, cross-functional teams working towards fulfillment of corporate goals and productivity. Implemented SQL queries using joins and sub queries to retrieve data from the database. prowect MANAGER-INTERN | © = =Managed project requirements using JIRA and Confluence. © = Collected, cleaned, and analyzed data using IFTTT, WeWiredWeb, and MS Excel using functions like Pivot Tables and graphs. © Created mockups and wireframes; documented use cases, activity diagrams, sequence diagrams, and workflow. © = Analyzed and reviewed developer Python and HTML codes. © =©Prepared and executed test plans including documenting and resolving issues. . Documented Business Requirement Documents (BRDs) and Functional Requirement Documents (FRDs). atcat MANAGER-INTERN | Implemented advanced MS Excel functionalities like VLOOKUP, Pivot Tables to forecast revenue based on historical data. © Analyzed old detection cases using JIRA tickets and Salesforce to determine which products have maximum False/True Positives and False/True Negatives. Conducted market analysis and research on other threat intelligence companies to see how they differ from each other. Created innovation games to help engineers decide product features. Coordinated with Product Manager to gather requirements and make modifications and corrections to the product specific documents. Certifications * Scrum Fundamentals Certified (April, 2016) © Microsoft Project 2016: Essential Training (February, 2016) * Hootsuite Certificate Courseware (October, 2015) * IBM DB2 Database and Application Fundamentals (October, 2013) Technical Skills * Database: Oracle 91, MySOL * Software/Tools: VB, MS Visio, Tableau, MS Project Professional, Salesforce, SharePoint Education (MAY, 2016) MS INFORMATION SYSTEMS-BUSINESS ANALYTICS (AUGUST, 2013) BE INFORMATION TECHNOLOGY Academic Projects ANALYTICS PROJECT (2016) e Used regression analysis, Tableau, and forecasting to conclude which states in US should stop the production of GE crops, soil damage, and which crops can be excluded from being produced genetically. DATA WAREHOUSING FOR (2015) © Offered a system design solution to a start-up based on requirements of and data provided by the company. Proposed a data warehouse management plan to manage inventory, sales, and customer data in order to help in day-to-day operations. The plan included gathering requirements, choosing KPI, data quality and data sources analysis, dimensional modeling, ETL system requirements, and budgeting. SUPPLY CHAIN MANAGEMENT FOR [J CONSTRUCTIONS PVT. LTD. (2015) * Analyzed operations data to propose a business plan using advanced MS Excel functions like VLOOKUP, Pivot tables, and linear regression. Aimed at improving overhead costs and improved the profit margin of the company by 1.5% per project.", "metadata": {"filename": "02a87605b8841c0f.pdf", "original_category": "Business Analyst", "extraction_method": "ocr"}, "parsed_education": [{"degree": "MS", "institution": null, "years": "2016", "field_of_study": "Information Systems"}, {"degree": "MS", "institution": null, "years": "2015", "field_of_study": "Unknown"}], "extracted_skills": ["Confluence", "Python", "SQL", "Google Analytics", "JIRA", "Excel", "PowerPoint", "Visio", "SharePoint", "Salesforce", "Scrum", "teams", "HTML", "Tableau", "Word", "Oracle"], "parsed_summary": " Business Analyst experienced in supporting analytical needs of organizations with prior project/product management", "personal_info": {"phone": null, "first_name": "Pivot", "last_name": "Tables"}}
{"cv_id": "02a87605b8841c0f", "target_role": "Tester", "score": 0, "cv_text": "Summary Business Analyst experienced in supporting analytical needs of organizations with prior project/product management experience. Result- oriented individual recognized for effectively resolving challenging issues aspiring to become an Analytics expert. Work Experience = ANALYST [| Extracted data from Sabre, Duetto, and Google Analytics into MS Excel, implemented advanced functionalities like Pivot Tables, VLOOKUP, and Macros to perform data analysis for business; impacting insights & making recommendations. Used predictive analysis to predict the number of guests for any given night to maximize occupancy and increase revenue. Documented monthly e-commerce performance reports in MS Word and created MS PowerPoint presentations for higher management. * Defined KPI and metrics to measure business's success. © Part of diverse, cross-functional teams working towards fulfillment of corporate goals and productivity. Implemented SQL queries using joins and sub queries to retrieve data from the database. prowect MANAGER-INTERN | © = =Managed project requirements using JIRA and Confluence. © = Collected, cleaned, and analyzed data using IFTTT, WeWiredWeb, and MS Excel using functions like Pivot Tables and graphs. © Created mockups and wireframes; documented use cases, activity diagrams, sequence diagrams, and workflow. © = Analyzed and reviewed developer Python and HTML codes. © =©Prepared and executed test plans including documenting and resolving issues. . Documented Business Requirement Documents (BRDs) and Functional Requirement Documents (FRDs). atcat MANAGER-INTERN | Implemented advanced MS Excel functionalities like VLOOKUP, Pivot Tables to forecast revenue based on historical data. © Analyzed old detection cases using JIRA tickets and Salesforce to determine which products have maximum False/True Positives and False/True Negatives. Conducted market analysis and research on other threat intelligence companies to see how they differ from each other. Created innovation games to help engineers decide product features. Coordinated with Product Manager to gather requirements and make modifications and corrections to the product specific documents. Certifications * Scrum Fundamentals Certified (April, 2016) © Microsoft Project 2016: Essential Training (February, 2016) * Hootsuite Certificate Courseware (October, 2015) * IBM DB2 Database and Application Fundamentals (October, 2013) Technical Skills * Database: Oracle 91, MySOL * Software/Tools: VB, MS Visio, Tableau, MS Project Professional, Salesforce, SharePoint Education (MAY, 2016) MS INFORMATION SYSTEMS-BUSINESS ANALYTICS (AUGUST, 2013) BE INFORMATION TECHNOLOGY Academic Projects ANALYTICS PROJECT (2016) e Used regression analysis, Tableau, and forecasting to conclude which states in US should stop the production of GE crops, soil damage, and which crops can be excluded from being produced genetically. DATA WAREHOUSING FOR (2015) © Offered a system design solution to a start-up based on requirements of and data provided by the company. Proposed a data warehouse management plan to manage inventory, sales, and customer data in order to help in day-to-day operations. The plan included gathering requirements, choosing KPI, data quality and data sources analysis, dimensional modeling, ETL system requirements, and budgeting. SUPPLY CHAIN MANAGEMENT FOR [J CONSTRUCTIONS PVT. LTD. (2015) * Analyzed operations data to propose a business plan using advanced MS Excel functions like VLOOKUP, Pivot tables, and linear regression. Aimed at improving overhead costs and improved the profit margin of the company by 1.5% per project.", "metadata": {"filename": "02a87605b8841c0f.pdf", "original_category": "Business Analyst", "extraction_method": "ocr"}, "parsed_education": [{"degree": "MS", "institution": null, "years": "2016", "field_of_study": "Information Systems"}, {"degree": "MS", "institution": null, "years": "2015", "field_of_study": "Unknown"}], "extracted_skills": ["Confluence", "Python", "SQL", "Google Analytics", "JIRA", "Excel", "PowerPoint", "Visio", "SharePoint", "Salesforce", "Scrum", "teams", "HTML", "Tableau", "Word", "Oracle"], "parsed_summary": " Business Analyst experienced in supporting analytical needs of organizations with prior project/product management", "personal_info": {"phone": null, "first_name": "Pivot", "last_name": "Tables"}}
{"cv_id": "0d0d565220bd4a5c", "target_role": "Business Analyst", "score": 5, "cv_text": "Kaitlyn Riley Business Details Profile Address Dedicated Business Analyst with a strong understanding of finance, operational New York, NY proficiency, and business development. Adept in project management and trend analysis. United States Committed to gaining extensive knowledge of the structure, policies, and operations of an organization, to properly recommend solutions that improve business processes. Phone 917-678-5454 Email Employment History kaitlyn_rianalyst@gmail.com Business Analyst, Lexagon Jun 2019 — Present New York Ski | Is e Steadily provide direct support to process improvement in customer service operations. Business Development and e Analyze, define, and develop complex business process methods to simplify and Management improve the customer experience for this busy recruiting firm of 80 associates. eooee e Work directly with business users to understand requirements and expectations, Leadership while making recommendations for business and process improvements. ec0e0e0d e Research best business practices both internally and externally to establish benchmark data. Problem Solving e Build test scripts to thoroughly test the accuracy of loaded data. ore SS e Assist in the financial analysis and due diligence process for key projects, helping to Attention to Detail cut costs by 40% in my first year of employment alone. @eeee e Evaluate existing processes, and recommend optimal solutions and improvements. Interpersonal Skills ecoee0ed Finance and Accounting Ed ucation ecoee0d NYU, Leonard N. Stern School of Business, Bachelor of Science, Finance Sep 2015 — May 2019 New York Languages . e Overall GPA: 3.65; Major GPA: 3.89 English ecoeeo0d Spanish; Castilian Internships ecoec0e French Business Technology Intern, Muher Technologies renc ecco Oct 2018 — Jun 2019 New York", "metadata": {"filename": "0d0d565220bd4a5c.pdf", "original_category": "Business Analyst", "extraction_method": "ocr"}, "parsed_education": [], "extracted_skills": ["process improvement", "project management"], "parsed_summary": "Kaitlyn Riley Business Details Profile Address Dedicated Business Analyst with a strong understanding of finance, operational New York, NY proficiency, and business development. Adept in project management and trend analysis. United States Committed to gaining extensive knowledge of the structure, policies, and operations of an organization, to properly recommend solutions that improve business processes. Phone 917-678-5454 Email Employment History kaitlyn_rianalyst@gmail.com Business Analyst, L", "personal_info": {"phone": "917-678-5454", "first_name": null, "last_name": null}}
{"cv_id": "0d0d565220bd4a5c", "target_role": "Data Scientist", "score": 1, "cv_text": "Kaitlyn Riley Business Details Profile Address Dedicated Business Analyst with a strong understanding of finance, operational New York, NY proficiency, and business development. Adept in project management and trend analysis. United States Committed to gaining extensive knowledge of the structure, policies, and operations of an organization, to properly recommend solutions that improve business processes. Phone 917-678-5454 Email Employment History kaitlyn_rianalyst@gmail.com Business Analyst, Lexagon Jun 2019 — Present New York Ski | Is e Steadily provide direct support to process improvement in customer service operations. Business Development and e Analyze, define, and develop complex business process methods to simplify and Management improve the customer experience for this busy recruiting firm of 80 associates. eooee e Work directly with business users to understand requirements and expectations, Leadership while making recommendations for business and process improvements. ec0e0e0d e Research best business practices both internally and externally to establish benchmark data. Problem Solving e Build test scripts to thoroughly test the accuracy of loaded data. ore SS e Assist in the financial analysis and due diligence process for key projects, helping to Attention to Detail cut costs by 40% in my first year of employment alone. @eeee e Evaluate existing processes, and recommend optimal solutions and improvements. Interpersonal Skills ecoee0ed Finance and Accounting Ed ucation ecoee0d NYU, Leonard N. Stern School of Business, Bachelor of Science, Finance Sep 2015 — May 2019 New York Languages . e Overall GPA: 3.65; Major GPA: 3.89 English ecoeeo0d Spanish; Castilian Internships ecoec0e French Business Technology Intern, Muher Technologies renc ecco Oct 2018 — Jun 2019 New York", "metadata": {"filename": "0d0d565220bd4a5c.pdf", "original_category": "Business Analyst", "extraction_method": "ocr"}, "parsed_education": [], "extracted_skills": ["process improvement", "project management"], "parsed_summary": "Kaitlyn Riley Business Details Profile Address Dedicated Business Analyst with a strong understanding of finance, operational New York, NY proficiency, and business development. Adept in project management and trend analysis. United States Committed to gaining extensive knowledge of the structure, policies, and operations of an organization, to properly recommend solutions that improve business processes. Phone 917-678-5454 Email Employment History kaitlyn_rianalyst@gmail.com Business Analyst, L", "personal_info": {"phone": "917-678-5454", "first_name": null, "last_name": null}}
{"cv_id": "0d0d565220bd4a5c", "target_role": "DevOps Engineer", "score": 0, "cv_text": "Kaitlyn Riley Business Details Profile Address Dedicated Business Analyst with a strong understanding of finance, operational New York, NY proficiency, and business development. Adept in project management and trend analysis. United States Committed to gaining extensive knowledge of the structure, policies, and operations of an organization, to properly recommend solutions that improve business processes. Phone 917-678-5454 Email Employment History kaitlyn_rianalyst@gmail.com Business Analyst, Lexagon Jun 2019 — Present New York Ski | Is e Steadily provide direct support to process improvement in customer service operations. Business Development and e Analyze, define, and develop complex business process methods to simplify and Management improve the customer experience for this busy recruiting firm of 80 associates. eooee e Work directly with business users to understand requirements and expectations, Leadership while making recommendations for business and process improvements. ec0e0e0d e Research best business practices both internally and externally to establish benchmark data. Problem Solving e Build test scripts to thoroughly test the accuracy of loaded data. ore SS e Assist in the financial analysis and due diligence process for key projects, helping to Attention to Detail cut costs by 40% in my first year of employment alone. @eeee e Evaluate existing processes, and recommend optimal solutions and improvements. Interpersonal Skills ecoee0ed Finance and Accounting Ed ucation ecoee0d NYU, Leonard N. Stern School of Business, Bachelor of Science, Finance Sep 2015 — May 2019 New York Languages . e Overall GPA: 3.65; Major GPA: 3.89 English ecoeeo0d Spanish; Castilian Internships ecoec0e French Business Technology Intern, Muher Technologies renc ecco Oct 2018 — Jun 2019 New York", "metadata": {"filename": "0d0d565220bd4a5c.pdf", "original_category": "Business Analyst", "extraction_method": "ocr"}, "parsed_education": [], "extracted_skills": ["process improvement", "project management"], "parsed_summary": "Kaitlyn Riley Business Details Profile Address Dedicated Business Analyst with a strong understanding of finance, operational New York, NY proficiency, and business development. Adept in project management and trend analysis. United States Committed to gaining extensive knowledge of the structure, policies, and operations of an organization, to properly recommend solutions that improve business processes. Phone 917-678-5454 Email Employment History kaitlyn_rianalyst@gmail.com Business Analyst, L", "personal_info": {"phone": "917-678-5454", "first_name": null, "last_name": null}}
{"cv_id": "0d0d565220bd4a5c", "target_role": "ETL Developer", "score": 0, "cv_text": "Kaitlyn Riley Business Details Profile Address Dedicated Business Analyst with a strong understanding of finance, operational New York, NY proficiency, and business development. Adept in project management and trend analysis. United States Committed to gaining extensive knowledge of the structure, policies, and operations of an organization, to properly recommend solutions that improve business processes. Phone 917-678-5454 Email Employment History kaitlyn_rianalyst@gmail.com Business Analyst, Lexagon Jun 2019 — Present New York Ski | Is e Steadily provide direct support to process improvement in customer service operations. Business Development and e Analyze, define, and develop complex business process methods to simplify and Management improve the customer experience for this busy recruiting firm of 80 associates. eooee e Work directly with business users to understand requirements and expectations, Leadership while making recommendations for business and process improvements. ec0e0e0d e Research best business practices both internally and externally to establish benchmark data. Problem Solving e Build test scripts to thoroughly test the accuracy of loaded data. ore SS e Assist in the financial analysis and due diligence process for key projects, helping to Attention to Detail cut costs by 40% in my first year of employment alone. @eeee e Evaluate existing processes, and recommend optimal solutions and improvements. Interpersonal Skills ecoee0ed Finance and Accounting Ed ucation ecoee0d NYU, Leonard N. Stern School of Business, Bachelor of Science, Finance Sep 2015 — May 2019 New York Languages . e Overall GPA: 3.65; Major GPA: 3.89 English ecoeeo0d Spanish; Castilian Internships ecoec0e French Business Technology Intern, Muher Technologies renc ecco Oct 2018 — Jun 2019 New York", "metadata": {"filename": "0d0d565220bd4a5c.pdf", "original_category": "Business Analyst", "extraction_method": "ocr"}, "parsed_education": [], "extracted_skills": ["process improvement", "project management"], "parsed_summary": "Kaitlyn Riley Business Details Profile Address Dedicated Business Analyst with a strong understanding of finance, operational New York, NY proficiency, and business development. Adept in project management and trend analysis. United States Committed to gaining extensive knowledge of the structure, policies, and operations of an organization, to properly recommend solutions that improve business processes. Phone 917-678-5454 Email Employment History kaitlyn_rianalyst@gmail.com Business Analyst, L", "personal_info": {"phone": "917-678-5454", "first_name": null, "last_name": null}}
{"cv_id": "0d0d565220bd4a5c", "target_role": "Java Developer", "score": 0, "cv_text": "Kaitlyn Riley Business Details Profile Address Dedicated Business Analyst with a strong understanding of finance, operational New York, NY proficiency, and business development. Adept in project management and trend analysis. United States Committed to gaining extensive knowledge of the structure, policies, and operations of an organization, to properly recommend solutions that improve business processes. Phone 917-678-5454 Email Employment History kaitlyn_rianalyst@gmail.com Business Analyst, Lexagon Jun 2019 — Present New York Ski | Is e Steadily provide direct support to process improvement in customer service operations. Business Development and e Analyze, define, and develop complex business process methods to simplify and Management improve the customer experience for this busy recruiting firm of 80 associates. eooee e Work directly with business users to understand requirements and expectations, Leadership while making recommendations for business and process improvements. ec0e0e0d e Research best business practices both internally and externally to establish benchmark data. Problem Solving e Build test scripts to thoroughly test the accuracy of loaded data. ore SS e Assist in the financial analysis and due diligence process for key projects, helping to Attention to Detail cut costs by 40% in my first year of employment alone. @eeee e Evaluate existing processes, and recommend optimal solutions and improvements. Interpersonal Skills ecoee0ed Finance and Accounting Ed ucation ecoee0d NYU, Leonard N. Stern School of Business, Bachelor of Science, Finance Sep 2015 — May 2019 New York Languages . e Overall GPA: 3.65; Major GPA: 3.89 English ecoeeo0d Spanish; Castilian Internships ecoec0e French Business Technology Intern, Muher Technologies renc ecco Oct 2018 — Jun 2019 New York", "metadata": {"filename": "0d0d565220bd4a5c.pdf", "original_category": "Business Analyst", "extraction_method": "ocr"}, "parsed_education": [], "extracted_skills": ["process improvement", "project management"], "parsed_summary": "Kaitlyn Riley Business Details Profile Address Dedicated Business Analyst with a strong understanding of finance, operational New York, NY proficiency, and business development. Adept in project management and trend analysis. United States Committed to gaining extensive knowledge of the structure, policies, and operations of an organization, to properly recommend solutions that improve business processes. Phone 917-678-5454 Email Employment History kaitlyn_rianalyst@gmail.com Business Analyst, L", "personal_info": {"phone": "917-678-5454", "first_name": null, "last_name": null}}
{"cv_id": "0d0d565220bd4a5c", "target_role": "Python Developer", "score": 0, "cv_text": "Kaitlyn Riley Business Details Profile Address Dedicated Business Analyst with a strong understanding of finance, operational New York, NY proficiency, and business development. Adept in project management and trend analysis. United States Committed to gaining extensive knowledge of the structure, policies, and operations of an organization, to properly recommend solutions that improve business processes. Phone 917-678-5454 Email Employment History kaitlyn_rianalyst@gmail.com Business Analyst, Lexagon Jun 2019 — Present New York Ski | Is e Steadily provide direct support to process improvement in customer service operations. Business Development and e Analyze, define, and develop complex business process methods to simplify and Management improve the customer experience for this busy recruiting firm of 80 associates. eooee e Work directly with business users to understand requirements and expectations, Leadership while making recommendations for business and process improvements. ec0e0e0d e Research best business practices both internally and externally to establish benchmark data. Problem Solving e Build test scripts to thoroughly test the accuracy of loaded data. ore SS e Assist in the financial analysis and due diligence process for key projects, helping to Attention to Detail cut costs by 40% in my first year of employment alone. @eeee e Evaluate existing processes, and recommend optimal solutions and improvements. Interpersonal Skills ecoee0ed Finance and Accounting Ed ucation ecoee0d NYU, Leonard N. Stern School of Business, Bachelor of Science, Finance Sep 2015 — May 2019 New York Languages . e Overall GPA: 3.65; Major GPA: 3.89 English ecoeeo0d Spanish; Castilian Internships ecoec0e French Business Technology Intern, Muher Technologies renc ecco Oct 2018 — Jun 2019 New York", "metadata": {"filename": "0d0d565220bd4a5c.pdf", "original_category": "Business Analyst", "extraction_method": "ocr"}, "parsed_education": [], "extracted_skills": ["process improvement", "project management"], "parsed_summary": "Kaitlyn Riley Business Details Profile Address Dedicated Business Analyst with a strong understanding of finance, operational New York, NY proficiency, and business development. Adept in project management and trend analysis. United States Committed to gaining extensive knowledge of the structure, policies, and operations of an organization, to properly recommend solutions that improve business processes. Phone 917-678-5454 Email Employment History kaitlyn_rianalyst@gmail.com Business Analyst, L", "personal_info": {"phone": "917-678-5454", "first_name": null, "last_name": null}}
{"cv_id": "0d0d565220bd4a5c", "target_role": "React Developer", "score": 0, "cv_text": "Kaitlyn Riley Business Details Profile Address Dedicated Business Analyst with a strong understanding of finance, operational New York, NY proficiency, and business development. Adept in project management and trend analysis. United States Committed to gaining extensive knowledge of the structure, policies, and operations of an organization, to properly recommend solutions that improve business processes. Phone 917-678-5454 Email Employment History kaitlyn_rianalyst@gmail.com Business Analyst, Lexagon Jun 2019 — Present New York Ski | Is e Steadily provide direct support to process improvement in customer service operations. Business Development and e Analyze, define, and develop complex business process methods to simplify and Management improve the customer experience for this busy recruiting firm of 80 associates. eooee e Work directly with business users to understand requirements and expectations, Leadership while making recommendations for business and process improvements. ec0e0e0d e Research best business practices both internally and externally to establish benchmark data. Problem Solving e Build test scripts to thoroughly test the accuracy of loaded data. ore SS e Assist in the financial analysis and due diligence process for key projects, helping to Attention to Detail cut costs by 40% in my first year of employment alone. @eeee e Evaluate existing processes, and recommend optimal solutions and improvements. Interpersonal Skills ecoee0ed Finance and Accounting Ed ucation ecoee0d NYU, Leonard N. Stern School of Business, Bachelor of Science, Finance Sep 2015 — May 2019 New York Languages . e Overall GPA: 3.65; Major GPA: 3.89 English ecoeeo0d Spanish; Castilian Internships ecoec0e French Business Technology Intern, Muher Technologies renc ecco Oct 2018 — Jun 2019 New York", "metadata": {"filename": "0d0d565220bd4a5c.pdf", "original_category": "Business Analyst", "extraction_method": "ocr"}, "parsed_education": [], "extracted_skills": ["process improvement", "project management"], "parsed_summary": "Kaitlyn Riley Business Details Profile Address Dedicated Business Analyst with a strong understanding of finance, operational New York, NY proficiency, and business development. Adept in project management and trend analysis. United States Committed to gaining extensive knowledge of the structure, policies, and operations of an organization, to properly recommend solutions that improve business processes. Phone 917-678-5454 Email Employment History kaitlyn_rianalyst@gmail.com Business Analyst, L", "personal_info": {"phone": "917-678-5454", "first_name": null, "last_name": null}}
{"cv_id": "0d0d565220bd4a5c", "target_role": "SQL Developer", "score": 2, "cv_text": "Kaitlyn Riley Business Details Profile Address Dedicated Business Analyst with a strong understanding of finance, operational New York, NY proficiency, and business development. Adept in project management and trend analysis. United States Committed to gaining extensive knowledge of the structure, policies, and operations of an organization, to properly recommend solutions that improve business processes. Phone 917-678-5454 Email Employment History kaitlyn_rianalyst@gmail.com Business Analyst, Lexagon Jun 2019 — Present New York Ski | Is e Steadily provide direct support to process improvement in customer service operations. Business Development and e Analyze, define, and develop complex business process methods to simplify and Management improve the customer experience for this busy recruiting firm of 80 associates. eooee e Work directly with business users to understand requirements and expectations, Leadership while making recommendations for business and process improvements. ec0e0e0d e Research best business practices both internally and externally to establish benchmark data. Problem Solving e Build test scripts to thoroughly test the accuracy of loaded data. ore SS e Assist in the financial analysis and due diligence process for key projects, helping to Attention to Detail cut costs by 40% in my first year of employment alone. @eeee e Evaluate existing processes, and recommend optimal solutions and improvements. Interpersonal Skills ecoee0ed Finance and Accounting Ed ucation ecoee0d NYU, Leonard N. Stern School of Business, Bachelor of Science, Finance Sep 2015 — May 2019 New York Languages . e Overall GPA: 3.65; Major GPA: 3.89 English ecoeeo0d Spanish; Castilian Internships ecoec0e French Business Technology Intern, Muher Technologies renc ecco Oct 2018 — Jun 2019 New York", "metadata": {"filename": "0d0d565220bd4a5c.pdf", "original_category": "Business Analyst", "extraction_method": "ocr"}, "parsed_education": [], "extracted_skills": ["process improvement", "project management"], "parsed_summary": "Kaitlyn Riley Business Details Profile Address Dedicated Business Analyst with a strong understanding of finance, operational New York, NY proficiency, and business development. Adept in project management and trend analysis. United States Committed to gaining extensive knowledge of the structure, policies, and operations of an organization, to properly recommend solutions that improve business processes. Phone 917-678-5454 Email Employment History kaitlyn_rianalyst@gmail.com Business Analyst, L", "personal_info": {"phone": "917-678-5454", "first_name": null, "last_name": null}}
{"cv_id": "0d0d565220bd4a5c", "target_role": "Web Developer", "score": 0, "cv_text": "Kaitlyn Riley Business Details Profile Address Dedicated Business Analyst with a strong understanding of finance, operational New York, NY proficiency, and business development. Adept in project management and trend analysis. United States Committed to gaining extensive knowledge of the structure, policies, and operations of an organization, to properly recommend solutions that improve business processes. Phone 917-678-5454 Email Employment History kaitlyn_rianalyst@gmail.com Business Analyst, Lexagon Jun 2019 — Present New York Ski | Is e Steadily provide direct support to process improvement in customer service operations. Business Development and e Analyze, define, and develop complex business process methods to simplify and Management improve the customer experience for this busy recruiting firm of 80 associates. eooee e Work directly with business users to understand requirements and expectations, Leadership while making recommendations for business and process improvements. ec0e0e0d e Research best business practices both internally and externally to establish benchmark data. Problem Solving e Build test scripts to thoroughly test the accuracy of loaded data. ore SS e Assist in the financial analysis and due diligence process for key projects, helping to Attention to Detail cut costs by 40% in my first year of employment alone. @eeee e Evaluate existing processes, and recommend optimal solutions and improvements. Interpersonal Skills ecoee0ed Finance and Accounting Ed ucation ecoee0d NYU, Leonard N. Stern School of Business, Bachelor of Science, Finance Sep 2015 — May 2019 New York Languages . e Overall GPA: 3.65; Major GPA: 3.89 English ecoeeo0d Spanish; Castilian Internships ecoec0e French Business Technology Intern, Muher Technologies renc ecco Oct 2018 — Jun 2019 New York", "metadata": {"filename": "0d0d565220bd4a5c.pdf", "original_category": "Business Analyst", "extraction_method": "ocr"}, "parsed_education": [], "extracted_skills": ["process improvement", "project management"], "parsed_summary": "Kaitlyn Riley Business Details Profile Address Dedicated Business Analyst with a strong understanding of finance, operational New York, NY proficiency, and business development. Adept in project management and trend analysis. United States Committed to gaining extensive knowledge of the structure, policies, and operations of an organization, to properly recommend solutions that improve business processes. Phone 917-678-5454 Email Employment History kaitlyn_rianalyst@gmail.com Business Analyst, L", "personal_info": {"phone": "917-678-5454", "first_name": null, "last_name": null}}
{"cv_id": "0d0d565220bd4a5c", "target_role": "SAP Developer", "score": 2, "cv_text": "Kaitlyn Riley Business Details Profile Address Dedicated Business Analyst with a strong understanding of finance, operational New York, NY proficiency, and business development. Adept in project management and trend analysis. United States Committed to gaining extensive knowledge of the structure, policies, and operations of an organization, to properly recommend solutions that improve business processes. Phone 917-678-5454 Email Employment History kaitlyn_rianalyst@gmail.com Business Analyst, Lexagon Jun 2019 — Present New York Ski | Is e Steadily provide direct support to process improvement in customer service operations. Business Development and e Analyze, define, and develop complex business process methods to simplify and Management improve the customer experience for this busy recruiting firm of 80 associates. eooee e Work directly with business users to understand requirements and expectations, Leadership while making recommendations for business and process improvements. ec0e0e0d e Research best business practices both internally and externally to establish benchmark data. Problem Solving e Build test scripts to thoroughly test the accuracy of loaded data. ore SS e Assist in the financial analysis and due diligence process for key projects, helping to Attention to Detail cut costs by 40% in my first year of employment alone. @eeee e Evaluate existing processes, and recommend optimal solutions and improvements. Interpersonal Skills ecoee0ed Finance and Accounting Ed ucation ecoee0d NYU, Leonard N. Stern School of Business, Bachelor of Science, Finance Sep 2015 — May 2019 New York Languages . e Overall GPA: 3.65; Major GPA: 3.89 English ecoeeo0d Spanish; Castilian Internships ecoec0e French Business Technology Intern, Muher Technologies renc ecco Oct 2018 — Jun 2019 New York", "metadata": {"filename": "0d0d565220bd4a5c.pdf", "original_category": "Business Analyst", "extraction_method": "ocr"}, "parsed_education": [], "extracted_skills": ["process improvement", "project management"], "parsed_summary": "Kaitlyn Riley Business Details Profile Address Dedicated Business Analyst with a strong understanding of finance, operational New York, NY proficiency, and business development. Adept in project management and trend analysis. United States Committed to gaining extensive knowledge of the structure, policies, and operations of an organization, to properly recommend solutions that improve business processes. Phone 917-678-5454 Email Employment History kaitlyn_rianalyst@gmail.com Business Analyst, L", "personal_info": {"phone": "917-678-5454", "first_name": null, "last_name": null}}
{"cv_id": "0d0d565220bd4a5c", "target_role": "Tester", "score": 0, "cv_text": "Kaitlyn Riley Business Details Profile Address Dedicated Business Analyst with a strong understanding of finance, operational New York, NY proficiency, and business development. Adept in project management and trend analysis. United States Committed to gaining extensive knowledge of the structure, policies, and operations of an organization, to properly recommend solutions that improve business processes. Phone 917-678-5454 Email Employment History kaitlyn_rianalyst@gmail.com Business Analyst, Lexagon Jun 2019 — Present New York Ski | Is e Steadily provide direct support to process improvement in customer service operations. Business Development and e Analyze, define, and develop complex business process methods to simplify and Management improve the customer experience for this busy recruiting firm of 80 associates. eooee e Work directly with business users to understand requirements and expectations, Leadership while making recommendations for business and process improvements. ec0e0e0d e Research best business practices both internally and externally to establish benchmark data. Problem Solving e Build test scripts to thoroughly test the accuracy of loaded data. ore SS e Assist in the financial analysis and due diligence process for key projects, helping to Attention to Detail cut costs by 40% in my first year of employment alone. @eeee e Evaluate existing processes, and recommend optimal solutions and improvements. Interpersonal Skills ecoee0ed Finance and Accounting Ed ucation ecoee0d NYU, Leonard N. Stern School of Business, Bachelor of Science, Finance Sep 2015 — May 2019 New York Languages . e Overall GPA: 3.65; Major GPA: 3.89 English ecoeeo0d Spanish; Castilian Internships ecoec0e French Business Technology Intern, Muher Technologies renc ecco Oct 2018 — Jun 2019 New York", "metadata": {"filename": "0d0d565220bd4a5c.pdf", "original_category": "Business Analyst", "extraction_method": "ocr"}, "parsed_education": [], "extracted_skills": ["process improvement", "project management"], "parsed_summary": "Kaitlyn Riley Business Details Profile Address Dedicated Business Analyst with a strong understanding of finance, operational New York, NY proficiency, and business development. Adept in project management and trend analysis. United States Committed to gaining extensive knowledge of the structure, policies, and operations of an organization, to properly recommend solutions that improve business processes. Phone 917-678-5454 Email Employment History kaitlyn_rianalyst@gmail.com Business Analyst, L", "personal_info": {"phone": "917-678-5454", "first_name": null, "last_name": null}}
{"cv_id": "125e8e373621d730", "target_role": "Business Analyst", "score": 5, "cv_text": "Junior Business tCVv Isabella G. GARCIA 989 S. Woodrow Lane Atlanta, GA 30125 Cell: 404-888-4539 ‘Apostion as a Junior Business Analyst where | can make use of my technical and Management skills in delivering effective business services in a major IT firm’. Summary of Skills: «Indepth of system development life-cyck, project planning techniques and «Advance technical knowledge with good understanding of business processes «Comprehensive knowledge of presentation software, word processing software and spreadsheet *Knowledge of computer service architectures, HTML and Internet research +Excefient project management and critical thinking skills «Good communcator, excellent interpersonal skills and ability to work effectively with less supervsion «Possess strong analytical and troubleshooting skilis Ability to work under pressure with multitasking skills Professional Ex; e; Hay Yards Solutions, Georgina June 2005 till date Junior Business Analyst «Responsible for generating innovative solutions to bridge the gap between business and IT «Performs the tasks of gathering, analyzing and storing information *Handies the responsibilities of analyzing and documenting business requirements «Assist Senior Business Analyst in planning, designing, programming, testing and «Responsible for generating accurate data on company performance, project expense, user behavior, and employment rates", "metadata": {"filename": "125e8e373621d730.pdf", "original_category": "Business Analyst", "extraction_method": "ocr"}, "parsed_education": [], "extracted_skills": ["HTML", "word", "project management"], "parsed_summary": " of Skills : Indepth of system development life-cyck, project planning techniques and Advance technical knowledge with good understanding of business processes Comprehensive knowledge of presentation software, word processing software and spreadsheet *Knowledge of computer service architectures, HTML and Internet research +Excefient project management and critical thinking skills Good communcator, excellent interpersonal skills and ability to work effectively with less supervsion Possess strong analytical and troubleshooting skilis Ability to work under pressure with multitasking skills Professional Ex; e; Hay Yards Solutions, Georgina June 2005 till date Junior Business Analyst Responsible for generating innovative solutions to bridge the gap between business and IT Performs the tasks of gathering, analyzing and storing information *Handies the responsibilities of analyzing and documenting business requirements Assist Senior Business Analyst in planning, designing, programming, testing and Responsible for generating accurate data on company performance, project expense, user behavior, and employment rates", "personal_info": {"phone": "404-888-4539", "first_name": "tCVv", "last_name": "Isabella G. GARCIA"}}
{"cv_id": "125e8e373621d730", "target_role": "Data Scientist", "score": 1, "cv_text": "Junior Business tCVv Isabella G. GARCIA 989 S. Woodrow Lane Atlanta, GA 30125 Cell: 404-888-4539 ‘Apostion as a Junior Business Analyst where | can make use of my technical and Management skills in delivering effective business services in a major IT firm’. Summary of Skills: «Indepth of system development life-cyck, project planning techniques and «Advance technical knowledge with good understanding of business processes «Comprehensive knowledge of presentation software, word processing software and spreadsheet *Knowledge of computer service architectures, HTML and Internet research +Excefient project management and critical thinking skills «Good communcator, excellent interpersonal skills and ability to work effectively with less supervsion «Possess strong analytical and troubleshooting skilis Ability to work under pressure with multitasking skills Professional Ex; e; Hay Yards Solutions, Georgina June 2005 till date Junior Business Analyst «Responsible for generating innovative solutions to bridge the gap between business and IT «Performs the tasks of gathering, analyzing and storing information *Handies the responsibilities of analyzing and documenting business requirements «Assist Senior Business Analyst in planning, designing, programming, testing and «Responsible for generating accurate data on company performance, project expense, user behavior, and employment rates", "metadata": {"filename": "125e8e373621d730.pdf", "original_category": "Business Analyst", "extraction_method": "ocr"}, "parsed_education": [], "extracted_skills": ["HTML", "word", "project management"], "parsed_summary": " of Skills : Indepth of system development life-cyck, project planning techniques and Advance technical knowledge with good understanding of business processes Comprehensive knowledge of presentation software, word processing software and spreadsheet *Knowledge of computer service architectures, HTML and Internet research +Excefient project management and critical thinking skills Good communcator, excellent interpersonal skills and ability to work effectively with less supervsion Possess strong analytical and troubleshooting skilis Ability to work under pressure with multitasking skills Professional Ex; e; Hay Yards Solutions, Georgina June 2005 till date Junior Business Analyst Responsible for generating innovative solutions to bridge the gap between business and IT Performs the tasks of gathering, analyzing and storing information *Handies the responsibilities of analyzing and documenting business requirements Assist Senior Business Analyst in planning, designing, programming, testing and Responsible for generating accurate data on company performance, project expense, user behavior, and employment rates", "personal_info": {"phone": "404-888-4539", "first_name": "tCVv", "last_name": "Isabella G. GARCIA"}}
{"cv_id": "125e8e373621d730", "target_role": "DevOps Engineer", "score": 0, "cv_text": "Junior Business tCVv Isabella G. GARCIA 989 S. Woodrow Lane Atlanta, GA 30125 Cell: 404-888-4539 ‘Apostion as a Junior Business Analyst where | can make use of my technical and Management skills in delivering effective business services in a major IT firm’. Summary of Skills: «Indepth of system development life-cyck, project planning techniques and «Advance technical knowledge with good understanding of business processes «Comprehensive knowledge of presentation software, word processing software and spreadsheet *Knowledge of computer service architectures, HTML and Internet research +Excefient project management and critical thinking skills «Good communcator, excellent interpersonal skills and ability to work effectively with less supervsion «Possess strong analytical and troubleshooting skilis Ability to work under pressure with multitasking skills Professional Ex; e; Hay Yards Solutions, Georgina June 2005 till date Junior Business Analyst «Responsible for generating innovative solutions to bridge the gap between business and IT «Performs the tasks of gathering, analyzing and storing information *Handies the responsibilities of analyzing and documenting business requirements «Assist Senior Business Analyst in planning, designing, programming, testing and «Responsible for generating accurate data on company performance, project expense, user behavior, and employment rates", "metadata": {"filename": "125e8e373621d730.pdf", "original_category": "Business Analyst", "extraction_method": "ocr"}, "parsed_education": [], "extracted_skills": ["HTML", "word", "project management"], "parsed_summary": " of Skills : Indepth of system development life-cyck, project planning techniques and Advance technical knowledge with good understanding of business processes Comprehensive knowledge of presentation software, word processing software and spreadsheet *Knowledge of computer service architectures, HTML and Internet research +Excefient project management and critical thinking skills Good communcator, excellent interpersonal skills and ability to work effectively with less supervsion Possess strong analytical and troubleshooting skilis Ability to work under pressure with multitasking skills Professional Ex; e; Hay Yards Solutions, Georgina June 2005 till date Junior Business Analyst Responsible for generating innovative solutions to bridge the gap between business and IT Performs the tasks of gathering, analyzing and storing information *Handies the responsibilities of analyzing and documenting business requirements Assist Senior Business Analyst in planning, designing, programming, testing and Responsible for generating accurate data on company performance, project expense, user behavior, and employment rates", "personal_info": {"phone": "404-888-4539", "first_name": "tCVv", "last_name": "Isabella G. GARCIA"}}
{"cv_id": "125e8e373621d730", "target_role": "ETL Developer", "score": 0, "cv_text": "Junior Business tCVv Isabella G. GARCIA 989 S. Woodrow Lane Atlanta, GA 30125 Cell: 404-888-4539 ‘Apostion as a Junior Business Analyst where | can make use of my technical and Management skills in delivering effective business services in a major IT firm’. Summary of Skills: «Indepth of system development life-cyck, project planning techniques and «Advance technical knowledge with good understanding of business processes «Comprehensive knowledge of presentation software, word processing software and spreadsheet *Knowledge of computer service architectures, HTML and Internet research +Excefient project management and critical thinking skills «Good communcator, excellent interpersonal skills and ability to work effectively with less supervsion «Possess strong analytical and troubleshooting skilis Ability to work under pressure with multitasking skills Professional Ex; e; Hay Yards Solutions, Georgina June 2005 till date Junior Business Analyst «Responsible for generating innovative solutions to bridge the gap between business and IT «Performs the tasks of gathering, analyzing and storing information *Handies the responsibilities of analyzing and documenting business requirements «Assist Senior Business Analyst in planning, designing, programming, testing and «Responsible for generating accurate data on company performance, project expense, user behavior, and employment rates", "metadata": {"filename": "125e8e373621d730.pdf", "original_category": "Business Analyst", "extraction_method": "ocr"}, "parsed_education": [], "extracted_skills": ["HTML", "word", "project management"], "parsed_summary": " of Skills : Indepth of system development life-cyck, project planning techniques and Advance technical knowledge with good understanding of business processes Comprehensive knowledge of presentation software, word processing software and spreadsheet *Knowledge of computer service architectures, HTML and Internet research +Excefient project management and critical thinking skills Good communcator, excellent interpersonal skills and ability to work effectively with less supervsion Possess strong analytical and troubleshooting skilis Ability to work under pressure with multitasking skills Professional Ex; e; Hay Yards Solutions, Georgina June 2005 till date Junior Business Analyst Responsible for generating innovative solutions to bridge the gap between business and IT Performs the tasks of gathering, analyzing and storing information *Handies the responsibilities of analyzing and documenting business requirements Assist Senior Business Analyst in planning, designing, programming, testing and Responsible for generating accurate data on company performance, project expense, user behavior, and employment rates", "personal_info": {"phone": "404-888-4539", "first_name": "tCVv", "last_name": "Isabella G. GARCIA"}}
{"cv_id": "125e8e373621d730", "target_role": "Java Developer", "score": 0, "cv_text": "Junior Business tCVv Isabella G. GARCIA 989 S. Woodrow Lane Atlanta, GA 30125 Cell: 404-888-4539 ‘Apostion as a Junior Business Analyst where | can make use of my technical and Management skills in delivering effective business services in a major IT firm’. Summary of Skills: «Indepth of system development life-cyck, project planning techniques and «Advance technical knowledge with good understanding of business processes «Comprehensive knowledge of presentation software, word processing software and spreadsheet *Knowledge of computer service architectures, HTML and Internet research +Excefient project management and critical thinking skills «Good communcator, excellent interpersonal skills and ability to work effectively with less supervsion «Possess strong analytical and troubleshooting skilis Ability to work under pressure with multitasking skills Professional Ex; e; Hay Yards Solutions, Georgina June 2005 till date Junior Business Analyst «Responsible for generating innovative solutions to bridge the gap between business and IT «Performs the tasks of gathering, analyzing and storing information *Handies the responsibilities of analyzing and documenting business requirements «Assist Senior Business Analyst in planning, designing, programming, testing and «Responsible for generating accurate data on company performance, project expense, user behavior, and employment rates", "metadata": {"filename": "125e8e373621d730.pdf", "original_category": "Business Analyst", "extraction_method": "ocr"}, "parsed_education": [], "extracted_skills": ["HTML", "word", "project management"], "parsed_summary": " of Skills : Indepth of system development life-cyck, project planning techniques and Advance technical knowledge with good understanding of business processes Comprehensive knowledge of presentation software, word processing software and spreadsheet *Knowledge of computer service architectures, HTML and Internet research +Excefient project management and critical thinking skills Good communcator, excellent interpersonal skills and ability to work effectively with less supervsion Possess strong analytical and troubleshooting skilis Ability to work under pressure with multitasking skills Professional Ex; e; Hay Yards Solutions, Georgina June 2005 till date Junior Business Analyst Responsible for generating innovative solutions to bridge the gap between business and IT Performs the tasks of gathering, analyzing and storing information *Handies the responsibilities of analyzing and documenting business requirements Assist Senior Business Analyst in planning, designing, programming, testing and Responsible for generating accurate data on company performance, project expense, user behavior, and employment rates", "personal_info": {"phone": "404-888-4539", "first_name": "tCVv", "last_name": "Isabella G. GARCIA"}}
{"cv_id": "125e8e373621d730", "target_role": "Python Developer", "score": 0, "cv_text": "Junior Business tCVv Isabella G. GARCIA 989 S. Woodrow Lane Atlanta, GA 30125 Cell: 404-888-4539 ‘Apostion as a Junior Business Analyst where | can make use of my technical and Management skills in delivering effective business services in a major IT firm’. Summary of Skills: «Indepth of system development life-cyck, project planning techniques and «Advance technical knowledge with good understanding of business processes «Comprehensive knowledge of presentation software, word processing software and spreadsheet *Knowledge of computer service architectures, HTML and Internet research +Excefient project management and critical thinking skills «Good communcator, excellent interpersonal skills and ability to work effectively with less supervsion «Possess strong analytical and troubleshooting skilis Ability to work under pressure with multitasking skills Professional Ex; e; Hay Yards Solutions, Georgina June 2005 till date Junior Business Analyst «Responsible for generating innovative solutions to bridge the gap between business and IT «Performs the tasks of gathering, analyzing and storing information *Handies the responsibilities of analyzing and documenting business requirements «Assist Senior Business Analyst in planning, designing, programming, testing and «Responsible for generating accurate data on company performance, project expense, user behavior, and employment rates", "metadata": {"filename": "125e8e373621d730.pdf", "original_category": "Business Analyst", "extraction_method": "ocr"}, "parsed_education": [], "extracted_skills": ["HTML", "word", "project management"], "parsed_summary": " of Skills : Indepth of system development life-cyck, project planning techniques and Advance technical knowledge with good understanding of business processes Comprehensive knowledge of presentation software, word processing software and spreadsheet *Knowledge of computer service architectures, HTML and Internet research +Excefient project management and critical thinking skills Good communcator, excellent interpersonal skills and ability to work effectively with less supervsion Possess strong analytical and troubleshooting skilis Ability to work under pressure with multitasking skills Professional Ex; e; Hay Yards Solutions, Georgina June 2005 till date Junior Business Analyst Responsible for generating innovative solutions to bridge the gap between business and IT Performs the tasks of gathering, analyzing and storing information *Handies the responsibilities of analyzing and documenting business requirements Assist Senior Business Analyst in planning, designing, programming, testing and Responsible for generating accurate data on company performance, project expense, user behavior, and employment rates", "personal_info": {"phone": "404-888-4539", "first_name": "tCVv", "last_name": "Isabella G. GARCIA"}}
{"cv_id": "125e8e373621d730", "target_role": "React Developer", "score": 0, "cv_text": "Junior Business tCVv Isabella G. GARCIA 989 S. Woodrow Lane Atlanta, GA 30125 Cell: 404-888-4539 ‘Apostion as a Junior Business Analyst where | can make use of my technical and Management skills in delivering effective business services in a major IT firm’. Summary of Skills: «Indepth of system development life-cyck, project planning techniques and «Advance technical knowledge with good understanding of business processes «Comprehensive knowledge of presentation software, word processing software and spreadsheet *Knowledge of computer service architectures, HTML and Internet research +Excefient project management and critical thinking skills «Good communcator, excellent interpersonal skills and ability to work effectively with less supervsion «Possess strong analytical and troubleshooting skilis Ability to work under pressure with multitasking skills Professional Ex; e; Hay Yards Solutions, Georgina June 2005 till date Junior Business Analyst «Responsible for generating innovative solutions to bridge the gap between business and IT «Performs the tasks of gathering, analyzing and storing information *Handies the responsibilities of analyzing and documenting business requirements «Assist Senior Business Analyst in planning, designing, programming, testing and «Responsible for generating accurate data on company performance, project expense, user behavior, and employment rates", "metadata": {"filename": "125e8e373621d730.pdf", "original_category": "Business Analyst", "extraction_method": "ocr"}, "parsed_education": [], "extracted_skills": ["HTML", "word", "project management"], "parsed_summary": " of Skills : Indepth of system development life-cyck, project planning techniques and Advance technical knowledge with good understanding of business processes Comprehensive knowledge of presentation software, word processing software and spreadsheet *Knowledge of computer service architectures, HTML and Internet research +Excefient project management and critical thinking skills Good communcator, excellent interpersonal skills and ability to work effectively with less supervsion Possess strong analytical and troubleshooting skilis Ability to work under pressure with multitasking skills Professional Ex; e; Hay Yards Solutions, Georgina June 2005 till date Junior Business Analyst Responsible for generating innovative solutions to bridge the gap between business and IT Performs the tasks of gathering, analyzing and storing information *Handies the responsibilities of analyzing and documenting business requirements Assist Senior Business Analyst in planning, designing, programming, testing and Responsible for generating accurate data on company performance, project expense, user behavior, and employment rates", "personal_info": {"phone": "404-888-4539", "first_name": "tCVv", "last_name": "Isabella G. GARCIA"}}
{"cv_id": "125e8e373621d730", "target_role": "SQL Developer", "score": 2, "cv_text": "Junior Business tCVv Isabella G. GARCIA 989 S. Woodrow Lane Atlanta, GA 30125 Cell: 404-888-4539 ‘Apostion as a Junior Business Analyst where | can make use of my technical and Management skills in delivering effective business services in a major IT firm’. Summary of Skills: «Indepth of system development life-cyck, project planning techniques and «Advance technical knowledge with good understanding of business processes «Comprehensive knowledge of presentation software, word processing software and spreadsheet *Knowledge of computer service architectures, HTML and Internet research +Excefient project management and critical thinking skills «Good communcator, excellent interpersonal skills and ability to work effectively with less supervsion «Possess strong analytical and troubleshooting skilis Ability to work under pressure with multitasking skills Professional Ex; e; Hay Yards Solutions, Georgina June 2005 till date Junior Business Analyst «Responsible for generating innovative solutions to bridge the gap between business and IT «Performs the tasks of gathering, analyzing and storing information *Handies the responsibilities of analyzing and documenting business requirements «Assist Senior Business Analyst in planning, designing, programming, testing and «Responsible for generating accurate data on company performance, project expense, user behavior, and employment rates", "metadata": {"filename": "125e8e373621d730.pdf", "original_category": "Business Analyst", "extraction_method": "ocr"}, "parsed_education": [], "extracted_skills": ["HTML", "word", "project management"], "parsed_summary": " of Skills : Indepth of system development life-cyck, project planning techniques and Advance technical knowledge with good understanding of business processes Comprehensive knowledge of presentation software, word processing software and spreadsheet *Knowledge of computer service architectures, HTML and Internet research +Excefient project management and critical thinking skills Good communcator, excellent interpersonal skills and ability to work effectively with less supervsion Possess strong analytical and troubleshooting skilis Ability to work under pressure with multitasking skills Professional Ex; e; Hay Yards Solutions, Georgina June 2005 till date Junior Business Analyst Responsible for generating innovative solutions to bridge the gap between business and IT Performs the tasks of gathering, analyzing and storing information *Handies the responsibilities of analyzing and documenting business requirements Assist Senior Business Analyst in planning, designing, programming, testing and Responsible for generating accurate data on company performance, project expense, user behavior, and employment rates", "personal_info": {"phone": "404-888-4539", "first_name": "tCVv", "last_name": "Isabella G. GARCIA"}}
{"cv_id": "125e8e373621d730", "target_role": "Web Developer", "score": 0, "cv_text": "Junior Business tCVv Isabella G. GARCIA 989 S. Woodrow Lane Atlanta, GA 30125 Cell: 404-888-4539 ‘Apostion as a Junior Business Analyst where | can make use of my technical and Management skills in delivering effective business services in a major IT firm’. Summary of Skills: «Indepth of system development life-cyck, project planning techniques and «Advance technical knowledge with good understanding of business processes «Comprehensive knowledge of presentation software, word processing software and spreadsheet *Knowledge of computer service architectures, HTML and Internet research +Excefient project management and critical thinking skills «Good communcator, excellent interpersonal skills and ability to work effectively with less supervsion «Possess strong analytical and troubleshooting skilis Ability to work under pressure with multitasking skills Professional Ex; e; Hay Yards Solutions, Georgina June 2005 till date Junior Business Analyst «Responsible for generating innovative solutions to bridge the gap between business and IT «Performs the tasks of gathering, analyzing and storing information *Handies the responsibilities of analyzing and documenting business requirements «Assist Senior Business Analyst in planning, designing, programming, testing and «Responsible for generating accurate data on company performance, project expense, user behavior, and employment rates", "metadata": {"filename": "125e8e373621d730.pdf", "original_category": "Business Analyst", "extraction_method": "ocr"}, "parsed_education": [], "extracted_skills": ["HTML", "word", "project management"], "parsed_summary": " of Skills : Indepth of system development life-cyck, project planning techniques and Advance technical knowledge with good understanding of business processes Comprehensive knowledge of presentation software, word processing software and spreadsheet *Knowledge of computer service architectures, HTML and Internet research +Excefient project management and critical thinking skills Good communcator, excellent interpersonal skills and ability to work effectively with less supervsion Possess strong analytical and troubleshooting skilis Ability to work under pressure with multitasking skills Professional Ex; e; Hay Yards Solutions, Georgina June 2005 till date Junior Business Analyst Responsible for generating innovative solutions to bridge the gap between business and IT Performs the tasks of gathering, analyzing and storing information *Handies the responsibilities of analyzing and documenting business requirements Assist Senior Business Analyst in planning, designing, programming, testing and Responsible for generating accurate data on company performance, project expense, user behavior, and employment rates", "personal_info": {"phone": "404-888-4539", "first_name": "tCVv", "last_name": "Isabella G. GARCIA"}}
{"cv_id": "125e8e373621d730", "target_role": "SAP Developer", "score": 2, "cv_text": "Junior Business tCVv Isabella G. GARCIA 989 S. Woodrow Lane Atlanta, GA 30125 Cell: 404-888-4539 ‘Apostion as a Junior Business Analyst where | can make use of my technical and Management skills in delivering effective business services in a major IT firm’. Summary of Skills: «Indepth of system development life-cyck, project planning techniques and «Advance technical knowledge with good understanding of business processes «Comprehensive knowledge of presentation software, word processing software and spreadsheet *Knowledge of computer service architectures, HTML and Internet research +Excefient project management and critical thinking skills «Good communcator, excellent interpersonal skills and ability to work effectively with less supervsion «Possess strong analytical and troubleshooting skilis Ability to work under pressure with multitasking skills Professional Ex; e; Hay Yards Solutions, Georgina June 2005 till date Junior Business Analyst «Responsible for generating innovative solutions to bridge the gap between business and IT «Performs the tasks of gathering, analyzing and storing information *Handies the responsibilities of analyzing and documenting business requirements «Assist Senior Business Analyst in planning, designing, programming, testing and «Responsible for generating accurate data on company performance, project expense, user behavior, and employment rates", "metadata": {"filename": "125e8e373621d730.pdf", "original_category": "Business Analyst", "extraction_method": "ocr"}, "parsed_education": [], "extracted_skills": ["HTML", "word", "project management"], "parsed_summary": " of Skills : Indepth of system development life-cyck, project planning techniques and Advance technical knowledge with good understanding of business processes Comprehensive knowledge of presentation software, word processing software and spreadsheet *Knowledge of computer service architectures, HTML and Internet research +Excefient project management and critical thinking skills Good communcator, excellent interpersonal skills and ability to work effectively with less supervsion Possess strong analytical and troubleshooting skilis Ability to work under pressure with multitasking skills Professional Ex; e; Hay Yards Solutions, Georgina June 2005 till date Junior Business Analyst Responsible for generating innovative solutions to bridge the gap between business and IT Performs the tasks of gathering, analyzing and storing information *Handies the responsibilities of analyzing and documenting business requirements Assist Senior Business Analyst in planning, designing, programming, testing and Responsible for generating accurate data on company performance, project expense, user behavior, and employment rates", "personal_info": {"phone": "404-888-4539", "first_name": "tCVv", "last_name": "Isabella G. GARCIA"}}
{"cv_id": "125e8e373621d730", "target_role": "Tester", "score": 0, "cv_text": "Junior Business tCVv Isabella G. GARCIA 989 S. Woodrow Lane Atlanta, GA 30125 Cell: 404-888-4539 ‘Apostion as a Junior Business Analyst where | can make use of my technical and Management skills in delivering effective business services in a major IT firm’. Summary of Skills: «Indepth of system development life-cyck, project planning techniques and «Advance technical knowledge with good understanding of business processes «Comprehensive knowledge of presentation software, word processing software and spreadsheet *Knowledge of computer service architectures, HTML and Internet research +Excefient project management and critical thinking skills «Good communcator, excellent interpersonal skills and ability to work effectively with less supervsion «Possess strong analytical and troubleshooting skilis Ability to work under pressure with multitasking skills Professional Ex; e; Hay Yards Solutions, Georgina June 2005 till date Junior Business Analyst «Responsible for generating innovative solutions to bridge the gap between business and IT «Performs the tasks of gathering, analyzing and storing information *Handies the responsibilities of analyzing and documenting business requirements «Assist Senior Business Analyst in planning, designing, programming, testing and «Responsible for generating accurate data on company performance, project expense, user behavior, and employment rates", "metadata": {"filename": "125e8e373621d730.pdf", "original_category": "Business Analyst", "extraction_method": "ocr"}, "parsed_education": [], "extracted_skills": ["HTML", "word", "project management"], "parsed_summary": " of Skills : Indepth of system development life-cyck, project planning techniques and Advance technical knowledge with good understanding of business processes Comprehensive knowledge of presentation software, word processing software and spreadsheet *Knowledge of computer service architectures, HTML and Internet research +Excefient project management and critical thinking skills Good communcator, excellent interpersonal skills and ability to work effectively with less supervsion Possess strong analytical and troubleshooting skilis Ability to work under pressure with multitasking skills Professional Ex; e; Hay Yards Solutions, Georgina June 2005 till date Junior Business Analyst Responsible for generating innovative solutions to bridge the gap between business and IT Performs the tasks of gathering, analyzing and storing information *Handies the responsibilities of analyzing and documenting business requirements Assist Senior Business Analyst in planning, designing, programming, testing and Responsible for generating accurate data on company performance, project expense, user behavior, and employment rates", "personal_info": {"phone": "404-888-4539", "first_name": "tCVv", "last_name": "Isabella G. GARCIA"}}
{"cv_id": "12706334e4122045", "target_role": "Business Analyst", "score": 5, "cv_text": "MICHEAL POLLARD Junior Business Analyst - Providing Data Management and Analysis for Strategic Decision-Making \\ +1-503-628-8758 @help@enhancv.com- © linkedin.com SUMMARY Junior Business Analyst with 3+ of years of experience in customer-focused, dynamic environment. Highly apt at seeing beyond the numbers to provide systematic solutions to increase profit margins by an AVG of 20K/ year. Ability to listen with intent to the customer problems to gather data and find solutions to individual problems. Built a 5000+ customer database through the years, based on loyalty and respect. EXPERIENCE Junior Business Analyst Carroll €3 2020- Ongoing 9 Dallas, TX Carroll is the global leader in cloud-based sales, marketing, learning, and customer experience solutions. + Increased gross revenue of 15% in 2021 (compared to 2020) with no change to fixed costs with data-oriented, customer-centric solutions + Automated manual review process using excel that saved around 1- hour of work per week + Expanded BI Audience by an additional 200+ users by offering new insights and features to the business Research Associate & Intern Business Analyst Grimes 2019-2020 9 Dallas, TX Grimes is the alternative within top-tier executive search and part of the global top-10 executive search firm TRANSEARCH International - one of the leading executive search and leadership advisory organizations in the world. + Improved internal processes by creating manuals to cut back on training time by 30% + Reduced IPS (Customer Issues) by 2.2% while impacting merely 3% of GMV - Supported sales to achieve 132% and 162% quota in 2019 and 2020 Sales Associate Borer Ltd @§ 2018-2019 9 Bronx. NY Borer Ltd is an affiliate brand mainly focused on audience based programmatic display marketing. + Exceeded the incremental spend target by 120% due to providing personalized and customer-focused information + Turned 2500+ cold leads into customers by offering them solutions to their problems and listening carefully to their concerns + Helped with 150+ product launches by making cold calls, collecting and analyzing customer data TRAINING / COURSES Microsoft Excel Expert Data Analysis for Decision- (Excel and Excel 2019) Making Microsoft edxX Google Data Analytics Professional Certificate Coursera www.enhancv.com 9 Dallas, TX SKILLS Bl Data Analysis © MSO Client Management Sales Targets Cold Calling Lead Generation EDUCATION Bachelor of Science in Business and Political Economy New York University &4) 2014 - 2018 9 Manhattan, NY STRENGTHS Data Management Systematic approach towards systematizing and analyzing data with Macros in Excel. Providing growth- focused solutions, increasing profit margins by at least 25%/ year. Customer Growth by 15K/ Year Knowledge of specific niches to implement business growth solutions: from product launches to lead generation. Accumulating a loyal customer base, responsible for the 30% expansion of the business within the past year. Product Expansion Using systematized data to provide opportunities with a focus on enhancing the overall customer experience by an annual AVG of 65%. ACHIEVEMENTS f Successful launch of 100+ new products Solely through the past 2 years, have provided data-focused solutions to increase sales on new unites by 45%. High Achiever Q4 2021 Received the company-wide recognition for helping the sales team surpass their targets by 150%. Powered by (XZ Enhancy", "metadata": {"filename": "12706334e4122045.pdf", "original_category": "Business Analyst", "extraction_method": "ocr"}, "parsed_education": [{"degree": "BACHELOR", "institution": null, "years": "2014 - 2018", "field_of_study": "Unknown"}], "extracted_skills": ["excel", "Decision-Making", "Excel"], "parsed_summary": " Junior Business Analyst with 3+ of years of", "personal_info": {"phone": "+1-503-628-8758", "first_name": null, "last_name": null}}
{"cv_id": "12706334e4122045", "target_role": "Data Scientist", "score": 1, "cv_text": "MICHEAL POLLARD Junior Business Analyst - Providing Data Management and Analysis for Strategic Decision-Making \\ +1-503-628-8758 @help@enhancv.com- © linkedin.com SUMMARY Junior Business Analyst with 3+ of years of experience in customer-focused, dynamic environment. Highly apt at seeing beyond the numbers to provide systematic solutions to increase profit margins by an AVG of 20K/ year. Ability to listen with intent to the customer problems to gather data and find solutions to individual problems. Built a 5000+ customer database through the years, based on loyalty and respect. EXPERIENCE Junior Business Analyst Carroll €3 2020- Ongoing 9 Dallas, TX Carroll is the global leader in cloud-based sales, marketing, learning, and customer experience solutions. + Increased gross revenue of 15% in 2021 (compared to 2020) with no change to fixed costs with data-oriented, customer-centric solutions + Automated manual review process using excel that saved around 1- hour of work per week + Expanded BI Audience by an additional 200+ users by offering new insights and features to the business Research Associate & Intern Business Analyst Grimes 2019-2020 9 Dallas, TX Grimes is the alternative within top-tier executive search and part of the global top-10 executive search firm TRANSEARCH International - one of the leading executive search and leadership advisory organizations in the world. + Improved internal processes by creating manuals to cut back on training time by 30% + Reduced IPS (Customer Issues) by 2.2% while impacting merely 3% of GMV - Supported sales to achieve 132% and 162% quota in 2019 and 2020 Sales Associate Borer Ltd @§ 2018-2019 9 Bronx. NY Borer Ltd is an affiliate brand mainly focused on audience based programmatic display marketing. + Exceeded the incremental spend target by 120% due to providing personalized and customer-focused information + Turned 2500+ cold leads into customers by offering them solutions to their problems and listening carefully to their concerns + Helped with 150+ product launches by making cold calls, collecting and analyzing customer data TRAINING / COURSES Microsoft Excel Expert Data Analysis for Decision- (Excel and Excel 2019) Making Microsoft edxX Google Data Analytics Professional Certificate Coursera www.enhancv.com 9 Dallas, TX SKILLS Bl Data Analysis © MSO Client Management Sales Targets Cold Calling Lead Generation EDUCATION Bachelor of Science in Business and Political Economy New York University &4) 2014 - 2018 9 Manhattan, NY STRENGTHS Data Management Systematic approach towards systematizing and analyzing data with Macros in Excel. Providing growth- focused solutions, increasing profit margins by at least 25%/ year. Customer Growth by 15K/ Year Knowledge of specific niches to implement business growth solutions: from product launches to lead generation. Accumulating a loyal customer base, responsible for the 30% expansion of the business within the past year. Product Expansion Using systematized data to provide opportunities with a focus on enhancing the overall customer experience by an annual AVG of 65%. ACHIEVEMENTS f Successful launch of 100+ new products Solely through the past 2 years, have provided data-focused solutions to increase sales on new unites by 45%. High Achiever Q4 2021 Received the company-wide recognition for helping the sales team surpass their targets by 150%. Powered by (XZ Enhancy", "metadata": {"filename": "12706334e4122045.pdf", "original_category": "Business Analyst", "extraction_method": "ocr"}, "parsed_education": [{"degree": "BACHELOR", "institution": null, "years": "2014 - 2018", "field_of_study": "Unknown"}], "extracted_skills": ["excel", "Decision-Making", "Excel"], "parsed_summary": " Junior Business Analyst with 3+ of years of", "personal_info": {"phone": "+1-503-628-8758", "first_name": null, "last_name": null}}
{"cv_id": "12706334e4122045", "target_role": "DevOps Engineer", "score": 0, "cv_text": "MICHEAL POLLARD Junior Business Analyst - Providing Data Management and Analysis for Strategic Decision-Making \\ +1-503-628-8758 @help@enhancv.com- © linkedin.com SUMMARY Junior Business Analyst with 3+ of years of experience in customer-focused, dynamic environment. Highly apt at seeing beyond the numbers to provide systematic solutions to increase profit margins by an AVG of 20K/ year. Ability to listen with intent to the customer problems to gather data and find solutions to individual problems. Built a 5000+ customer database through the years, based on loyalty and respect. EXPERIENCE Junior Business Analyst Carroll €3 2020- Ongoing 9 Dallas, TX Carroll is the global leader in cloud-based sales, marketing, learning, and customer experience solutions. + Increased gross revenue of 15% in 2021 (compared to 2020) with no change to fixed costs with data-oriented, customer-centric solutions + Automated manual review process using excel that saved around 1- hour of work per week + Expanded BI Audience by an additional 200+ users by offering new insights and features to the business Research Associate & Intern Business Analyst Grimes 2019-2020 9 Dallas, TX Grimes is the alternative within top-tier executive search and part of the global top-10 executive search firm TRANSEARCH International - one of the leading executive search and leadership advisory organizations in the world. + Improved internal processes by creating manuals to cut back on training time by 30% + Reduced IPS (Customer Issues) by 2.2% while impacting merely 3% of GMV - Supported sales to achieve 132% and 162% quota in 2019 and 2020 Sales Associate Borer Ltd @§ 2018-2019 9 Bronx. NY Borer Ltd is an affiliate brand mainly focused on audience based programmatic display marketing. + Exceeded the incremental spend target by 120% due to providing personalized and customer-focused information + Turned 2500+ cold leads into customers by offering them solutions to their problems and listening carefully to their concerns + Helped with 150+ product launches by making cold calls, collecting and analyzing customer data TRAINING / COURSES Microsoft Excel Expert Data Analysis for Decision- (Excel and Excel 2019) Making Microsoft edxX Google Data Analytics Professional Certificate Coursera www.enhancv.com 9 Dallas, TX SKILLS Bl Data Analysis © MSO Client Management Sales Targets Cold Calling Lead Generation EDUCATION Bachelor of Science in Business and Political Economy New York University &4) 2014 - 2018 9 Manhattan, NY STRENGTHS Data Management Systematic approach towards systematizing and analyzing data with Macros in Excel. Providing growth- focused solutions, increasing profit margins by at least 25%/ year. Customer Growth by 15K/ Year Knowledge of specific niches to implement business growth solutions: from product launches to lead generation. Accumulating a loyal customer base, responsible for the 30% expansion of the business within the past year. Product Expansion Using systematized data to provide opportunities with a focus on enhancing the overall customer experience by an annual AVG of 65%. ACHIEVEMENTS f Successful launch of 100+ new products Solely through the past 2 years, have provided data-focused solutions to increase sales on new unites by 45%. High Achiever Q4 2021 Received the company-wide recognition for helping the sales team surpass their targets by 150%. Powered by (XZ Enhancy", "metadata": {"filename": "12706334e4122045.pdf", "original_category": "Business Analyst", "extraction_method": "ocr"}, "parsed_education": [{"degree": "BACHELOR", "institution": null, "years": "2014 - 2018", "field_of_study": "Unknown"}], "extracted_skills": ["excel", "Decision-Making", "Excel"], "parsed_summary": " Junior Business Analyst with 3+ of years of", "personal_info": {"phone": "+1-503-628-8758", "first_name": null, "last_name": null}}
{"cv_id": "12706334e4122045", "target_role": "ETL Developer", "score": 0, "cv_text": "MICHEAL POLLARD Junior Business Analyst - Providing Data Management and Analysis for Strategic Decision-Making \\ +1-503-628-8758 @help@enhancv.com- © linkedin.com SUMMARY Junior Business Analyst with 3+ of years of experience in customer-focused, dynamic environment. Highly apt at seeing beyond the numbers to provide systematic solutions to increase profit margins by an AVG of 20K/ year. Ability to listen with intent to the customer problems to gather data and find solutions to individual problems. Built a 5000+ customer database through the years, based on loyalty and respect. EXPERIENCE Junior Business Analyst Carroll €3 2020- Ongoing 9 Dallas, TX Carroll is the global leader in cloud-based sales, marketing, learning, and customer experience solutions. + Increased gross revenue of 15% in 2021 (compared to 2020) with no change to fixed costs with data-oriented, customer-centric solutions + Automated manual review process using excel that saved around 1- hour of work per week + Expanded BI Audience by an additional 200+ users by offering new insights and features to the business Research Associate & Intern Business Analyst Grimes 2019-2020 9 Dallas, TX Grimes is the alternative within top-tier executive search and part of the global top-10 executive search firm TRANSEARCH International - one of the leading executive search and leadership advisory organizations in the world. + Improved internal processes by creating manuals to cut back on training time by 30% + Reduced IPS (Customer Issues) by 2.2% while impacting merely 3% of GMV - Supported sales to achieve 132% and 162% quota in 2019 and 2020 Sales Associate Borer Ltd @§ 2018-2019 9 Bronx. NY Borer Ltd is an affiliate brand mainly focused on audience based programmatic display marketing. + Exceeded the incremental spend target by 120% due to providing personalized and customer-focused information + Turned 2500+ cold leads into customers by offering them solutions to their problems and listening carefully to their concerns + Helped with 150+ product launches by making cold calls, collecting and analyzing customer data TRAINING / COURSES Microsoft Excel Expert Data Analysis for Decision- (Excel and Excel 2019) Making Microsoft edxX Google Data Analytics Professional Certificate Coursera www.enhancv.com 9 Dallas, TX SKILLS Bl Data Analysis © MSO Client Management Sales Targets Cold Calling Lead Generation EDUCATION Bachelor of Science in Business and Political Economy New York University &4) 2014 - 2018 9 Manhattan, NY STRENGTHS Data Management Systematic approach towards systematizing and analyzing data with Macros in Excel. Providing growth- focused solutions, increasing profit margins by at least 25%/ year. Customer Growth by 15K/ Year Knowledge of specific niches to implement business growth solutions: from product launches to lead generation. Accumulating a loyal customer base, responsible for the 30% expansion of the business within the past year. Product Expansion Using systematized data to provide opportunities with a focus on enhancing the overall customer experience by an annual AVG of 65%. ACHIEVEMENTS f Successful launch of 100+ new products Solely through the past 2 years, have provided data-focused solutions to increase sales on new unites by 45%. High Achiever Q4 2021 Received the company-wide recognition for helping the sales team surpass their targets by 150%. Powered by (XZ Enhancy", "metadata": {"filename": "12706334e4122045.pdf", "original_category": "Business Analyst", "extraction_method": "ocr"}, "parsed_education": [{"degree": "BACHELOR", "institution": null, "years": "2014 - 2018", "field_of_study": "Unknown"}], "extracted_skills": ["excel", "Decision-Making", "Excel"], "parsed_summary": " Junior Business Analyst with 3+ of years of", "personal_info": {"phone": "+1-503-628-8758", "first_name": null, "last_name": null}}
{"cv_id": "12706334e4122045", "target_role": "Java Developer", "score": 0, "cv_text": "MICHEAL POLLARD Junior Business Analyst - Providing Data Management and Analysis for Strategic Decision-Making \\ +1-503-628-8758 @help@enhancv.com- © linkedin.com SUMMARY Junior Business Analyst with 3+ of years of experience in customer-focused, dynamic environment. Highly apt at seeing beyond the numbers to provide systematic solutions to increase profit margins by an AVG of 20K/ year. Ability to listen with intent to the customer problems to gather data and find solutions to individual problems. Built a 5000+ customer database through the years, based on loyalty and respect. EXPERIENCE Junior Business Analyst Carroll €3 2020- Ongoing 9 Dallas, TX Carroll is the global leader in cloud-based sales, marketing, learning, and customer experience solutions. + Increased gross revenue of 15% in 2021 (compared to 2020) with no change to fixed costs with data-oriented, customer-centric solutions + Automated manual review process using excel that saved around 1- hour of work per week + Expanded BI Audience by an additional 200+ users by offering new insights and features to the business Research Associate & Intern Business Analyst Grimes 2019-2020 9 Dallas, TX Grimes is the alternative within top-tier executive search and part of the global top-10 executive search firm TRANSEARCH International - one of the leading executive search and leadership advisory organizations in the world. + Improved internal processes by creating manuals to cut back on training time by 30% + Reduced IPS (Customer Issues) by 2.2% while impacting merely 3% of GMV - Supported sales to achieve 132% and 162% quota in 2019 and 2020 Sales Associate Borer Ltd @§ 2018-2019 9 Bronx. NY Borer Ltd is an affiliate brand mainly focused on audience based programmatic display marketing. + Exceeded the incremental spend target by 120% due to providing personalized and customer-focused information + Turned 2500+ cold leads into customers by offering them solutions to their problems and listening carefully to their concerns + Helped with 150+ product launches by making cold calls, collecting and analyzing customer data TRAINING / COURSES Microsoft Excel Expert Data Analysis for Decision- (Excel and Excel 2019) Making Microsoft edxX Google Data Analytics Professional Certificate Coursera www.enhancv.com 9 Dallas, TX SKILLS Bl Data Analysis © MSO Client Management Sales Targets Cold Calling Lead Generation EDUCATION Bachelor of Science in Business and Political Economy New York University &4) 2014 - 2018 9 Manhattan, NY STRENGTHS Data Management Systematic approach towards systematizing and analyzing data with Macros in Excel. Providing growth- focused solutions, increasing profit margins by at least 25%/ year. Customer Growth by 15K/ Year Knowledge of specific niches to implement business growth solutions: from product launches to lead generation. Accumulating a loyal customer base, responsible for the 30% expansion of the business within the past year. Product Expansion Using systematized data to provide opportunities with a focus on enhancing the overall customer experience by an annual AVG of 65%. ACHIEVEMENTS f Successful launch of 100+ new products Solely through the past 2 years, have provided data-focused solutions to increase sales on new unites by 45%. High Achiever Q4 2021 Received the company-wide recognition for helping the sales team surpass their targets by 150%. Powered by (XZ Enhancy", "metadata": {"filename": "12706334e4122045.pdf", "original_category": "Business Analyst", "extraction_method": "ocr"}, "parsed_education": [{"degree": "BACHELOR", "institution": null, "years": "2014 - 2018", "field_of_study": "Unknown"}], "extracted_skills": ["excel", "Decision-Making", "Excel"], "parsed_summary": " Junior Business Analyst with 3+ of years of", "personal_info": {"phone": "+1-503-628-8758", "first_name": null, "last_name": null}}
{"cv_id": "12706334e4122045", "target_role": "Python Developer", "score": 0, "cv_text": "MICHEAL POLLARD Junior Business Analyst - Providing Data Management and Analysis for Strategic Decision-Making \\ +1-503-628-8758 @help@enhancv.com- © linkedin.com SUMMARY Junior Business Analyst with 3+ of years of experience in customer-focused, dynamic environment. Highly apt at seeing beyond the numbers to provide systematic solutions to increase profit margins by an AVG of 20K/ year. Ability to listen with intent to the customer problems to gather data and find solutions to individual problems. Built a 5000+ customer database through the years, based on loyalty and respect. EXPERIENCE Junior Business Analyst Carroll €3 2020- Ongoing 9 Dallas, TX Carroll is the global leader in cloud-based sales, marketing, learning, and customer experience solutions. + Increased gross revenue of 15% in 2021 (compared to 2020) with no change to fixed costs with data-oriented, customer-centric solutions + Automated manual review process using excel that saved around 1- hour of work per week + Expanded BI Audience by an additional 200+ users by offering new insights and features to the business Research Associate & Intern Business Analyst Grimes 2019-2020 9 Dallas, TX Grimes is the alternative within top-tier executive search and part of the global top-10 executive search firm TRANSEARCH International - one of the leading executive search and leadership advisory organizations in the world. + Improved internal processes by creating manuals to cut back on training time by 30% + Reduced IPS (Customer Issues) by 2.2% while impacting merely 3% of GMV - Supported sales to achieve 132% and 162% quota in 2019 and 2020 Sales Associate Borer Ltd @§ 2018-2019 9 Bronx. NY Borer Ltd is an affiliate brand mainly focused on audience based programmatic display marketing. + Exceeded the incremental spend target by 120% due to providing personalized and customer-focused information + Turned 2500+ cold leads into customers by offering them solutions to their problems and listening carefully to their concerns + Helped with 150+ product launches by making cold calls, collecting and analyzing customer data TRAINING / COURSES Microsoft Excel Expert Data Analysis for Decision- (Excel and Excel 2019) Making Microsoft edxX Google Data Analytics Professional Certificate Coursera www.enhancv.com 9 Dallas, TX SKILLS Bl Data Analysis © MSO Client Management Sales Targets Cold Calling Lead Generation EDUCATION Bachelor of Science in Business and Political Economy New York University &4) 2014 - 2018 9 Manhattan, NY STRENGTHS Data Management Systematic approach towards systematizing and analyzing data with Macros in Excel. Providing growth- focused solutions, increasing profit margins by at least 25%/ year. Customer Growth by 15K/ Year Knowledge of specific niches to implement business growth solutions: from product launches to lead generation. Accumulating a loyal customer base, responsible for the 30% expansion of the business within the past year. Product Expansion Using systematized data to provide opportunities with a focus on enhancing the overall customer experience by an annual AVG of 65%. ACHIEVEMENTS f Successful launch of 100+ new products Solely through the past 2 years, have provided data-focused solutions to increase sales on new unites by 45%. High Achiever Q4 2021 Received the company-wide recognition for helping the sales team surpass their targets by 150%. Powered by (XZ Enhancy", "metadata": {"filename": "12706334e4122045.pdf", "original_category": "Business Analyst", "extraction_method": "ocr"}, "parsed_education": [{"degree": "BACHELOR", "institution": null, "years": "2014 - 2018", "field_of_study": "Unknown"}], "extracted_skills": ["excel", "Decision-Making", "Excel"], "parsed_summary": " Junior Business Analyst with 3+ of years of", "personal_info": {"phone": "+1-503-628-8758", "first_name": null, "last_name": null}}
{"cv_id": "12706334e4122045", "target_role": "React Developer", "score": 0, "cv_text": "MICHEAL POLLARD Junior Business Analyst - Providing Data Management and Analysis for Strategic Decision-Making \\ +1-503-628-8758 @help@enhancv.com- © linkedin.com SUMMARY Junior Business Analyst with 3+ of years of experience in customer-focused, dynamic environment. Highly apt at seeing beyond the numbers to provide systematic solutions to increase profit margins by an AVG of 20K/ year. Ability to listen with intent to the customer problems to gather data and find solutions to individual problems. Built a 5000+ customer database through the years, based on loyalty and respect. EXPERIENCE Junior Business Analyst Carroll €3 2020- Ongoing 9 Dallas, TX Carroll is the global leader in cloud-based sales, marketing, learning, and customer experience solutions. + Increased gross revenue of 15% in 2021 (compared to 2020) with no change to fixed costs with data-oriented, customer-centric solutions + Automated manual review process using excel that saved around 1- hour of work per week + Expanded BI Audience by an additional 200+ users by offering new insights and features to the business Research Associate & Intern Business Analyst Grimes 2019-2020 9 Dallas, TX Grimes is the alternative within top-tier executive search and part of the global top-10 executive search firm TRANSEARCH International - one of the leading executive search and leadership advisory organizations in the world. + Improved internal processes by creating manuals to cut back on training time by 30% + Reduced IPS (Customer Issues) by 2.2% while impacting merely 3% of GMV - Supported sales to achieve 132% and 162% quota in 2019 and 2020 Sales Associate Borer Ltd @§ 2018-2019 9 Bronx. NY Borer Ltd is an affiliate brand mainly focused on audience based programmatic display marketing. + Exceeded the incremental spend target by 120% due to providing personalized and customer-focused information + Turned 2500+ cold leads into customers by offering them solutions to their problems and listening carefully to their concerns + Helped with 150+ product launches by making cold calls, collecting and analyzing customer data TRAINING / COURSES Microsoft Excel Expert Data Analysis for Decision- (Excel and Excel 2019) Making Microsoft edxX Google Data Analytics Professional Certificate Coursera www.enhancv.com 9 Dallas, TX SKILLS Bl Data Analysis © MSO Client Management Sales Targets Cold Calling Lead Generation EDUCATION Bachelor of Science in Business and Political Economy New York University &4) 2014 - 2018 9 Manhattan, NY STRENGTHS Data Management Systematic approach towards systematizing and analyzing data with Macros in Excel. Providing growth- focused solutions, increasing profit margins by at least 25%/ year. Customer Growth by 15K/ Year Knowledge of specific niches to implement business growth solutions: from product launches to lead generation. Accumulating a loyal customer base, responsible for the 30% expansion of the business within the past year. Product Expansion Using systematized data to provide opportunities with a focus on enhancing the overall customer experience by an annual AVG of 65%. ACHIEVEMENTS f Successful launch of 100+ new products Solely through the past 2 years, have provided data-focused solutions to increase sales on new unites by 45%. High Achiever Q4 2021 Received the company-wide recognition for helping the sales team surpass their targets by 150%. Powered by (XZ Enhancy", "metadata": {"filename": "12706334e4122045.pdf", "original_category": "Business Analyst", "extraction_method": "ocr"}, "parsed_education": [{"degree": "BACHELOR", "institution": null, "years": "2014 - 2018", "field_of_study": "Unknown"}], "extracted_skills": ["excel", "Decision-Making", "Excel"], "parsed_summary": " Junior Business Analyst with 3+ of years of", "personal_info": {"phone": "+1-503-628-8758", "first_name": null, "last_name": null}}
{"cv_id": "12706334e4122045", "target_role": "SQL Developer", "score": 2, "cv_text": "MICHEAL POLLARD Junior Business Analyst - Providing Data Management and Analysis for Strategic Decision-Making \\ +1-503-628-8758 @help@enhancv.com- © linkedin.com SUMMARY Junior Business Analyst with 3+ of years of experience in customer-focused, dynamic environment. Highly apt at seeing beyond the numbers to provide systematic solutions to increase profit margins by an AVG of 20K/ year. Ability to listen with intent to the customer problems to gather data and find solutions to individual problems. Built a 5000+ customer database through the years, based on loyalty and respect. EXPERIENCE Junior Business Analyst Carroll €3 2020- Ongoing 9 Dallas, TX Carroll is the global leader in cloud-based sales, marketing, learning, and customer experience solutions. + Increased gross revenue of 15% in 2021 (compared to 2020) with no change to fixed costs with data-oriented, customer-centric solutions + Automated manual review process using excel that saved around 1- hour of work per week + Expanded BI Audience by an additional 200+ users by offering new insights and features to the business Research Associate & Intern Business Analyst Grimes 2019-2020 9 Dallas, TX Grimes is the alternative within top-tier executive search and part of the global top-10 executive search firm TRANSEARCH International - one of the leading executive search and leadership advisory organizations in the world. + Improved internal processes by creating manuals to cut back on training time by 30% + Reduced IPS (Customer Issues) by 2.2% while impacting merely 3% of GMV - Supported sales to achieve 132% and 162% quota in 2019 and 2020 Sales Associate Borer Ltd @§ 2018-2019 9 Bronx. NY Borer Ltd is an affiliate brand mainly focused on audience based programmatic display marketing. + Exceeded the incremental spend target by 120% due to providing personalized and customer-focused information + Turned 2500+ cold leads into customers by offering them solutions to their problems and listening carefully to their concerns + Helped with 150+ product launches by making cold calls, collecting and analyzing customer data TRAINING / COURSES Microsoft Excel Expert Data Analysis for Decision- (Excel and Excel 2019) Making Microsoft edxX Google Data Analytics Professional Certificate Coursera www.enhancv.com 9 Dallas, TX SKILLS Bl Data Analysis © MSO Client Management Sales Targets Cold Calling Lead Generation EDUCATION Bachelor of Science in Business and Political Economy New York University &4) 2014 - 2018 9 Manhattan, NY STRENGTHS Data Management Systematic approach towards systematizing and analyzing data with Macros in Excel. Providing growth- focused solutions, increasing profit margins by at least 25%/ year. Customer Growth by 15K/ Year Knowledge of specific niches to implement business growth solutions: from product launches to lead generation. Accumulating a loyal customer base, responsible for the 30% expansion of the business within the past year. Product Expansion Using systematized data to provide opportunities with a focus on enhancing the overall customer experience by an annual AVG of 65%. ACHIEVEMENTS f Successful launch of 100+ new products Solely through the past 2 years, have provided data-focused solutions to increase sales on new unites by 45%. High Achiever Q4 2021 Received the company-wide recognition for helping the sales team surpass their targets by 150%. Powered by (XZ Enhancy", "metadata": {"filename": "12706334e4122045.pdf", "original_category": "Business Analyst", "extraction_method": "ocr"}, "parsed_education": [{"degree": "BACHELOR", "institution": null, "years": "2014 - 2018", "field_of_study": "Unknown"}], "extracted_skills": ["excel", "Decision-Making", "Excel"], "parsed_summary": " Junior Business Analyst with 3+ of years of", "personal_info": {"phone": "+1-503-628-8758", "first_name": null, "last_name": null}}
{"cv_id": "12706334e4122045", "target_role": "Web Developer", "score": 0, "cv_text": "MICHEAL POLLARD Junior Business Analyst - Providing Data Management and Analysis for Strategic Decision-Making \\ +1-503-628-8758 @help@enhancv.com- © linkedin.com SUMMARY Junior Business Analyst with 3+ of years of experience in customer-focused, dynamic environment. Highly apt at seeing beyond the numbers to provide systematic solutions to increase profit margins by an AVG of 20K/ year. Ability to listen with intent to the customer problems to gather data and find solutions to individual problems. Built a 5000+ customer database through the years, based on loyalty and respect. EXPERIENCE Junior Business Analyst Carroll €3 2020- Ongoing 9 Dallas, TX Carroll is the global leader in cloud-based sales, marketing, learning, and customer experience solutions. + Increased gross revenue of 15% in 2021 (compared to 2020) with no change to fixed costs with data-oriented, customer-centric solutions + Automated manual review process using excel that saved around 1- hour of work per week + Expanded BI Audience by an additional 200+ users by offering new insights and features to the business Research Associate & Intern Business Analyst Grimes 2019-2020 9 Dallas, TX Grimes is the alternative within top-tier executive search and part of the global top-10 executive search firm TRANSEARCH International - one of the leading executive search and leadership advisory organizations in the world. + Improved internal processes by creating manuals to cut back on training time by 30% + Reduced IPS (Customer Issues) by 2.2% while impacting merely 3% of GMV - Supported sales to achieve 132% and 162% quota in 2019 and 2020 Sales Associate Borer Ltd @§ 2018-2019 9 Bronx. NY Borer Ltd is an affiliate brand mainly focused on audience based programmatic display marketing. + Exceeded the incremental spend target by 120% due to providing personalized and customer-focused information + Turned 2500+ cold leads into customers by offering them solutions to their problems and listening carefully to their concerns + Helped with 150+ product launches by making cold calls, collecting and analyzing customer data TRAINING / COURSES Microsoft Excel Expert Data Analysis for Decision- (Excel and Excel 2019) Making Microsoft edxX Google Data Analytics Professional Certificate Coursera www.enhancv.com 9 Dallas, TX SKILLS Bl Data Analysis © MSO Client Management Sales Targets Cold Calling Lead Generation EDUCATION Bachelor of Science in Business and Political Economy New York University &4) 2014 - 2018 9 Manhattan, NY STRENGTHS Data Management Systematic approach towards systematizing and analyzing data with Macros in Excel. Providing growth- focused solutions, increasing profit margins by at least 25%/ year. Customer Growth by 15K/ Year Knowledge of specific niches to implement business growth solutions: from product launches to lead generation. Accumulating a loyal customer base, responsible for the 30% expansion of the business within the past year. Product Expansion Using systematized data to provide opportunities with a focus on enhancing the overall customer experience by an annual AVG of 65%. ACHIEVEMENTS f Successful launch of 100+ new products Solely through the past 2 years, have provided data-focused solutions to increase sales on new unites by 45%. High Achiever Q4 2021 Received the company-wide recognition for helping the sales team surpass their targets by 150%. Powered by (XZ Enhancy", "metadata": {"filename": "12706334e4122045.pdf", "original_category": "Business Analyst", "extraction_method": "ocr"}, "parsed_education": [{"degree": "BACHELOR", "institution": null, "years": "2014 - 2018", "field_of_study": "Unknown"}], "extracted_skills": ["excel", "Decision-Making", "Excel"], "parsed_summary": " Junior Business Analyst with 3+ of years of", "personal_info": {"phone": "+1-503-628-8758", "first_name": null, "last_name": null}}
{"cv_id": "12706334e4122045", "target_role": "SAP Developer", "score": 2, "cv_text": "MICHEAL POLLARD Junior Business Analyst - Providing Data Management and Analysis for Strategic Decision-Making \\ +1-503-628-8758 @help@enhancv.com- © linkedin.com SUMMARY Junior Business Analyst with 3+ of years of experience in customer-focused, dynamic environment. Highly apt at seeing beyond the numbers to provide systematic solutions to increase profit margins by an AVG of 20K/ year. Ability to listen with intent to the customer problems to gather data and find solutions to individual problems. Built a 5000+ customer database through the years, based on loyalty and respect. EXPERIENCE Junior Business Analyst Carroll €3 2020- Ongoing 9 Dallas, TX Carroll is the global leader in cloud-based sales, marketing, learning, and customer experience solutions. + Increased gross revenue of 15% in 2021 (compared to 2020) with no change to fixed costs with data-oriented, customer-centric solutions + Automated manual review process using excel that saved around 1- hour of work per week + Expanded BI Audience by an additional 200+ users by offering new insights and features to the business Research Associate & Intern Business Analyst Grimes 2019-2020 9 Dallas, TX Grimes is the alternative within top-tier executive search and part of the global top-10 executive search firm TRANSEARCH International - one of the leading executive search and leadership advisory organizations in the world. + Improved internal processes by creating manuals to cut back on training time by 30% + Reduced IPS (Customer Issues) by 2.2% while impacting merely 3% of GMV - Supported sales to achieve 132% and 162% quota in 2019 and 2020 Sales Associate Borer Ltd @§ 2018-2019 9 Bronx. NY Borer Ltd is an affiliate brand mainly focused on audience based programmatic display marketing. + Exceeded the incremental spend target by 120% due to providing personalized and customer-focused information + Turned 2500+ cold leads into customers by offering them solutions to their problems and listening carefully to their concerns + Helped with 150+ product launches by making cold calls, collecting and analyzing customer data TRAINING / COURSES Microsoft Excel Expert Data Analysis for Decision- (Excel and Excel 2019) Making Microsoft edxX Google Data Analytics Professional Certificate Coursera www.enhancv.com 9 Dallas, TX SKILLS Bl Data Analysis © MSO Client Management Sales Targets Cold Calling Lead Generation EDUCATION Bachelor of Science in Business and Political Economy New York University &4) 2014 - 2018 9 Manhattan, NY STRENGTHS Data Management Systematic approach towards systematizing and analyzing data with Macros in Excel. Providing growth- focused solutions, increasing profit margins by at least 25%/ year. Customer Growth by 15K/ Year Knowledge of specific niches to implement business growth solutions: from product launches to lead generation. Accumulating a loyal customer base, responsible for the 30% expansion of the business within the past year. Product Expansion Using systematized data to provide opportunities with a focus on enhancing the overall customer experience by an annual AVG of 65%. ACHIEVEMENTS f Successful launch of 100+ new products Solely through the past 2 years, have provided data-focused solutions to increase sales on new unites by 45%. High Achiever Q4 2021 Received the company-wide recognition for helping the sales team surpass their targets by 150%. Powered by (XZ Enhancy", "metadata": {"filename": "12706334e4122045.pdf", "original_category": "Business Analyst", "extraction_method": "ocr"}, "parsed_education": [{"degree": "BACHELOR", "institution": null, "years": "2014 - 2018", "field_of_study": "Unknown"}], "extracted_skills": ["excel", "Decision-Making", "Excel"], "parsed_summary": " Junior Business Analyst with 3+ of years of", "personal_info": {"phone": "+1-503-628-8758", "first_name": null, "last_name": null}}
{"cv_id": "12706334e4122045", "target_role": "Tester", "score": 0, "cv_text": "MICHEAL POLLARD Junior Business Analyst - Providing Data Management and Analysis for Strategic Decision-Making \\ +1-503-628-8758 @help@enhancv.com- © linkedin.com SUMMARY Junior Business Analyst with 3+ of years of experience in customer-focused, dynamic environment. Highly apt at seeing beyond the numbers to provide systematic solutions to increase profit margins by an AVG of 20K/ year. Ability to listen with intent to the customer problems to gather data and find solutions to individual problems. Built a 5000+ customer database through the years, based on loyalty and respect. EXPERIENCE Junior Business Analyst Carroll €3 2020- Ongoing 9 Dallas, TX Carroll is the global leader in cloud-based sales, marketing, learning, and customer experience solutions. + Increased gross revenue of 15% in 2021 (compared to 2020) with no change to fixed costs with data-oriented, customer-centric solutions + Automated manual review process using excel that saved around 1- hour of work per week + Expanded BI Audience by an additional 200+ users by offering new insights and features to the business Research Associate & Intern Business Analyst Grimes 2019-2020 9 Dallas, TX Grimes is the alternative within top-tier executive search and part of the global top-10 executive search firm TRANSEARCH International - one of the leading executive search and leadership advisory organizations in the world. + Improved internal processes by creating manuals to cut back on training time by 30% + Reduced IPS (Customer Issues) by 2.2% while impacting merely 3% of GMV - Supported sales to achieve 132% and 162% quota in 2019 and 2020 Sales Associate Borer Ltd @§ 2018-2019 9 Bronx. NY Borer Ltd is an affiliate brand mainly focused on audience based programmatic display marketing. + Exceeded the incremental spend target by 120% due to providing personalized and customer-focused information + Turned 2500+ cold leads into customers by offering them solutions to their problems and listening carefully to their concerns + Helped with 150+ product launches by making cold calls, collecting and analyzing customer data TRAINING / COURSES Microsoft Excel Expert Data Analysis for Decision- (Excel and Excel 2019) Making Microsoft edxX Google Data Analytics Professional Certificate Coursera www.enhancv.com 9 Dallas, TX SKILLS Bl Data Analysis © MSO Client Management Sales Targets Cold Calling Lead Generation EDUCATION Bachelor of Science in Business and Political Economy New York University &4) 2014 - 2018 9 Manhattan, NY STRENGTHS Data Management Systematic approach towards systematizing and analyzing data with Macros in Excel. Providing growth- focused solutions, increasing profit margins by at least 25%/ year. Customer Growth by 15K/ Year Knowledge of specific niches to implement business growth solutions: from product launches to lead generation. Accumulating a loyal customer base, responsible for the 30% expansion of the business within the past year. Product Expansion Using systematized data to provide opportunities with a focus on enhancing the overall customer experience by an annual AVG of 65%. ACHIEVEMENTS f Successful launch of 100+ new products Solely through the past 2 years, have provided data-focused solutions to increase sales on new unites by 45%. High Achiever Q4 2021 Received the company-wide recognition for helping the sales team surpass their targets by 150%. Powered by (XZ Enhancy", "metadata": {"filename": "12706334e4122045.pdf", "original_category": "Business Analyst", "extraction_method": "ocr"}, "parsed_education": [{"degree": "BACHELOR", "institution": null, "years": "2014 - 2018", "field_of_study": "Unknown"}], "extracted_skills": ["excel", "Decision-Making", "Excel"], "parsed_summary": " Junior Business Analyst with 3+ of years of", "personal_info": {"phone": "+1-503-628-8758", "first_name": null, "last_name": null}}
{"cv_id": "127e369e6d6bb585", "target_role": "Business Analyst", "score": 5, "cv_text": "Jordan Kirtley Business Analyst Phone 305-730-3464 Linkedin linkedin.com/in/jordanzkirtley E-mail jordanzkirtley@gmail.com Twitter twitter.com/jordanzkirtley Insightful entry-level business analyst with skills in financial modeling and AWS. Excited to deliver profitable insights at WCS. As MBA student at University of Miami, used financial modeling and guided team of 5 to raise $5,000 for local animal shelter. Education 2017 - 2019 MBA University of Miami Marketing and Sales Project * Conducted senior project in market segmentation, branding, and promotion that raised $5,000 for the Broward County Animal Shelter. * Awarded the Catherine L. Gallardo scholarship for charity work. * Conducted rigorous financial modeling to find best project path. * Recruited and managed team of 5 students and community members to implement project strategy. President, Student Economics Club * Led energetic group of 30+ engaged business students to analyze business trends and build lasting relationships. * Supported and organized 10+ club events such as forums to discuss valuation, strategy, capital markets, and venture capitalism. Pursued Educational Excellence * Excelled in accounting, macroeconomics, marketing, and statistics. * Admitted into Masters Scholar program for academic excellence. 2013 - 2017 BS Business Administration Florida State University * Vice President, Association for Business Communication. * Completed 6-credit senior project in financial modeling. Additional Activities 2015 - 2019 Whitewater Videographer * Chased rafts down Class V rivers daily to create and sell trip videos. * Redesigned pricing scheme to reap 40% more revenue than average. Volunteer Driver, Broward County Animal Shelter * Drove vanloads of 50+ cats and dogs per month to rescues. * Analyzed & restructured loading to fit 20% more animals per trip. Eagle Scout, BSA * Recognized for work ethic and interpersonal skills. * Completed Eagle project that raised $4,300 for disabled in Ghana. Skills financial modeling future state assessment gap analysis", "metadata": {"filename": "127e369e6d6bb585.pdf", "original_category": "Business Analyst", "extraction_method": "ocr"}, "parsed_education": [{"degree": "MBA", "institution": null, "years": "2017 - 2019", "field_of_study": "Marketing"}, {"degree": "MASTERS", "institution": null, "years": "2013 - 2017", "field_of_study": "Statistics"}, {"degree": "BS", "institution": null, "years": "2015 - 2019", "field_of_study": "Business Administration"}], "extracted_skills": ["Communication", "gap analysis", "AWS", "financial modeling"], "parsed_summary": "Jordan Kirtley Business Analyst Phone 305-730-3464 Linkedin linkedin.com/in/jordanzkirtley E-mail jordanzkirtley@gmail.com Twitter twitter.com/jordanzkirtley Insightful entry-level business analyst with skills in financial modeling and AWS. Excited to deliver profitable insights at WCS. As MBA student at University of Miami, used financial modeling and guided team of 5 to raise $5,000 for local animal shelter.", "personal_info": {"phone": "305-730-3464", "first_name": "Jordan", "last_name": "Kirtley Business"}}
{"cv_id": "127e369e6d6bb585", "target_role": "Data Scientist", "score": 1, "cv_text": "Jordan Kirtley Business Analyst Phone 305-730-3464 Linkedin linkedin.com/in/jordanzkirtley E-mail jordanzkirtley@gmail.com Twitter twitter.com/jordanzkirtley Insightful entry-level business analyst with skills in financial modeling and AWS. Excited to deliver profitable insights at WCS. As MBA student at University of Miami, used financial modeling and guided team of 5 to raise $5,000 for local animal shelter. Education 2017 - 2019 MBA University of Miami Marketing and Sales Project * Conducted senior project in market segmentation, branding, and promotion that raised $5,000 for the Broward County Animal Shelter. * Awarded the Catherine L. Gallardo scholarship for charity work. * Conducted rigorous financial modeling to find best project path. * Recruited and managed team of 5 students and community members to implement project strategy. President, Student Economics Club * Led energetic group of 30+ engaged business students to analyze business trends and build lasting relationships. * Supported and organized 10+ club events such as forums to discuss valuation, strategy, capital markets, and venture capitalism. Pursued Educational Excellence * Excelled in accounting, macroeconomics, marketing, and statistics. * Admitted into Masters Scholar program for academic excellence. 2013 - 2017 BS Business Administration Florida State University * Vice President, Association for Business Communication. * Completed 6-credit senior project in financial modeling. Additional Activities 2015 - 2019 Whitewater Videographer * Chased rafts down Class V rivers daily to create and sell trip videos. * Redesigned pricing scheme to reap 40% more revenue than average. Volunteer Driver, Broward County Animal Shelter * Drove vanloads of 50+ cats and dogs per month to rescues. * Analyzed & restructured loading to fit 20% more animals per trip. Eagle Scout, BSA * Recognized for work ethic and interpersonal skills. * Completed Eagle project that raised $4,300 for disabled in Ghana. Skills financial modeling future state assessment gap analysis", "metadata": {"filename": "127e369e6d6bb585.pdf", "original_category": "Business Analyst", "extraction_method": "ocr"}, "parsed_education": [{"degree": "MBA", "institution": null, "years": "2017 - 2019", "field_of_study": "Marketing"}, {"degree": "MASTERS", "institution": null, "years": "2013 - 2017", "field_of_study": "Statistics"}, {"degree": "BS", "institution": null, "years": "2015 - 2019", "field_of_study": "Business Administration"}], "extracted_skills": ["Communication", "gap analysis", "AWS", "financial modeling"], "parsed_summary": "Jordan Kirtley Business Analyst Phone 305-730-3464 Linkedin linkedin.com/in/jordanzkirtley E-mail jordanzkirtley@gmail.com Twitter twitter.com/jordanzkirtley Insightful entry-level business analyst with skills in financial modeling and AWS. Excited to deliver profitable insights at WCS. As MBA student at University of Miami, used financial modeling and guided team of 5 to raise $5,000 for local animal shelter.", "personal_info": {"phone": "305-730-3464", "first_name": "Jordan", "last_name": "Kirtley Business"}}
{"cv_id": "127e369e6d6bb585", "target_role": "DevOps Engineer", "score": 0, "cv_text": "Jordan Kirtley Business Analyst Phone 305-730-3464 Linkedin linkedin.com/in/jordanzkirtley E-mail jordanzkirtley@gmail.com Twitter twitter.com/jordanzkirtley Insightful entry-level business analyst with skills in financial modeling and AWS. Excited to deliver profitable insights at WCS. As MBA student at University of Miami, used financial modeling and guided team of 5 to raise $5,000 for local animal shelter. Education 2017 - 2019 MBA University of Miami Marketing and Sales Project * Conducted senior project in market segmentation, branding, and promotion that raised $5,000 for the Broward County Animal Shelter. * Awarded the Catherine L. Gallardo scholarship for charity work. * Conducted rigorous financial modeling to find best project path. * Recruited and managed team of 5 students and community members to implement project strategy. President, Student Economics Club * Led energetic group of 30+ engaged business students to analyze business trends and build lasting relationships. * Supported and organized 10+ club events such as forums to discuss valuation, strategy, capital markets, and venture capitalism. Pursued Educational Excellence * Excelled in accounting, macroeconomics, marketing, and statistics. * Admitted into Masters Scholar program for academic excellence. 2013 - 2017 BS Business Administration Florida State University * Vice President, Association for Business Communication. * Completed 6-credit senior project in financial modeling. Additional Activities 2015 - 2019 Whitewater Videographer * Chased rafts down Class V rivers daily to create and sell trip videos. * Redesigned pricing scheme to reap 40% more revenue than average. Volunteer Driver, Broward County Animal Shelter * Drove vanloads of 50+ cats and dogs per month to rescues. * Analyzed & restructured loading to fit 20% more animals per trip. Eagle Scout, BSA * Recognized for work ethic and interpersonal skills. * Completed Eagle project that raised $4,300 for disabled in Ghana. Skills financial modeling future state assessment gap analysis", "metadata": {"filename": "127e369e6d6bb585.pdf", "original_category": "Business Analyst", "extraction_method": "ocr"}, "parsed_education": [{"degree": "MBA", "institution": null, "years": "2017 - 2019", "field_of_study": "Marketing"}, {"degree": "MASTERS", "institution": null, "years": "2013 - 2017", "field_of_study": "Statistics"}, {"degree": "BS", "institution": null, "years": "2015 - 2019", "field_of_study": "Business Administration"}], "extracted_skills": ["Communication", "gap analysis", "AWS", "financial modeling"], "parsed_summary": "Jordan Kirtley Business Analyst Phone 305-730-3464 Linkedin linkedin.com/in/jordanzkirtley E-mail jordanzkirtley@gmail.com Twitter twitter.com/jordanzkirtley Insightful entry-level business analyst with skills in financial modeling and AWS. Excited to deliver profitable insights at WCS. As MBA student at University of Miami, used financial modeling and guided team of 5 to raise $5,000 for local animal shelter.", "personal_info": {"phone": "305-730-3464", "first_name": "Jordan", "last_name": "Kirtley Business"}}
{"cv_id": "127e369e6d6bb585", "target_role": "ETL Developer", "score": 0, "cv_text": "Jordan Kirtley Business Analyst Phone 305-730-3464 Linkedin linkedin.com/in/jordanzkirtley E-mail jordanzkirtley@gmail.com Twitter twitter.com/jordanzkirtley Insightful entry-level business analyst with skills in financial modeling and AWS. Excited to deliver profitable insights at WCS. As MBA student at University of Miami, used financial modeling and guided team of 5 to raise $5,000 for local animal shelter. Education 2017 - 2019 MBA University of Miami Marketing and Sales Project * Conducted senior project in market segmentation, branding, and promotion that raised $5,000 for the Broward County Animal Shelter. * Awarded the Catherine L. Gallardo scholarship for charity work. * Conducted rigorous financial modeling to find best project path. * Recruited and managed team of 5 students and community members to implement project strategy. President, Student Economics Club * Led energetic group of 30+ engaged business students to analyze business trends and build lasting relationships. * Supported and organized 10+ club events such as forums to discuss valuation, strategy, capital markets, and venture capitalism. Pursued Educational Excellence * Excelled in accounting, macroeconomics, marketing, and statistics. * Admitted into Masters Scholar program for academic excellence. 2013 - 2017 BS Business Administration Florida State University * Vice President, Association for Business Communication. * Completed 6-credit senior project in financial modeling. Additional Activities 2015 - 2019 Whitewater Videographer * Chased rafts down Class V rivers daily to create and sell trip videos. * Redesigned pricing scheme to reap 40% more revenue than average. Volunteer Driver, Broward County Animal Shelter * Drove vanloads of 50+ cats and dogs per month to rescues. * Analyzed & restructured loading to fit 20% more animals per trip. Eagle Scout, BSA * Recognized for work ethic and interpersonal skills. * Completed Eagle project that raised $4,300 for disabled in Ghana. Skills financial modeling future state assessment gap analysis", "metadata": {"filename": "127e369e6d6bb585.pdf", "original_category": "Business Analyst", "extraction_method": "ocr"}, "parsed_education": [{"degree": "MBA", "institution": null, "years": "2017 - 2019", "field_of_study": "Marketing"}, {"degree": "MASTERS", "institution": null, "years": "2013 - 2017", "field_of_study": "Statistics"}, {"degree": "BS", "institution": null, "years": "2015 - 2019", "field_of_study": "Business Administration"}], "extracted_skills": ["Communication", "gap analysis", "AWS", "financial modeling"], "parsed_summary": "Jordan Kirtley Business Analyst Phone 305-730-3464 Linkedin linkedin.com/in/jordanzkirtley E-mail jordanzkirtley@gmail.com Twitter twitter.com/jordanzkirtley Insightful entry-level business analyst with skills in financial modeling and AWS. Excited to deliver profitable insights at WCS. As MBA student at University of Miami, used financial modeling and guided team of 5 to raise $5,000 for local animal shelter.", "personal_info": {"phone": "305-730-3464", "first_name": "Jordan", "last_name": "Kirtley Business"}}
{"cv_id": "127e369e6d6bb585", "target_role": "Java Developer", "score": 0, "cv_text": "Jordan Kirtley Business Analyst Phone 305-730-3464 Linkedin linkedin.com/in/jordanzkirtley E-mail jordanzkirtley@gmail.com Twitter twitter.com/jordanzkirtley Insightful entry-level business analyst with skills in financial modeling and AWS. Excited to deliver profitable insights at WCS. As MBA student at University of Miami, used financial modeling and guided team of 5 to raise $5,000 for local animal shelter. Education 2017 - 2019 MBA University of Miami Marketing and Sales Project * Conducted senior project in market segmentation, branding, and promotion that raised $5,000 for the Broward County Animal Shelter. * Awarded the Catherine L. Gallardo scholarship for charity work. * Conducted rigorous financial modeling to find best project path. * Recruited and managed team of 5 students and community members to implement project strategy. President, Student Economics Club * Led energetic group of 30+ engaged business students to analyze business trends and build lasting relationships. * Supported and organized 10+ club events such as forums to discuss valuation, strategy, capital markets, and venture capitalism. Pursued Educational Excellence * Excelled in accounting, macroeconomics, marketing, and statistics. * Admitted into Masters Scholar program for academic excellence. 2013 - 2017 BS Business Administration Florida State University * Vice President, Association for Business Communication. * Completed 6-credit senior project in financial modeling. Additional Activities 2015 - 2019 Whitewater Videographer * Chased rafts down Class V rivers daily to create and sell trip videos. * Redesigned pricing scheme to reap 40% more revenue than average. Volunteer Driver, Broward County Animal Shelter * Drove vanloads of 50+ cats and dogs per month to rescues. * Analyzed & restructured loading to fit 20% more animals per trip. Eagle Scout, BSA * Recognized for work ethic and interpersonal skills. * Completed Eagle project that raised $4,300 for disabled in Ghana. Skills financial modeling future state assessment gap analysis", "metadata": {"filename": "127e369e6d6bb585.pdf", "original_category": "Business Analyst", "extraction_method": "ocr"}, "parsed_education": [{"degree": "MBA", "institution": null, "years": "2017 - 2019", "field_of_study": "Marketing"}, {"degree": "MASTERS", "institution": null, "years": "2013 - 2017", "field_of_study": "Statistics"}, {"degree": "BS", "institution": null, "years": "2015 - 2019", "field_of_study": "Business Administration"}], "extracted_skills": ["Communication", "gap analysis", "AWS", "financial modeling"], "parsed_summary": "Jordan Kirtley Business Analyst Phone 305-730-3464 Linkedin linkedin.com/in/jordanzkirtley E-mail jordanzkirtley@gmail.com Twitter twitter.com/jordanzkirtley Insightful entry-level business analyst with skills in financial modeling and AWS. Excited to deliver profitable insights at WCS. As MBA student at University of Miami, used financial modeling and guided team of 5 to raise $5,000 for local animal shelter.", "personal_info": {"phone": "305-730-3464", "first_name": "Jordan", "last_name": "Kirtley Business"}}
{"cv_id": "127e369e6d6bb585", "target_role": "Python Developer", "score": 0, "cv_text": "Jordan Kirtley Business Analyst Phone 305-730-3464 Linkedin linkedin.com/in/jordanzkirtley E-mail jordanzkirtley@gmail.com Twitter twitter.com/jordanzkirtley Insightful entry-level business analyst with skills in financial modeling and AWS. Excited to deliver profitable insights at WCS. As MBA student at University of Miami, used financial modeling and guided team of 5 to raise $5,000 for local animal shelter. Education 2017 - 2019 MBA University of Miami Marketing and Sales Project * Conducted senior project in market segmentation, branding, and promotion that raised $5,000 for the Broward County Animal Shelter. * Awarded the Catherine L. Gallardo scholarship for charity work. * Conducted rigorous financial modeling to find best project path. * Recruited and managed team of 5 students and community members to implement project strategy. President, Student Economics Club * Led energetic group of 30+ engaged business students to analyze business trends and build lasting relationships. * Supported and organized 10+ club events such as forums to discuss valuation, strategy, capital markets, and venture capitalism. Pursued Educational Excellence * Excelled in accounting, macroeconomics, marketing, and statistics. * Admitted into Masters Scholar program for academic excellence. 2013 - 2017 BS Business Administration Florida State University * Vice President, Association for Business Communication. * Completed 6-credit senior project in financial modeling. Additional Activities 2015 - 2019 Whitewater Videographer * Chased rafts down Class V rivers daily to create and sell trip videos. * Redesigned pricing scheme to reap 40% more revenue than average. Volunteer Driver, Broward County Animal Shelter * Drove vanloads of 50+ cats and dogs per month to rescues. * Analyzed & restructured loading to fit 20% more animals per trip. Eagle Scout, BSA * Recognized for work ethic and interpersonal skills. * Completed Eagle project that raised $4,300 for disabled in Ghana. Skills financial modeling future state assessment gap analysis", "metadata": {"filename": "127e369e6d6bb585.pdf", "original_category": "Business Analyst", "extraction_method": "ocr"}, "parsed_education": [{"degree": "MBA", "institution": null, "years": "2017 - 2019", "field_of_study": "Marketing"}, {"degree": "MASTERS", "institution": null, "years": "2013 - 2017", "field_of_study": "Statistics"}, {"degree": "BS", "institution": null, "years": "2015 - 2019", "field_of_study": "Business Administration"}], "extracted_skills": ["Communication", "gap analysis", "AWS", "financial modeling"], "parsed_summary": "Jordan Kirtley Business Analyst Phone 305-730-3464 Linkedin linkedin.com/in/jordanzkirtley E-mail jordanzkirtley@gmail.com Twitter twitter.com/jordanzkirtley Insightful entry-level business analyst with skills in financial modeling and AWS. Excited to deliver profitable insights at WCS. As MBA student at University of Miami, used financial modeling and guided team of 5 to raise $5,000 for local animal shelter.", "personal_info": {"phone": "305-730-3464", "first_name": "Jordan", "last_name": "Kirtley Business"}}
{"cv_id": "127e369e6d6bb585", "target_role": "React Developer", "score": 0, "cv_text": "Jordan Kirtley Business Analyst Phone 305-730-3464 Linkedin linkedin.com/in/jordanzkirtley E-mail jordanzkirtley@gmail.com Twitter twitter.com/jordanzkirtley Insightful entry-level business analyst with skills in financial modeling and AWS. Excited to deliver profitable insights at WCS. As MBA student at University of Miami, used financial modeling and guided team of 5 to raise $5,000 for local animal shelter. Education 2017 - 2019 MBA University of Miami Marketing and Sales Project * Conducted senior project in market segmentation, branding, and promotion that raised $5,000 for the Broward County Animal Shelter. * Awarded the Catherine L. Gallardo scholarship for charity work. * Conducted rigorous financial modeling to find best project path. * Recruited and managed team of 5 students and community members to implement project strategy. President, Student Economics Club * Led energetic group of 30+ engaged business students to analyze business trends and build lasting relationships. * Supported and organized 10+ club events such as forums to discuss valuation, strategy, capital markets, and venture capitalism. Pursued Educational Excellence * Excelled in accounting, macroeconomics, marketing, and statistics. * Admitted into Masters Scholar program for academic excellence. 2013 - 2017 BS Business Administration Florida State University * Vice President, Association for Business Communication. * Completed 6-credit senior project in financial modeling. Additional Activities 2015 - 2019 Whitewater Videographer * Chased rafts down Class V rivers daily to create and sell trip videos. * Redesigned pricing scheme to reap 40% more revenue than average. Volunteer Driver, Broward County Animal Shelter * Drove vanloads of 50+ cats and dogs per month to rescues. * Analyzed & restructured loading to fit 20% more animals per trip. Eagle Scout, BSA * Recognized for work ethic and interpersonal skills. * Completed Eagle project that raised $4,300 for disabled in Ghana. Skills financial modeling future state assessment gap analysis", "metadata": {"filename": "127e369e6d6bb585.pdf", "original_category": "Business Analyst", "extraction_method": "ocr"}, "parsed_education": [{"degree": "MBA", "institution": null, "years": "2017 - 2019", "field_of_study": "Marketing"}, {"degree": "MASTERS", "institution": null, "years": "2013 - 2017", "field_of_study": "Statistics"}, {"degree": "BS", "institution": null, "years": "2015 - 2019", "field_of_study": "Business Administration"}], "extracted_skills": ["Communication", "gap analysis", "AWS", "financial modeling"], "parsed_summary": "Jordan Kirtley Business Analyst Phone 305-730-3464 Linkedin linkedin.com/in/jordanzkirtley E-mail jordanzkirtley@gmail.com Twitter twitter.com/jordanzkirtley Insightful entry-level business analyst with skills in financial modeling and AWS. Excited to deliver profitable insights at WCS. As MBA student at University of Miami, used financial modeling and guided team of 5 to raise $5,000 for local animal shelter.", "personal_info": {"phone": "305-730-3464", "first_name": "Jordan", "last_name": "Kirtley Business"}}
{"cv_id": "127e369e6d6bb585", "target_role": "SQL Developer", "score": 2, "cv_text": "Jordan Kirtley Business Analyst Phone 305-730-3464 Linkedin linkedin.com/in/jordanzkirtley E-mail jordanzkirtley@gmail.com Twitter twitter.com/jordanzkirtley Insightful entry-level business analyst with skills in financial modeling and AWS. Excited to deliver profitable insights at WCS. As MBA student at University of Miami, used financial modeling and guided team of 5 to raise $5,000 for local animal shelter. Education 2017 - 2019 MBA University of Miami Marketing and Sales Project * Conducted senior project in market segmentation, branding, and promotion that raised $5,000 for the Broward County Animal Shelter. * Awarded the Catherine L. Gallardo scholarship for charity work. * Conducted rigorous financial modeling to find best project path. * Recruited and managed team of 5 students and community members to implement project strategy. President, Student Economics Club * Led energetic group of 30+ engaged business students to analyze business trends and build lasting relationships. * Supported and organized 10+ club events such as forums to discuss valuation, strategy, capital markets, and venture capitalism. Pursued Educational Excellence * Excelled in accounting, macroeconomics, marketing, and statistics. * Admitted into Masters Scholar program for academic excellence. 2013 - 2017 BS Business Administration Florida State University * Vice President, Association for Business Communication. * Completed 6-credit senior project in financial modeling. Additional Activities 2015 - 2019 Whitewater Videographer * Chased rafts down Class V rivers daily to create and sell trip videos. * Redesigned pricing scheme to reap 40% more revenue than average. Volunteer Driver, Broward County Animal Shelter * Drove vanloads of 50+ cats and dogs per month to rescues. * Analyzed & restructured loading to fit 20% more animals per trip. Eagle Scout, BSA * Recognized for work ethic and interpersonal skills. * Completed Eagle project that raised $4,300 for disabled in Ghana. Skills financial modeling future state assessment gap analysis", "metadata": {"filename": "127e369e6d6bb585.pdf", "original_category": "Business Analyst", "extraction_method": "ocr"}, "parsed_education": [{"degree": "MBA", "institution": null, "years": "2017 - 2019", "field_of_study": "Marketing"}, {"degree": "MASTERS", "institution": null, "years": "2013 - 2017", "field_of_study": "Statistics"}, {"degree": "BS", "institution": null, "years": "2015 - 2019", "field_of_study": "Business Administration"}], "extracted_skills": ["Communication", "gap analysis", "AWS", "financial modeling"], "parsed_summary": "Jordan Kirtley Business Analyst Phone 305-730-3464 Linkedin linkedin.com/in/jordanzkirtley E-mail jordanzkirtley@gmail.com Twitter twitter.com/jordanzkirtley Insightful entry-level business analyst with skills in financial modeling and AWS. Excited to deliver profitable insights at WCS. As MBA student at University of Miami, used financial modeling and guided team of 5 to raise $5,000 for local animal shelter.", "personal_info": {"phone": "305-730-3464", "first_name": "Jordan", "last_name": "Kirtley Business"}}
{"cv_id": "127e369e6d6bb585", "target_role": "Web Developer", "score": 0, "cv_text": "Jordan Kirtley Business Analyst Phone 305-730-3464 Linkedin linkedin.com/in/jordanzkirtley E-mail jordanzkirtley@gmail.com Twitter twitter.com/jordanzkirtley Insightful entry-level business analyst with skills in financial modeling and AWS. Excited to deliver profitable insights at WCS. As MBA student at University of Miami, used financial modeling and guided team of 5 to raise $5,000 for local animal shelter. Education 2017 - 2019 MBA University of Miami Marketing and Sales Project * Conducted senior project in market segmentation, branding, and promotion that raised $5,000 for the Broward County Animal Shelter. * Awarded the Catherine L. Gallardo scholarship for charity work. * Conducted rigorous financial modeling to find best project path. * Recruited and managed team of 5 students and community members to implement project strategy. President, Student Economics Club * Led energetic group of 30+ engaged business students to analyze business trends and build lasting relationships. * Supported and organized 10+ club events such as forums to discuss valuation, strategy, capital markets, and venture capitalism. Pursued Educational Excellence * Excelled in accounting, macroeconomics, marketing, and statistics. * Admitted into Masters Scholar program for academic excellence. 2013 - 2017 BS Business Administration Florida State University * Vice President, Association for Business Communication. * Completed 6-credit senior project in financial modeling. Additional Activities 2015 - 2019 Whitewater Videographer * Chased rafts down Class V rivers daily to create and sell trip videos. * Redesigned pricing scheme to reap 40% more revenue than average. Volunteer Driver, Broward County Animal Shelter * Drove vanloads of 50+ cats and dogs per month to rescues. * Analyzed & restructured loading to fit 20% more animals per trip. Eagle Scout, BSA * Recognized for work ethic and interpersonal skills. * Completed Eagle project that raised $4,300 for disabled in Ghana. Skills financial modeling future state assessment gap analysis", "metadata": {"filename": "127e369e6d6bb585.pdf", "original_category": "Business Analyst", "extraction_method": "ocr"}, "parsed_education": [{"degree": "MBA", "institution": null, "years": "2017 - 2019", "field_of_study": "Marketing"}, {"degree": "MASTERS", "institution": null, "years": "2013 - 2017", "field_of_study": "Statistics"}, {"degree": "BS", "institution": null, "years": "2015 - 2019", "field_of_study": "Business Administration"}], "extracted_skills": ["Communication", "gap analysis", "AWS", "financial modeling"], "parsed_summary": "Jordan Kirtley Business Analyst Phone 305-730-3464 Linkedin linkedin.com/in/jordanzkirtley E-mail jordanzkirtley@gmail.com Twitter twitter.com/jordanzkirtley Insightful entry-level business analyst with skills in financial modeling and AWS. Excited to deliver profitable insights at WCS. As MBA student at University of Miami, used financial modeling and guided team of 5 to raise $5,000 for local animal shelter.", "personal_info": {"phone": "305-730-3464", "first_name": "Jordan", "last_name": "Kirtley Business"}}
{"cv_id": "127e369e6d6bb585", "target_role": "SAP Developer", "score": 2, "cv_text": "Jordan Kirtley Business Analyst Phone 305-730-3464 Linkedin linkedin.com/in/jordanzkirtley E-mail jordanzkirtley@gmail.com Twitter twitter.com/jordanzkirtley Insightful entry-level business analyst with skills in financial modeling and AWS. Excited to deliver profitable insights at WCS. As MBA student at University of Miami, used financial modeling and guided team of 5 to raise $5,000 for local animal shelter. Education 2017 - 2019 MBA University of Miami Marketing and Sales Project * Conducted senior project in market segmentation, branding, and promotion that raised $5,000 for the Broward County Animal Shelter. * Awarded the Catherine L. Gallardo scholarship for charity work. * Conducted rigorous financial modeling to find best project path. * Recruited and managed team of 5 students and community members to implement project strategy. President, Student Economics Club * Led energetic group of 30+ engaged business students to analyze business trends and build lasting relationships. * Supported and organized 10+ club events such as forums to discuss valuation, strategy, capital markets, and venture capitalism. Pursued Educational Excellence * Excelled in accounting, macroeconomics, marketing, and statistics. * Admitted into Masters Scholar program for academic excellence. 2013 - 2017 BS Business Administration Florida State University * Vice President, Association for Business Communication. * Completed 6-credit senior project in financial modeling. Additional Activities 2015 - 2019 Whitewater Videographer * Chased rafts down Class V rivers daily to create and sell trip videos. * Redesigned pricing scheme to reap 40% more revenue than average. Volunteer Driver, Broward County Animal Shelter * Drove vanloads of 50+ cats and dogs per month to rescues. * Analyzed & restructured loading to fit 20% more animals per trip. Eagle Scout, BSA * Recognized for work ethic and interpersonal skills. * Completed Eagle project that raised $4,300 for disabled in Ghana. Skills financial modeling future state assessment gap analysis", "metadata": {"filename": "127e369e6d6bb585.pdf", "original_category": "Business Analyst", "extraction_method": "ocr"}, "parsed_education": [{"degree": "MBA", "institution": null, "years": "2017 - 2019", "field_of_study": "Marketing"}, {"degree": "MASTERS", "institution": null, "years": "2013 - 2017", "field_of_study": "Statistics"}, {"degree": "BS", "institution": null, "years": "2015 - 2019", "field_of_study": "Business Administration"}], "extracted_skills": ["Communication", "gap analysis", "AWS", "financial modeling"], "parsed_summary": "Jordan Kirtley Business Analyst Phone 305-730-3464 Linkedin linkedin.com/in/jordanzkirtley E-mail jordanzkirtley@gmail.com Twitter twitter.com/jordanzkirtley Insightful entry-level business analyst with skills in financial modeling and AWS. Excited to deliver profitable insights at WCS. As MBA student at University of Miami, used financial modeling and guided team of 5 to raise $5,000 for local animal shelter.", "personal_info": {"phone": "305-730-3464", "first_name": "Jordan", "last_name": "Kirtley Business"}}
{"cv_id": "127e369e6d6bb585", "target_role": "Tester", "score": 0, "cv_text": "Jordan Kirtley Business Analyst Phone 305-730-3464 Linkedin linkedin.com/in/jordanzkirtley E-mail jordanzkirtley@gmail.com Twitter twitter.com/jordanzkirtley Insightful entry-level business analyst with skills in financial modeling and AWS. Excited to deliver profitable insights at WCS. As MBA student at University of Miami, used financial modeling and guided team of 5 to raise $5,000 for local animal shelter. Education 2017 - 2019 MBA University of Miami Marketing and Sales Project * Conducted senior project in market segmentation, branding, and promotion that raised $5,000 for the Broward County Animal Shelter. * Awarded the Catherine L. Gallardo scholarship for charity work. * Conducted rigorous financial modeling to find best project path. * Recruited and managed team of 5 students and community members to implement project strategy. President, Student Economics Club * Led energetic group of 30+ engaged business students to analyze business trends and build lasting relationships. * Supported and organized 10+ club events such as forums to discuss valuation, strategy, capital markets, and venture capitalism. Pursued Educational Excellence * Excelled in accounting, macroeconomics, marketing, and statistics. * Admitted into Masters Scholar program for academic excellence. 2013 - 2017 BS Business Administration Florida State University * Vice President, Association for Business Communication. * Completed 6-credit senior project in financial modeling. Additional Activities 2015 - 2019 Whitewater Videographer * Chased rafts down Class V rivers daily to create and sell trip videos. * Redesigned pricing scheme to reap 40% more revenue than average. Volunteer Driver, Broward County Animal Shelter * Drove vanloads of 50+ cats and dogs per month to rescues. * Analyzed & restructured loading to fit 20% more animals per trip. Eagle Scout, BSA * Recognized for work ethic and interpersonal skills. * Completed Eagle project that raised $4,300 for disabled in Ghana. Skills financial modeling future state assessment gap analysis", "metadata": {"filename": "127e369e6d6bb585.pdf", "original_category": "Business Analyst", "extraction_method": "ocr"}, "parsed_education": [{"degree": "MBA", "institution": null, "years": "2017 - 2019", "field_of_study": "Marketing"}, {"degree": "MASTERS", "institution": null, "years": "2013 - 2017", "field_of_study": "Statistics"}, {"degree": "BS", "institution": null, "years": "2015 - 2019", "field_of_study": "Business Administration"}], "extracted_skills": ["Communication", "gap analysis", "AWS", "financial modeling"], "parsed_summary": "Jordan Kirtley Business Analyst Phone 305-730-3464 Linkedin linkedin.com/in/jordanzkirtley E-mail jordanzkirtley@gmail.com Twitter twitter.com/jordanzkirtley Insightful entry-level business analyst with skills in financial modeling and AWS. Excited to deliver profitable insights at WCS. As MBA student at University of Miami, used financial modeling and guided team of 5 to raise $5,000 for local animal shelter.", "personal_info": {"phone": "305-730-3464", "first_name": "Jordan", "last_name": "Kirtley Business"}}
{"cv_id": "133933ee492cb76f", "target_role": "Business Analyst", "score": 5, "cv_text": "ROBERT SMITH Sr. Business System Analyst - Health Care E-mail: info@qwikresume.com Phone: (0123)-456-789 SUMMARY Seasoned, accomplished Business Systems Analyst with an extensive history of supporting enterprise-level solution development through highest caliber of needs analysis. requirements definition, functionalAechnical specification development, application testing, and post-implementation support, Superior ability to liaise und coordinate with internal and extemal stakeholders while collaborating with on and offshore project teams. Offshore, Testing, Training. UAT. User Stories., Use Cases, NetSuite, CRM, Marketo, Insurance Systems WORK EXPERIENCE Sr. Business System Analyst - Health Care UPTODATE - June 2014 — Present * UpToDate is an evidence-based clinical decision support resource for healthcare practitioners. Assess and analyze the business environment to detine the scope of the business problems, capturing project requirements, * Objectives and expectations. Elicit requirements for projects, enhancements, or defect fx requests using Interviews, workshops, data analysis, current business process descriptions, task, and workflow analysis. * Functional specifications, data mappings, and user stories. Support sules operations, marketing, customer service and finance departments. * ‘Translations for ull user screens and user documents. Post implementation support and enhancements. * — Salesl.ogix (CRM) projects to implement new products for us and international enterprise customers, Wrote user stories, functional specifications, upplication configumitions, coordinate QA anc UAT testing and post-implementation support for sales ops_ * Gather, document, and analyze client functional, transactional and insurance product business requirements for first Best's underwriting management system (UMS). Client facing and consultative role offering system solutions to enhance client implementations and transform client worktlow and business processes. * Between the customer and technical team providing support throughout the project development life cycle. Used the UMS configuration tool to build and maintain application forms and rules. Sales team support on REP. Sr. Business System Analyst FIRSTBEST SYSTEMS - November 2005 — April 2014 * Co-lead 4 two year-long series of implementations through requirements gathering sessions, functional. 0 This Eres Resume Template is the copyright of Qwikresume.corm. Usage Guidelines", "metadata": {"filename": "133933ee492cb76f.pdf", "original_category": "Business Analyst", "extraction_method": "ocr"}, "parsed_education": [], "extracted_skills": ["requirements gathering", "teams"], "parsed_summary": " Seasoned, accomplished Business Systems Analyst with an extensive history of supporting enterprise-level solution development through highest caliber of needs analysis. requirements definition, functionalAechnical specification development, application testing, and post-implementation support, Superior ability to liaise und coordinate with internal and extemal stakeholders while collaborating with on and offshore project teams. Offshore, Testing, Training. UAT. User Stories., Use Cases, NetSuite, CRM, Marketo, Insurance Systems WORK", "personal_info": {"phone": "(0123)-456-789", "first_name": null, "last_name": null}}
{"cv_id": "133933ee492cb76f", "target_role": "Data Scientist", "score": 1, "cv_text": "ROBERT SMITH Sr. Business System Analyst - Health Care E-mail: info@qwikresume.com Phone: (0123)-456-789 SUMMARY Seasoned, accomplished Business Systems Analyst with an extensive history of supporting enterprise-level solution development through highest caliber of needs analysis. requirements definition, functionalAechnical specification development, application testing, and post-implementation support, Superior ability to liaise und coordinate with internal and extemal stakeholders while collaborating with on and offshore project teams. Offshore, Testing, Training. UAT. User Stories., Use Cases, NetSuite, CRM, Marketo, Insurance Systems WORK EXPERIENCE Sr. Business System Analyst - Health Care UPTODATE - June 2014 — Present * UpToDate is an evidence-based clinical decision support resource for healthcare practitioners. Assess and analyze the business environment to detine the scope of the business problems, capturing project requirements, * Objectives and expectations. Elicit requirements for projects, enhancements, or defect fx requests using Interviews, workshops, data analysis, current business process descriptions, task, and workflow analysis. * Functional specifications, data mappings, and user stories. Support sules operations, marketing, customer service and finance departments. * ‘Translations for ull user screens and user documents. Post implementation support and enhancements. * — Salesl.ogix (CRM) projects to implement new products for us and international enterprise customers, Wrote user stories, functional specifications, upplication configumitions, coordinate QA anc UAT testing and post-implementation support for sales ops_ * Gather, document, and analyze client functional, transactional and insurance product business requirements for first Best's underwriting management system (UMS). Client facing and consultative role offering system solutions to enhance client implementations and transform client worktlow and business processes. * Between the customer and technical team providing support throughout the project development life cycle. Used the UMS configuration tool to build and maintain application forms and rules. Sales team support on REP. Sr. Business System Analyst FIRSTBEST SYSTEMS - November 2005 — April 2014 * Co-lead 4 two year-long series of implementations through requirements gathering sessions, functional. 0 This Eres Resume Template is the copyright of Qwikresume.corm. Usage Guidelines", "metadata": {"filename": "133933ee492cb76f.pdf", "original_category": "Business Analyst", "extraction_method": "ocr"}, "parsed_education": [], "extracted_skills": ["requirements gathering", "teams"], "parsed_summary": " Seasoned, accomplished Business Systems Analyst with an extensive history of supporting enterprise-level solution development through highest caliber of needs analysis. requirements definition, functionalAechnical specification development, application testing, and post-implementation support, Superior ability to liaise und coordinate with internal and extemal stakeholders while collaborating with on and offshore project teams. Offshore, Testing, Training. UAT. User Stories., Use Cases, NetSuite, CRM, Marketo, Insurance Systems WORK", "personal_info": {"phone": "(0123)-456-789", "first_name": null, "last_name": null}}
{"cv_id": "133933ee492cb76f", "target_role": "DevOps Engineer", "score": 0, "cv_text": "ROBERT SMITH Sr. Business System Analyst - Health Care E-mail: info@qwikresume.com Phone: (0123)-456-789 SUMMARY Seasoned, accomplished Business Systems Analyst with an extensive history of supporting enterprise-level solution development through highest caliber of needs analysis. requirements definition, functionalAechnical specification development, application testing, and post-implementation support, Superior ability to liaise und coordinate with internal and extemal stakeholders while collaborating with on and offshore project teams. Offshore, Testing, Training. UAT. User Stories., Use Cases, NetSuite, CRM, Marketo, Insurance Systems WORK EXPERIENCE Sr. Business System Analyst - Health Care UPTODATE - June 2014 — Present * UpToDate is an evidence-based clinical decision support resource for healthcare practitioners. Assess and analyze the business environment to detine the scope of the business problems, capturing project requirements, * Objectives and expectations. Elicit requirements for projects, enhancements, or defect fx requests using Interviews, workshops, data analysis, current business process descriptions, task, and workflow analysis. * Functional specifications, data mappings, and user stories. Support sules operations, marketing, customer service and finance departments. * ‘Translations for ull user screens and user documents. Post implementation support and enhancements. * — Salesl.ogix (CRM) projects to implement new products for us and international enterprise customers, Wrote user stories, functional specifications, upplication configumitions, coordinate QA anc UAT testing and post-implementation support for sales ops_ * Gather, document, and analyze client functional, transactional and insurance product business requirements for first Best's underwriting management system (UMS). Client facing and consultative role offering system solutions to enhance client implementations and transform client worktlow and business processes. * Between the customer and technical team providing support throughout the project development life cycle. Used the UMS configuration tool to build and maintain application forms and rules. Sales team support on REP. Sr. Business System Analyst FIRSTBEST SYSTEMS - November 2005 — April 2014 * Co-lead 4 two year-long series of implementations through requirements gathering sessions, functional. 0 This Eres Resume Template is the copyright of Qwikresume.corm. Usage Guidelines", "metadata": {"filename": "133933ee492cb76f.pdf", "original_category": "Business Analyst", "extraction_method": "ocr"}, "parsed_education": [], "extracted_skills": ["requirements gathering", "teams"], "parsed_summary": " Seasoned, accomplished Business Systems Analyst with an extensive history of supporting enterprise-level solution development through highest caliber of needs analysis. requirements definition, functionalAechnical specification development, application testing, and post-implementation support, Superior ability to liaise und coordinate with internal and extemal stakeholders while collaborating with on and offshore project teams. Offshore, Testing, Training. UAT. User Stories., Use Cases, NetSuite, CRM, Marketo, Insurance Systems WORK", "personal_info": {"phone": "(0123)-456-789", "first_name": null, "last_name": null}}
{"cv_id": "133933ee492cb76f", "target_role": "ETL Developer", "score": 0, "cv_text": "ROBERT SMITH Sr. Business System Analyst - Health Care E-mail: info@qwikresume.com Phone: (0123)-456-789 SUMMARY Seasoned, accomplished Business Systems Analyst with an extensive history of supporting enterprise-level solution development through highest caliber of needs analysis. requirements definition, functionalAechnical specification development, application testing, and post-implementation support, Superior ability to liaise und coordinate with internal and extemal stakeholders while collaborating with on and offshore project teams. Offshore, Testing, Training. UAT. User Stories., Use Cases, NetSuite, CRM, Marketo, Insurance Systems WORK EXPERIENCE Sr. Business System Analyst - Health Care UPTODATE - June 2014 — Present * UpToDate is an evidence-based clinical decision support resource for healthcare practitioners. Assess and analyze the business environment to detine the scope of the business problems, capturing project requirements, * Objectives and expectations. Elicit requirements for projects, enhancements, or defect fx requests using Interviews, workshops, data analysis, current business process descriptions, task, and workflow analysis. * Functional specifications, data mappings, and user stories. Support sules operations, marketing, customer service and finance departments. * ‘Translations for ull user screens and user documents. Post implementation support and enhancements. * — Salesl.ogix (CRM) projects to implement new products for us and international enterprise customers, Wrote user stories, functional specifications, upplication configumitions, coordinate QA anc UAT testing and post-implementation support for sales ops_ * Gather, document, and analyze client functional, transactional and insurance product business requirements for first Best's underwriting management system (UMS). Client facing and consultative role offering system solutions to enhance client implementations and transform client worktlow and business processes. * Between the customer and technical team providing support throughout the project development life cycle. Used the UMS configuration tool to build and maintain application forms and rules. Sales team support on REP. Sr. Business System Analyst FIRSTBEST SYSTEMS - November 2005 — April 2014 * Co-lead 4 two year-long series of implementations through requirements gathering sessions, functional. 0 This Eres Resume Template is the copyright of Qwikresume.corm. Usage Guidelines", "metadata": {"filename": "133933ee492cb76f.pdf", "original_category": "Business Analyst", "extraction_method": "ocr"}, "parsed_education": [], "extracted_skills": ["requirements gathering", "teams"], "parsed_summary": " Seasoned, accomplished Business Systems Analyst with an extensive history of supporting enterprise-level solution development through highest caliber of needs analysis. requirements definition, functionalAechnical specification development, application testing, and post-implementation support, Superior ability to liaise und coordinate with internal and extemal stakeholders while collaborating with on and offshore project teams. Offshore, Testing, Training. UAT. User Stories., Use Cases, NetSuite, CRM, Marketo, Insurance Systems WORK", "personal_info": {"phone": "(0123)-456-789", "first_name": null, "last_name": null}}
{"cv_id": "133933ee492cb76f", "target_role": "Java Developer", "score": 0, "cv_text": "ROBERT SMITH Sr. Business System Analyst - Health Care E-mail: info@qwikresume.com Phone: (0123)-456-789 SUMMARY Seasoned, accomplished Business Systems Analyst with an extensive history of supporting enterprise-level solution development through highest caliber of needs analysis. requirements definition, functionalAechnical specification development, application testing, and post-implementation support, Superior ability to liaise und coordinate with internal and extemal stakeholders while collaborating with on and offshore project teams. Offshore, Testing, Training. UAT. User Stories., Use Cases, NetSuite, CRM, Marketo, Insurance Systems WORK EXPERIENCE Sr. Business System Analyst - Health Care UPTODATE - June 2014 — Present * UpToDate is an evidence-based clinical decision support resource for healthcare practitioners. Assess and analyze the business environment to detine the scope of the business problems, capturing project requirements, * Objectives and expectations. Elicit requirements for projects, enhancements, or defect fx requests using Interviews, workshops, data analysis, current business process descriptions, task, and workflow analysis. * Functional specifications, data mappings, and user stories. Support sules operations, marketing, customer service and finance departments. * ‘Translations for ull user screens and user documents. Post implementation support and enhancements. * — Salesl.ogix (CRM) projects to implement new products for us and international enterprise customers, Wrote user stories, functional specifications, upplication configumitions, coordinate QA anc UAT testing and post-implementation support for sales ops_ * Gather, document, and analyze client functional, transactional and insurance product business requirements for first Best's underwriting management system (UMS). Client facing and consultative role offering system solutions to enhance client implementations and transform client worktlow and business processes. * Between the customer and technical team providing support throughout the project development life cycle. Used the UMS configuration tool to build and maintain application forms and rules. Sales team support on REP. Sr. Business System Analyst FIRSTBEST SYSTEMS - November 2005 — April 2014 * Co-lead 4 two year-long series of implementations through requirements gathering sessions, functional. 0 This Eres Resume Template is the copyright of Qwikresume.corm. Usage Guidelines", "metadata": {"filename": "133933ee492cb76f.pdf", "original_category": "Business Analyst", "extraction_method": "ocr"}, "parsed_education": [], "extracted_skills": ["requirements gathering", "teams"], "parsed_summary": " Seasoned, accomplished Business Systems Analyst with an extensive history of supporting enterprise-level solution development through highest caliber of needs analysis. requirements definition, functionalAechnical specification development, application testing, and post-implementation support, Superior ability to liaise und coordinate with internal and extemal stakeholders while collaborating with on and offshore project teams. Offshore, Testing, Training. UAT. User Stories., Use Cases, NetSuite, CRM, Marketo, Insurance Systems WORK", "personal_info": {"phone": "(0123)-456-789", "first_name": null, "last_name": null}}
{"cv_id": "133933ee492cb76f", "target_role": "Python Developer", "score": 0, "cv_text": "ROBERT SMITH Sr. Business System Analyst - Health Care E-mail: info@qwikresume.com Phone: (0123)-456-789 SUMMARY Seasoned, accomplished Business Systems Analyst with an extensive history of supporting enterprise-level solution development through highest caliber of needs analysis. requirements definition, functionalAechnical specification development, application testing, and post-implementation support, Superior ability to liaise und coordinate with internal and extemal stakeholders while collaborating with on and offshore project teams. Offshore, Testing, Training. UAT. User Stories., Use Cases, NetSuite, CRM, Marketo, Insurance Systems WORK EXPERIENCE Sr. Business System Analyst - Health Care UPTODATE - June 2014 — Present * UpToDate is an evidence-based clinical decision support resource for healthcare practitioners. Assess and analyze the business environment to detine the scope of the business problems, capturing project requirements, * Objectives and expectations. Elicit requirements for projects, enhancements, or defect fx requests using Interviews, workshops, data analysis, current business process descriptions, task, and workflow analysis. * Functional specifications, data mappings, and user stories. Support sules operations, marketing, customer service and finance departments. * ‘Translations for ull user screens and user documents. Post implementation support and enhancements. * — Salesl.ogix (CRM) projects to implement new products for us and international enterprise customers, Wrote user stories, functional specifications, upplication configumitions, coordinate QA anc UAT testing and post-implementation support for sales ops_ * Gather, document, and analyze client functional, transactional and insurance product business requirements for first Best's underwriting management system (UMS). Client facing and consultative role offering system solutions to enhance client implementations and transform client worktlow and business processes. * Between the customer and technical team providing support throughout the project development life cycle. Used the UMS configuration tool to build and maintain application forms and rules. Sales team support on REP. Sr. Business System Analyst FIRSTBEST SYSTEMS - November 2005 — April 2014 * Co-lead 4 two year-long series of implementations through requirements gathering sessions, functional. 0 This Eres Resume Template is the copyright of Qwikresume.corm. Usage Guidelines", "metadata": {"filename": "133933ee492cb76f.pdf", "original_category": "Business Analyst", "extraction_method": "ocr"}, "parsed_education": [], "extracted_skills": ["requirements gathering", "teams"], "parsed_summary": " Seasoned, accomplished Business Systems Analyst with an extensive history of supporting enterprise-level solution development through highest caliber of needs analysis. requirements definition, functionalAechnical specification development, application testing, and post-implementation support, Superior ability to liaise und coordinate with internal and extemal stakeholders while collaborating with on and offshore project teams. Offshore, Testing, Training. UAT. User Stories., Use Cases, NetSuite, CRM, Marketo, Insurance Systems WORK", "personal_info": {"phone": "(0123)-456-789", "first_name": null, "last_name": null}}
{"cv_id": "133933ee492cb76f", "target_role": "React Developer", "score": 0, "cv_text": "ROBERT SMITH Sr. Business System Analyst - Health Care E-mail: info@qwikresume.com Phone: (0123)-456-789 SUMMARY Seasoned, accomplished Business Systems Analyst with an extensive history of supporting enterprise-level solution development through highest caliber of needs analysis. requirements definition, functionalAechnical specification development, application testing, and post-implementation support, Superior ability to liaise und coordinate with internal and extemal stakeholders while collaborating with on and offshore project teams. Offshore, Testing, Training. UAT. User Stories., Use Cases, NetSuite, CRM, Marketo, Insurance Systems WORK EXPERIENCE Sr. Business System Analyst - Health Care UPTODATE - June 2014 — Present * UpToDate is an evidence-based clinical decision support resource for healthcare practitioners. Assess and analyze the business environment to detine the scope of the business problems, capturing project requirements, * Objectives and expectations. Elicit requirements for projects, enhancements, or defect fx requests using Interviews, workshops, data analysis, current business process descriptions, task, and workflow analysis. * Functional specifications, data mappings, and user stories. Support sules operations, marketing, customer service and finance departments. * ‘Translations for ull user screens and user documents. Post implementation support and enhancements. * — Salesl.ogix (CRM) projects to implement new products for us and international enterprise customers, Wrote user stories, functional specifications, upplication configumitions, coordinate QA anc UAT testing and post-implementation support for sales ops_ * Gather, document, and analyze client functional, transactional and insurance product business requirements for first Best's underwriting management system (UMS). Client facing and consultative role offering system solutions to enhance client implementations and transform client worktlow and business processes. * Between the customer and technical team providing support throughout the project development life cycle. Used the UMS configuration tool to build and maintain application forms and rules. Sales team support on REP. Sr. Business System Analyst FIRSTBEST SYSTEMS - November 2005 — April 2014 * Co-lead 4 two year-long series of implementations through requirements gathering sessions, functional. 0 This Eres Resume Template is the copyright of Qwikresume.corm. Usage Guidelines", "metadata": {"filename": "133933ee492cb76f.pdf", "original_category": "Business Analyst", "extraction_method": "ocr"}, "parsed_education": [], "extracted_skills": ["requirements gathering", "teams"], "parsed_summary": " Seasoned, accomplished Business Systems Analyst with an extensive history of supporting enterprise-level solution development through highest caliber of needs analysis. requirements definition, functionalAechnical specification development, application testing, and post-implementation support, Superior ability to liaise und coordinate with internal and extemal stakeholders while collaborating with on and offshore project teams. Offshore, Testing, Training. UAT. User Stories., Use Cases, NetSuite, CRM, Marketo, Insurance Systems WORK", "personal_info": {"phone": "(0123)-456-789", "first_name": null, "last_name": null}}
{"cv_id": "133933ee492cb76f", "target_role": "SQL Developer", "score": 2, "cv_text": "ROBERT SMITH Sr. Business System Analyst - Health Care E-mail: info@qwikresume.com Phone: (0123)-456-789 SUMMARY Seasoned, accomplished Business Systems Analyst with an extensive history of supporting enterprise-level solution development through highest caliber of needs analysis. requirements definition, functionalAechnical specification development, application testing, and post-implementation support, Superior ability to liaise und coordinate with internal and extemal stakeholders while collaborating with on and offshore project teams. Offshore, Testing, Training. UAT. User Stories., Use Cases, NetSuite, CRM, Marketo, Insurance Systems WORK EXPERIENCE Sr. Business System Analyst - Health Care UPTODATE - June 2014 — Present * UpToDate is an evidence-based clinical decision support resource for healthcare practitioners. Assess and analyze the business environment to detine the scope of the business problems, capturing project requirements, * Objectives and expectations. Elicit requirements for projects, enhancements, or defect fx requests using Interviews, workshops, data analysis, current business process descriptions, task, and workflow analysis. * Functional specifications, data mappings, and user stories. Support sules operations, marketing, customer service and finance departments. * ‘Translations for ull user screens and user documents. Post implementation support and enhancements. * — Salesl.ogix (CRM) projects to implement new products for us and international enterprise customers, Wrote user stories, functional specifications, upplication configumitions, coordinate QA anc UAT testing and post-implementation support for sales ops_ * Gather, document, and analyze client functional, transactional and insurance product business requirements for first Best's underwriting management system (UMS). Client facing and consultative role offering system solutions to enhance client implementations and transform client worktlow and business processes. * Between the customer and technical team providing support throughout the project development life cycle. Used the UMS configuration tool to build and maintain application forms and rules. Sales team support on REP. Sr. Business System Analyst FIRSTBEST SYSTEMS - November 2005 — April 2014 * Co-lead 4 two year-long series of implementations through requirements gathering sessions, functional. 0 This Eres Resume Template is the copyright of Qwikresume.corm. Usage Guidelines", "metadata": {"filename": "133933ee492cb76f.pdf", "original_category": "Business Analyst", "extraction_method": "ocr"}, "parsed_education": [], "extracted_skills": ["requirements gathering", "teams"], "parsed_summary": " Seasoned, accomplished Business Systems Analyst with an extensive history of supporting enterprise-level solution development through highest caliber of needs analysis. requirements definition, functionalAechnical specification development, application testing, and post-implementation support, Superior ability to liaise und coordinate with internal and extemal stakeholders while collaborating with on and offshore project teams. Offshore, Testing, Training. UAT. User Stories., Use Cases, NetSuite, CRM, Marketo, Insurance Systems WORK", "personal_info": {"phone": "(0123)-456-789", "first_name": null, "last_name": null}}
{"cv_id": "133933ee492cb76f", "target_role": "Web Developer", "score": 0, "cv_text": "ROBERT SMITH Sr. Business System Analyst - Health Care E-mail: info@qwikresume.com Phone: (0123)-456-789 SUMMARY Seasoned, accomplished Business Systems Analyst with an extensive history of supporting enterprise-level solution development through highest caliber of needs analysis. requirements definition, functionalAechnical specification development, application testing, and post-implementation support, Superior ability to liaise und coordinate with internal and extemal stakeholders while collaborating with on and offshore project teams. Offshore, Testing, Training. UAT. User Stories., Use Cases, NetSuite, CRM, Marketo, Insurance Systems WORK EXPERIENCE Sr. Business System Analyst - Health Care UPTODATE - June 2014 — Present * UpToDate is an evidence-based clinical decision support resource for healthcare practitioners. Assess and analyze the business environment to detine the scope of the business problems, capturing project requirements, * Objectives and expectations. Elicit requirements for projects, enhancements, or defect fx requests using Interviews, workshops, data analysis, current business process descriptions, task, and workflow analysis. * Functional specifications, data mappings, and user stories. Support sules operations, marketing, customer service and finance departments. * ‘Translations for ull user screens and user documents. Post implementation support and enhancements. * — Salesl.ogix (CRM) projects to implement new products for us and international enterprise customers, Wrote user stories, functional specifications, upplication configumitions, coordinate QA anc UAT testing and post-implementation support for sales ops_ * Gather, document, and analyze client functional, transactional and insurance product business requirements for first Best's underwriting management system (UMS). Client facing and consultative role offering system solutions to enhance client implementations and transform client worktlow and business processes. * Between the customer and technical team providing support throughout the project development life cycle. Used the UMS configuration tool to build and maintain application forms and rules. Sales team support on REP. Sr. Business System Analyst FIRSTBEST SYSTEMS - November 2005 — April 2014 * Co-lead 4 two year-long series of implementations through requirements gathering sessions, functional. 0 This Eres Resume Template is the copyright of Qwikresume.corm. Usage Guidelines", "metadata": {"filename": "133933ee492cb76f.pdf", "original_category": "Business Analyst", "extraction_method": "ocr"}, "parsed_education": [], "extracted_skills": ["requirements gathering", "teams"], "parsed_summary": " Seasoned, accomplished Business Systems Analyst with an extensive history of supporting enterprise-level solution development through highest caliber of needs analysis. requirements definition, functionalAechnical specification development, application testing, and post-implementation support, Superior ability to liaise und coordinate with internal and extemal stakeholders while collaborating with on and offshore project teams. Offshore, Testing, Training. UAT. User Stories., Use Cases, NetSuite, CRM, Marketo, Insurance Systems WORK", "personal_info": {"phone": "(0123)-456-789", "first_name": null, "last_name": null}}
{"cv_id": "133933ee492cb76f", "target_role": "SAP Developer", "score": 2, "cv_text": "ROBERT SMITH Sr. Business System Analyst - Health Care E-mail: info@qwikresume.com Phone: (0123)-456-789 SUMMARY Seasoned, accomplished Business Systems Analyst with an extensive history of supporting enterprise-level solution development through highest caliber of needs analysis. requirements definition, functionalAechnical specification development, application testing, and post-implementation support, Superior ability to liaise und coordinate with internal and extemal stakeholders while collaborating with on and offshore project teams. Offshore, Testing, Training. UAT. User Stories., Use Cases, NetSuite, CRM, Marketo, Insurance Systems WORK EXPERIENCE Sr. Business System Analyst - Health Care UPTODATE - June 2014 — Present * UpToDate is an evidence-based clinical decision support resource for healthcare practitioners. Assess and analyze the business environment to detine the scope of the business problems, capturing project requirements, * Objectives and expectations. Elicit requirements for projects, enhancements, or defect fx requests using Interviews, workshops, data analysis, current business process descriptions, task, and workflow analysis. * Functional specifications, data mappings, and user stories. Support sules operations, marketing, customer service and finance departments. * ‘Translations for ull user screens and user documents. Post implementation support and enhancements. * — Salesl.ogix (CRM) projects to implement new products for us and international enterprise customers, Wrote user stories, functional specifications, upplication configumitions, coordinate QA anc UAT testing and post-implementation support for sales ops_ * Gather, document, and analyze client functional, transactional and insurance product business requirements for first Best's underwriting management system (UMS). Client facing and consultative role offering system solutions to enhance client implementations and transform client worktlow and business processes. * Between the customer and technical team providing support throughout the project development life cycle. Used the UMS configuration tool to build and maintain application forms and rules. Sales team support on REP. Sr. Business System Analyst FIRSTBEST SYSTEMS - November 2005 — April 2014 * Co-lead 4 two year-long series of implementations through requirements gathering sessions, functional. 0 This Eres Resume Template is the copyright of Qwikresume.corm. Usage Guidelines", "metadata": {"filename": "133933ee492cb76f.pdf", "original_category": "Business Analyst", "extraction_method": "ocr"}, "parsed_education": [], "extracted_skills": ["requirements gathering", "teams"], "parsed_summary": " Seasoned, accomplished Business Systems Analyst with an extensive history of supporting enterprise-level solution development through highest caliber of needs analysis. requirements definition, functionalAechnical specification development, application testing, and post-implementation support, Superior ability to liaise und coordinate with internal and extemal stakeholders while collaborating with on and offshore project teams. Offshore, Testing, Training. UAT. User Stories., Use Cases, NetSuite, CRM, Marketo, Insurance Systems WORK", "personal_info": {"phone": "(0123)-456-789", "first_name": null, "last_name": null}}
{"cv_id": "133933ee492cb76f", "target_role": "Tester", "score": 0, "cv_text": "ROBERT SMITH Sr. Business System Analyst - Health Care E-mail: info@qwikresume.com Phone: (0123)-456-789 SUMMARY Seasoned, accomplished Business Systems Analyst with an extensive history of supporting enterprise-level solution development through highest caliber of needs analysis. requirements definition, functionalAechnical specification development, application testing, and post-implementation support, Superior ability to liaise und coordinate with internal and extemal stakeholders while collaborating with on and offshore project teams. Offshore, Testing, Training. UAT. User Stories., Use Cases, NetSuite, CRM, Marketo, Insurance Systems WORK EXPERIENCE Sr. Business System Analyst - Health Care UPTODATE - June 2014 — Present * UpToDate is an evidence-based clinical decision support resource for healthcare practitioners. Assess and analyze the business environment to detine the scope of the business problems, capturing project requirements, * Objectives and expectations. Elicit requirements for projects, enhancements, or defect fx requests using Interviews, workshops, data analysis, current business process descriptions, task, and workflow analysis. * Functional specifications, data mappings, and user stories. Support sules operations, marketing, customer service and finance departments. * ‘Translations for ull user screens and user documents. Post implementation support and enhancements. * — Salesl.ogix (CRM) projects to implement new products for us and international enterprise customers, Wrote user stories, functional specifications, upplication configumitions, coordinate QA anc UAT testing and post-implementation support for sales ops_ * Gather, document, and analyze client functional, transactional and insurance product business requirements for first Best's underwriting management system (UMS). Client facing and consultative role offering system solutions to enhance client implementations and transform client worktlow and business processes. * Between the customer and technical team providing support throughout the project development life cycle. Used the UMS configuration tool to build and maintain application forms and rules. Sales team support on REP. Sr. Business System Analyst FIRSTBEST SYSTEMS - November 2005 — April 2014 * Co-lead 4 two year-long series of implementations through requirements gathering sessions, functional. 0 This Eres Resume Template is the copyright of Qwikresume.corm. Usage Guidelines", "metadata": {"filename": "133933ee492cb76f.pdf", "original_category": "Business Analyst", "extraction_method": "ocr"}, "parsed_education": [], "extracted_skills": ["requirements gathering", "teams"], "parsed_summary": " Seasoned, accomplished Business Systems Analyst with an extensive history of supporting enterprise-level solution development through highest caliber of needs analysis. requirements definition, functionalAechnical specification development, application testing, and post-implementation support, Superior ability to liaise und coordinate with internal and extemal stakeholders while collaborating with on and offshore project teams. Offshore, Testing, Training. UAT. User Stories., Use Cases, NetSuite, CRM, Marketo, Insurance Systems WORK", "personal_info": {"phone": "(0123)-456-789", "first_name": null, "last_name": null}}
{"cv_id": "134f68fc1f1efe74", "target_role": "Business Analyst", "score": 5, "cv_text": "ISABELLE TODD Entry-Level Business Analyst & (971) @ isabelle_todd@hotmail.com @ imperfect-issue.info 9 Edmondbury, United States of America SUMMARY MY LIFE A highly analytical and results-driven business analyst with 3 PH | LOSOPHY years of experience in data analysis, statistical modeling, and data visualization. Skilled in using tools like Excel, Power BI, and Data is the new oil. The ability to Python to extract insights and drive decision-making. | am proud analyze and interpret data isa of my accomplishments, including the publication of a research valuable skill in today's business paper on customer segmentation, the development of an world. automated data tracking system, and my contributions to data- driven strategies that have positively impacted business outcomes. | am excited about the opportunity to leverage my skills and experience to support decision-making, policy STRENGTHS formation, and strategic planning as an entry-level business . . analyst at your organization. 5 Analytical Problem-Solving | possess a strong analytical mindset and excel at solving complex problems using data-driven approaches. My ability to EXPE RI E N CE interpret and analyze data allows me to make informed decisions and drive Data Ana lyst business success. ABC Company WP Collaboration and @ 2022- Ongoing 9 New York City Communication Analyzed and interpreted complex data sets to identify trends, patterns, lam an effective collaborator and and insights. Developed visualizations and interactive dashboards to communicator, skilled at working with communicate findings to stakeholders. cross-functional teams and presenting * Identified key customer segments resulting in a 10% increase in sales complex data insights in a clear and * Created regression models to predict customer churn, resulting in a 15% concise manner. | foster strong working reduction in churn rate relationships to achieve common goals. * Collaborated with cross-functional teams to develop data-driven strategies to optimize marketing campaigns 2 Adaptability and Continuous . * Learning Resea rch Assistant | embrace change and continuously seek XYZ University opportunities to expand my skill set and knowledge. | am a fast learner, always 8 2017-2022 9 Baltimore, MD . oo. a ; eager to explore new technologies and Conducted quantitative and qualitative research studies to gather data. methodologies to stay ahead in the rapidly Assisted in data analysis and report writing. Collaborated with professors evolving field of business analytics. on research projects. * Collected and analyzed survey data resulting in the publication of a research paper ¢ Assisted in conducting focus groups and interviews to gather data for SKI LLS research projects * Contributed to data cleaning and coding process to ensure data accuracy and reliability Data analysis Statistical modeling Data visualization SQL Excel Power BI Python R www.enhancv.com Powered by (CX? Enhancy", "metadata": {"filename": "134f68fc1f1efe74.pdf", "original_category": "Business Analyst", "extraction_method": "ocr"}, "parsed_education": [], "extracted_skills": ["Python", "excel", "SQL", "Communication", "Excel", "Power BI", "teams", "decision-making", "R"], "parsed_summary": " MY LIFE A highly analytical and results-driven business analyst with 3 PH | LOSOPHY years of", "personal_info": {"phone": "8 2017-2022 9", "first_name": null, "last_name": null}}
{"cv_id": "134f68fc1f1efe74", "target_role": "Data Scientist", "score": 1, "cv_text": "ISABELLE TODD Entry-Level Business Analyst & (971) @ isabelle_todd@hotmail.com @ imperfect-issue.info 9 Edmondbury, United States of America SUMMARY MY LIFE A highly analytical and results-driven business analyst with 3 PH | LOSOPHY years of experience in data analysis, statistical modeling, and data visualization. Skilled in using tools like Excel, Power BI, and Data is the new oil. The ability to Python to extract insights and drive decision-making. | am proud analyze and interpret data isa of my accomplishments, including the publication of a research valuable skill in today's business paper on customer segmentation, the development of an world. automated data tracking system, and my contributions to data- driven strategies that have positively impacted business outcomes. | am excited about the opportunity to leverage my skills and experience to support decision-making, policy STRENGTHS formation, and strategic planning as an entry-level business . . analyst at your organization. 5 Analytical Problem-Solving | possess a strong analytical mindset and excel at solving complex problems using data-driven approaches. My ability to EXPE RI E N CE interpret and analyze data allows me to make informed decisions and drive Data Ana lyst business success. ABC Company WP Collaboration and @ 2022- Ongoing 9 New York City Communication Analyzed and interpreted complex data sets to identify trends, patterns, lam an effective collaborator and and insights. Developed visualizations and interactive dashboards to communicator, skilled at working with communicate findings to stakeholders. cross-functional teams and presenting * Identified key customer segments resulting in a 10% increase in sales complex data insights in a clear and * Created regression models to predict customer churn, resulting in a 15% concise manner. | foster strong working reduction in churn rate relationships to achieve common goals. * Collaborated with cross-functional teams to develop data-driven strategies to optimize marketing campaigns 2 Adaptability and Continuous . * Learning Resea rch Assistant | embrace change and continuously seek XYZ University opportunities to expand my skill set and knowledge. | am a fast learner, always 8 2017-2022 9 Baltimore, MD . oo. a ; eager to explore new technologies and Conducted quantitative and qualitative research studies to gather data. methodologies to stay ahead in the rapidly Assisted in data analysis and report writing. Collaborated with professors evolving field of business analytics. on research projects. * Collected and analyzed survey data resulting in the publication of a research paper ¢ Assisted in conducting focus groups and interviews to gather data for SKI LLS research projects * Contributed to data cleaning and coding process to ensure data accuracy and reliability Data analysis Statistical modeling Data visualization SQL Excel Power BI Python R www.enhancv.com Powered by (CX? Enhancy", "metadata": {"filename": "134f68fc1f1efe74.pdf", "original_category": "Business Analyst", "extraction_method": "ocr"}, "parsed_education": [], "extracted_skills": ["Python", "excel", "SQL", "Communication", "Excel", "Power BI", "teams", "decision-making", "R"], "parsed_summary": " MY LIFE A highly analytical and results-driven business analyst with 3 PH | LOSOPHY years of", "personal_info": {"phone": "8 2017-2022 9", "first_name": null, "last_name": null}}
{"cv_id": "134f68fc1f1efe74", "target_role": "DevOps Engineer", "score": 0, "cv_text": "ISABELLE TODD Entry-Level Business Analyst & (971) @ isabelle_todd@hotmail.com @ imperfect-issue.info 9 Edmondbury, United States of America SUMMARY MY LIFE A highly analytical and results-driven business analyst with 3 PH | LOSOPHY years of experience in data analysis, statistical modeling, and data visualization. Skilled in using tools like Excel, Power BI, and Data is the new oil. The ability to Python to extract insights and drive decision-making. | am proud analyze and interpret data isa of my accomplishments, including the publication of a research valuable skill in today's business paper on customer segmentation, the development of an world. automated data tracking system, and my contributions to data- driven strategies that have positively impacted business outcomes. | am excited about the opportunity to leverage my skills and experience to support decision-making, policy STRENGTHS formation, and strategic planning as an entry-level business . . analyst at your organization. 5 Analytical Problem-Solving | possess a strong analytical mindset and excel at solving complex problems using data-driven approaches. My ability to EXPE RI E N CE interpret and analyze data allows me to make informed decisions and drive Data Ana lyst business success. ABC Company WP Collaboration and @ 2022- Ongoing 9 New York City Communication Analyzed and interpreted complex data sets to identify trends, patterns, lam an effective collaborator and and insights. Developed visualizations and interactive dashboards to communicator, skilled at working with communicate findings to stakeholders. cross-functional teams and presenting * Identified key customer segments resulting in a 10% increase in sales complex data insights in a clear and * Created regression models to predict customer churn, resulting in a 15% concise manner. | foster strong working reduction in churn rate relationships to achieve common goals. * Collaborated with cross-functional teams to develop data-driven strategies to optimize marketing campaigns 2 Adaptability and Continuous . * Learning Resea rch Assistant | embrace change and continuously seek XYZ University opportunities to expand my skill set and knowledge. | am a fast learner, always 8 2017-2022 9 Baltimore, MD . oo. a ; eager to explore new technologies and Conducted quantitative and qualitative research studies to gather data. methodologies to stay ahead in the rapidly Assisted in data analysis and report writing. Collaborated with professors evolving field of business analytics. on research projects. * Collected and analyzed survey data resulting in the publication of a research paper ¢ Assisted in conducting focus groups and interviews to gather data for SKI LLS research projects * Contributed to data cleaning and coding process to ensure data accuracy and reliability Data analysis Statistical modeling Data visualization SQL Excel Power BI Python R www.enhancv.com Powered by (CX? Enhancy", "metadata": {"filename": "134f68fc1f1efe74.pdf", "original_category": "Business Analyst", "extraction_method": "ocr"}, "parsed_education": [], "extracted_skills": ["Python", "excel", "SQL", "Communication", "Excel", "Power BI", "teams", "decision-making", "R"], "parsed_summary": " MY LIFE A highly analytical and results-driven business analyst with 3 PH | LOSOPHY years of", "personal_info": {"phone": "8 2017-2022 9", "first_name": null, "last_name": null}}
{"cv_id": "134f68fc1f1efe74", "target_role": "ETL Developer", "score": 0, "cv_text": "ISABELLE TODD Entry-Level Business Analyst & (971) @ isabelle_todd@hotmail.com @ imperfect-issue.info 9 Edmondbury, United States of America SUMMARY MY LIFE A highly analytical and results-driven business analyst with 3 PH | LOSOPHY years of experience in data analysis, statistical modeling, and data visualization. Skilled in using tools like Excel, Power BI, and Data is the new oil. The ability to Python to extract insights and drive decision-making. | am proud analyze and interpret data isa of my accomplishments, including the publication of a research valuable skill in today's business paper on customer segmentation, the development of an world. automated data tracking system, and my contributions to data- driven strategies that have positively impacted business outcomes. | am excited about the opportunity to leverage my skills and experience to support decision-making, policy STRENGTHS formation, and strategic planning as an entry-level business . . analyst at your organization. 5 Analytical Problem-Solving | possess a strong analytical mindset and excel at solving complex problems using data-driven approaches. My ability to EXPE RI E N CE interpret and analyze data allows me to make informed decisions and drive Data Ana lyst business success. ABC Company WP Collaboration and @ 2022- Ongoing 9 New York City Communication Analyzed and interpreted complex data sets to identify trends, patterns, lam an effective collaborator and and insights. Developed visualizations and interactive dashboards to communicator, skilled at working with communicate findings to stakeholders. cross-functional teams and presenting * Identified key customer segments resulting in a 10% increase in sales complex data insights in a clear and * Created regression models to predict customer churn, resulting in a 15% concise manner. | foster strong working reduction in churn rate relationships to achieve common goals. * Collaborated with cross-functional teams to develop data-driven strategies to optimize marketing campaigns 2 Adaptability and Continuous . * Learning Resea rch Assistant | embrace change and continuously seek XYZ University opportunities to expand my skill set and knowledge. | am a fast learner, always 8 2017-2022 9 Baltimore, MD . oo. a ; eager to explore new technologies and Conducted quantitative and qualitative research studies to gather data. methodologies to stay ahead in the rapidly Assisted in data analysis and report writing. Collaborated with professors evolving field of business analytics. on research projects. * Collected and analyzed survey data resulting in the publication of a research paper ¢ Assisted in conducting focus groups and interviews to gather data for SKI LLS research projects * Contributed to data cleaning and coding process to ensure data accuracy and reliability Data analysis Statistical modeling Data visualization SQL Excel Power BI Python R www.enhancv.com Powered by (CX? Enhancy", "metadata": {"filename": "134f68fc1f1efe74.pdf", "original_category": "Business Analyst", "extraction_method": "ocr"}, "parsed_education": [], "extracted_skills": ["Python", "excel", "SQL", "Communication", "Excel", "Power BI", "teams", "decision-making", "R"], "parsed_summary": " MY LIFE A highly analytical and results-driven business analyst with 3 PH | LOSOPHY years of", "personal_info": {"phone": "8 2017-2022 9", "first_name": null, "last_name": null}}
{"cv_id": "134f68fc1f1efe74", "target_role": "Java Developer", "score": 0, "cv_text": "ISABELLE TODD Entry-Level Business Analyst & (971) @ isabelle_todd@hotmail.com @ imperfect-issue.info 9 Edmondbury, United States of America SUMMARY MY LIFE A highly analytical and results-driven business analyst with 3 PH | LOSOPHY years of experience in data analysis, statistical modeling, and data visualization. Skilled in using tools like Excel, Power BI, and Data is the new oil. The ability to Python to extract insights and drive decision-making. | am proud analyze and interpret data isa of my accomplishments, including the publication of a research valuable skill in today's business paper on customer segmentation, the development of an world. automated data tracking system, and my contributions to data- driven strategies that have positively impacted business outcomes. | am excited about the opportunity to leverage my skills and experience to support decision-making, policy STRENGTHS formation, and strategic planning as an entry-level business . . analyst at your organization. 5 Analytical Problem-Solving | possess a strong analytical mindset and excel at solving complex problems using data-driven approaches. My ability to EXPE RI E N CE interpret and analyze data allows me to make informed decisions and drive Data Ana lyst business success. ABC Company WP Collaboration and @ 2022- Ongoing 9 New York City Communication Analyzed and interpreted complex data sets to identify trends, patterns, lam an effective collaborator and and insights. Developed visualizations and interactive dashboards to communicator, skilled at working with communicate findings to stakeholders. cross-functional teams and presenting * Identified key customer segments resulting in a 10% increase in sales complex data insights in a clear and * Created regression models to predict customer churn, resulting in a 15% concise manner. | foster strong working reduction in churn rate relationships to achieve common goals. * Collaborated with cross-functional teams to develop data-driven strategies to optimize marketing campaigns 2 Adaptability and Continuous . * Learning Resea rch Assistant | embrace change and continuously seek XYZ University opportunities to expand my skill set and knowledge. | am a fast learner, always 8 2017-2022 9 Baltimore, MD . oo. a ; eager to explore new technologies and Conducted quantitative and qualitative research studies to gather data. methodologies to stay ahead in the rapidly Assisted in data analysis and report writing. Collaborated with professors evolving field of business analytics. on research projects. * Collected and analyzed survey data resulting in the publication of a research paper ¢ Assisted in conducting focus groups and interviews to gather data for SKI LLS research projects * Contributed to data cleaning and coding process to ensure data accuracy and reliability Data analysis Statistical modeling Data visualization SQL Excel Power BI Python R www.enhancv.com Powered by (CX? Enhancy", "metadata": {"filename": "134f68fc1f1efe74.pdf", "original_category": "Business Analyst", "extraction_method": "ocr"}, "parsed_education": [], "extracted_skills": ["Python", "excel", "SQL", "Communication", "Excel", "Power BI", "teams", "decision-making", "R"], "parsed_summary": " MY LIFE A highly analytical and results-driven business analyst with 3 PH | LOSOPHY years of", "personal_info": {"phone": "8 2017-2022 9", "first_name": null, "last_name": null}}
{"cv_id": "134f68fc1f1efe74", "target_role": "Python Developer", "score": 0, "cv_text": "ISABELLE TODD Entry-Level Business Analyst & (971) @ isabelle_todd@hotmail.com @ imperfect-issue.info 9 Edmondbury, United States of America SUMMARY MY LIFE A highly analytical and results-driven business analyst with 3 PH | LOSOPHY years of experience in data analysis, statistical modeling, and data visualization. Skilled in using tools like Excel, Power BI, and Data is the new oil. The ability to Python to extract insights and drive decision-making. | am proud analyze and interpret data isa of my accomplishments, including the publication of a research valuable skill in today's business paper on customer segmentation, the development of an world. automated data tracking system, and my contributions to data- driven strategies that have positively impacted business outcomes. | am excited about the opportunity to leverage my skills and experience to support decision-making, policy STRENGTHS formation, and strategic planning as an entry-level business . . analyst at your organization. 5 Analytical Problem-Solving | possess a strong analytical mindset and excel at solving complex problems using data-driven approaches. My ability to EXPE RI E N CE interpret and analyze data allows me to make informed decisions and drive Data Ana lyst business success. ABC Company WP Collaboration and @ 2022- Ongoing 9 New York City Communication Analyzed and interpreted complex data sets to identify trends, patterns, lam an effective collaborator and and insights. Developed visualizations and interactive dashboards to communicator, skilled at working with communicate findings to stakeholders. cross-functional teams and presenting * Identified key customer segments resulting in a 10% increase in sales complex data insights in a clear and * Created regression models to predict customer churn, resulting in a 15% concise manner. | foster strong working reduction in churn rate relationships to achieve common goals. * Collaborated with cross-functional teams to develop data-driven strategies to optimize marketing campaigns 2 Adaptability and Continuous . * Learning Resea rch Assistant | embrace change and continuously seek XYZ University opportunities to expand my skill set and knowledge. | am a fast learner, always 8 2017-2022 9 Baltimore, MD . oo. a ; eager to explore new technologies and Conducted quantitative and qualitative research studies to gather data. methodologies to stay ahead in the rapidly Assisted in data analysis and report writing. Collaborated with professors evolving field of business analytics. on research projects. * Collected and analyzed survey data resulting in the publication of a research paper ¢ Assisted in conducting focus groups and interviews to gather data for SKI LLS research projects * Contributed to data cleaning and coding process to ensure data accuracy and reliability Data analysis Statistical modeling Data visualization SQL Excel Power BI Python R www.enhancv.com Powered by (CX? Enhancy", "metadata": {"filename": "134f68fc1f1efe74.pdf", "original_category": "Business Analyst", "extraction_method": "ocr"}, "parsed_education": [], "extracted_skills": ["Python", "excel", "SQL", "Communication", "Excel", "Power BI", "teams", "decision-making", "R"], "parsed_summary": " MY LIFE A highly analytical and results-driven business analyst with 3 PH | LOSOPHY years of", "personal_info": {"phone": "8 2017-2022 9", "first_name": null, "last_name": null}}
{"cv_id": "134f68fc1f1efe74", "target_role": "React Developer", "score": 0, "cv_text": "ISABELLE TODD Entry-Level Business Analyst & (971) @ isabelle_todd@hotmail.com @ imperfect-issue.info 9 Edmondbury, United States of America SUMMARY MY LIFE A highly analytical and results-driven business analyst with 3 PH | LOSOPHY years of experience in data analysis, statistical modeling, and data visualization. Skilled in using tools like Excel, Power BI, and Data is the new oil. The ability to Python to extract insights and drive decision-making. | am proud analyze and interpret data isa of my accomplishments, including the publication of a research valuable skill in today's business paper on customer segmentation, the development of an world. automated data tracking system, and my contributions to data- driven strategies that have positively impacted business outcomes. | am excited about the opportunity to leverage my skills and experience to support decision-making, policy STRENGTHS formation, and strategic planning as an entry-level business . . analyst at your organization. 5 Analytical Problem-Solving | possess a strong analytical mindset and excel at solving complex problems using data-driven approaches. My ability to EXPE RI E N CE interpret and analyze data allows me to make informed decisions and drive Data Ana lyst business success. ABC Company WP Collaboration and @ 2022- Ongoing 9 New York City Communication Analyzed and interpreted complex data sets to identify trends, patterns, lam an effective collaborator and and insights. Developed visualizations and interactive dashboards to communicator, skilled at working with communicate findings to stakeholders. cross-functional teams and presenting * Identified key customer segments resulting in a 10% increase in sales complex data insights in a clear and * Created regression models to predict customer churn, resulting in a 15% concise manner. | foster strong working reduction in churn rate relationships to achieve common goals. * Collaborated with cross-functional teams to develop data-driven strategies to optimize marketing campaigns 2 Adaptability and Continuous . * Learning Resea rch Assistant | embrace change and continuously seek XYZ University opportunities to expand my skill set and knowledge. | am a fast learner, always 8 2017-2022 9 Baltimore, MD . oo. a ; eager to explore new technologies and Conducted quantitative and qualitative research studies to gather data. methodologies to stay ahead in the rapidly Assisted in data analysis and report writing. Collaborated with professors evolving field of business analytics. on research projects. * Collected and analyzed survey data resulting in the publication of a research paper ¢ Assisted in conducting focus groups and interviews to gather data for SKI LLS research projects * Contributed to data cleaning and coding process to ensure data accuracy and reliability Data analysis Statistical modeling Data visualization SQL Excel Power BI Python R www.enhancv.com Powered by (CX? Enhancy", "metadata": {"filename": "134f68fc1f1efe74.pdf", "original_category": "Business Analyst", "extraction_method": "ocr"}, "parsed_education": [], "extracted_skills": ["Python", "excel", "SQL", "Communication", "Excel", "Power BI", "teams", "decision-making", "R"], "parsed_summary": " MY LIFE A highly analytical and results-driven business analyst with 3 PH | LOSOPHY years of", "personal_info": {"phone": "8 2017-2022 9", "first_name": null, "last_name": null}}
{"cv_id": "134f68fc1f1efe74", "target_role": "SQL Developer", "score": 2, "cv_text": "ISABELLE TODD Entry-Level Business Analyst & (971) @ isabelle_todd@hotmail.com @ imperfect-issue.info 9 Edmondbury, United States of America SUMMARY MY LIFE A highly analytical and results-driven business analyst with 3 PH | LOSOPHY years of experience in data analysis, statistical modeling, and data visualization. Skilled in using tools like Excel, Power BI, and Data is the new oil. The ability to Python to extract insights and drive decision-making. | am proud analyze and interpret data isa of my accomplishments, including the publication of a research valuable skill in today's business paper on customer segmentation, the development of an world. automated data tracking system, and my contributions to data- driven strategies that have positively impacted business outcomes. | am excited about the opportunity to leverage my skills and experience to support decision-making, policy STRENGTHS formation, and strategic planning as an entry-level business . . analyst at your organization. 5 Analytical Problem-Solving | possess a strong analytical mindset and excel at solving complex problems using data-driven approaches. My ability to EXPE RI E N CE interpret and analyze data allows me to make informed decisions and drive Data Ana lyst business success. ABC Company WP Collaboration and @ 2022- Ongoing 9 New York City Communication Analyzed and interpreted complex data sets to identify trends, patterns, lam an effective collaborator and and insights. Developed visualizations and interactive dashboards to communicator, skilled at working with communicate findings to stakeholders. cross-functional teams and presenting * Identified key customer segments resulting in a 10% increase in sales complex data insights in a clear and * Created regression models to predict customer churn, resulting in a 15% concise manner. | foster strong working reduction in churn rate relationships to achieve common goals. * Collaborated with cross-functional teams to develop data-driven strategies to optimize marketing campaigns 2 Adaptability and Continuous . * Learning Resea rch Assistant | embrace change and continuously seek XYZ University opportunities to expand my skill set and knowledge. | am a fast learner, always 8 2017-2022 9 Baltimore, MD . oo. a ; eager to explore new technologies and Conducted quantitative and qualitative research studies to gather data. methodologies to stay ahead in the rapidly Assisted in data analysis and report writing. Collaborated with professors evolving field of business analytics. on research projects. * Collected and analyzed survey data resulting in the publication of a research paper ¢ Assisted in conducting focus groups and interviews to gather data for SKI LLS research projects * Contributed to data cleaning and coding process to ensure data accuracy and reliability Data analysis Statistical modeling Data visualization SQL Excel Power BI Python R www.enhancv.com Powered by (CX? Enhancy", "metadata": {"filename": "134f68fc1f1efe74.pdf", "original_category": "Business Analyst", "extraction_method": "ocr"}, "parsed_education": [], "extracted_skills": ["Python", "excel", "SQL", "Communication", "Excel", "Power BI", "teams", "decision-making", "R"], "parsed_summary": " MY LIFE A highly analytical and results-driven business analyst with 3 PH | LOSOPHY years of", "personal_info": {"phone": "8 2017-2022 9", "first_name": null, "last_name": null}}
{"cv_id": "134f68fc1f1efe74", "target_role": "Web Developer", "score": 0, "cv_text": "ISABELLE TODD Entry-Level Business Analyst & (971) @ isabelle_todd@hotmail.com @ imperfect-issue.info 9 Edmondbury, United States of America SUMMARY MY LIFE A highly analytical and results-driven business analyst with 3 PH | LOSOPHY years of experience in data analysis, statistical modeling, and data visualization. Skilled in using tools like Excel, Power BI, and Data is the new oil. The ability to Python to extract insights and drive decision-making. | am proud analyze and interpret data isa of my accomplishments, including the publication of a research valuable skill in today's business paper on customer segmentation, the development of an world. automated data tracking system, and my contributions to data- driven strategies that have positively impacted business outcomes. | am excited about the opportunity to leverage my skills and experience to support decision-making, policy STRENGTHS formation, and strategic planning as an entry-level business . . analyst at your organization. 5 Analytical Problem-Solving | possess a strong analytical mindset and excel at solving complex problems using data-driven approaches. My ability to EXPE RI E N CE interpret and analyze data allows me to make informed decisions and drive Data Ana lyst business success. ABC Company WP Collaboration and @ 2022- Ongoing 9 New York City Communication Analyzed and interpreted complex data sets to identify trends, patterns, lam an effective collaborator and and insights. Developed visualizations and interactive dashboards to communicator, skilled at working with communicate findings to stakeholders. cross-functional teams and presenting * Identified key customer segments resulting in a 10% increase in sales complex data insights in a clear and * Created regression models to predict customer churn, resulting in a 15% concise manner. | foster strong working reduction in churn rate relationships to achieve common goals. * Collaborated with cross-functional teams to develop data-driven strategies to optimize marketing campaigns 2 Adaptability and Continuous . * Learning Resea rch Assistant | embrace change and continuously seek XYZ University opportunities to expand my skill set and knowledge. | am a fast learner, always 8 2017-2022 9 Baltimore, MD . oo. a ; eager to explore new technologies and Conducted quantitative and qualitative research studies to gather data. methodologies to stay ahead in the rapidly Assisted in data analysis and report writing. Collaborated with professors evolving field of business analytics. on research projects. * Collected and analyzed survey data resulting in the publication of a research paper ¢ Assisted in conducting focus groups and interviews to gather data for SKI LLS research projects * Contributed to data cleaning and coding process to ensure data accuracy and reliability Data analysis Statistical modeling Data visualization SQL Excel Power BI Python R www.enhancv.com Powered by (CX? Enhancy", "metadata": {"filename": "134f68fc1f1efe74.pdf", "original_category": "Business Analyst", "extraction_method": "ocr"}, "parsed_education": [], "extracted_skills": ["Python", "excel", "SQL", "Communication", "Excel", "Power BI", "teams", "decision-making", "R"], "parsed_summary": " MY LIFE A highly analytical and results-driven business analyst with 3 PH | LOSOPHY years of", "personal_info": {"phone": "8 2017-2022 9", "first_name": null, "last_name": null}}
{"cv_id": "134f68fc1f1efe74", "target_role": "SAP Developer", "score": 2, "cv_text": "ISABELLE TODD Entry-Level Business Analyst & (971) @ isabelle_todd@hotmail.com @ imperfect-issue.info 9 Edmondbury, United States of America SUMMARY MY LIFE A highly analytical and results-driven business analyst with 3 PH | LOSOPHY years of experience in data analysis, statistical modeling, and data visualization. Skilled in using tools like Excel, Power BI, and Data is the new oil. The ability to Python to extract insights and drive decision-making. | am proud analyze and interpret data isa of my accomplishments, including the publication of a research valuable skill in today's business paper on customer segmentation, the development of an world. automated data tracking system, and my contributions to data- driven strategies that have positively impacted business outcomes. | am excited about the opportunity to leverage my skills and experience to support decision-making, policy STRENGTHS formation, and strategic planning as an entry-level business . . analyst at your organization. 5 Analytical Problem-Solving | possess a strong analytical mindset and excel at solving complex problems using data-driven approaches. My ability to EXPE RI E N CE interpret and analyze data allows me to make informed decisions and drive Data Ana lyst business success. ABC Company WP Collaboration and @ 2022- Ongoing 9 New York City Communication Analyzed and interpreted complex data sets to identify trends, patterns, lam an effective collaborator and and insights. Developed visualizations and interactive dashboards to communicator, skilled at working with communicate findings to stakeholders. cross-functional teams and presenting * Identified key customer segments resulting in a 10% increase in sales complex data insights in a clear and * Created regression models to predict customer churn, resulting in a 15% concise manner. | foster strong working reduction in churn rate relationships to achieve common goals. * Collaborated with cross-functional teams to develop data-driven strategies to optimize marketing campaigns 2 Adaptability and Continuous . * Learning Resea rch Assistant | embrace change and continuously seek XYZ University opportunities to expand my skill set and knowledge. | am a fast learner, always 8 2017-2022 9 Baltimore, MD . oo. a ; eager to explore new technologies and Conducted quantitative and qualitative research studies to gather data. methodologies to stay ahead in the rapidly Assisted in data analysis and report writing. Collaborated with professors evolving field of business analytics. on research projects. * Collected and analyzed survey data resulting in the publication of a research paper ¢ Assisted in conducting focus groups and interviews to gather data for SKI LLS research projects * Contributed to data cleaning and coding process to ensure data accuracy and reliability Data analysis Statistical modeling Data visualization SQL Excel Power BI Python R www.enhancv.com Powered by (CX? Enhancy", "metadata": {"filename": "134f68fc1f1efe74.pdf", "original_category": "Business Analyst", "extraction_method": "ocr"}, "parsed_education": [], "extracted_skills": ["Python", "excel", "SQL", "Communication", "Excel", "Power BI", "teams", "decision-making", "R"], "parsed_summary": " MY LIFE A highly analytical and results-driven business analyst with 3 PH | LOSOPHY years of", "personal_info": {"phone": "8 2017-2022 9", "first_name": null, "last_name": null}}
{"cv_id": "134f68fc1f1efe74", "target_role": "Tester", "score": 0, "cv_text": "ISABELLE TODD Entry-Level Business Analyst & (971) @ isabelle_todd@hotmail.com @ imperfect-issue.info 9 Edmondbury, United States of America SUMMARY MY LIFE A highly analytical and results-driven business analyst with 3 PH | LOSOPHY years of experience in data analysis, statistical modeling, and data visualization. Skilled in using tools like Excel, Power BI, and Data is the new oil. The ability to Python to extract insights and drive decision-making. | am proud analyze and interpret data isa of my accomplishments, including the publication of a research valuable skill in today's business paper on customer segmentation, the development of an world. automated data tracking system, and my contributions to data- driven strategies that have positively impacted business outcomes. | am excited about the opportunity to leverage my skills and experience to support decision-making, policy STRENGTHS formation, and strategic planning as an entry-level business . . analyst at your organization. 5 Analytical Problem-Solving | possess a strong analytical mindset and excel at solving complex problems using data-driven approaches. My ability to EXPE RI E N CE interpret and analyze data allows me to make informed decisions and drive Data Ana lyst business success. ABC Company WP Collaboration and @ 2022- Ongoing 9 New York City Communication Analyzed and interpreted complex data sets to identify trends, patterns, lam an effective collaborator and and insights. Developed visualizations and interactive dashboards to communicator, skilled at working with communicate findings to stakeholders. cross-functional teams and presenting * Identified key customer segments resulting in a 10% increase in sales complex data insights in a clear and * Created regression models to predict customer churn, resulting in a 15% concise manner. | foster strong working reduction in churn rate relationships to achieve common goals. * Collaborated with cross-functional teams to develop data-driven strategies to optimize marketing campaigns 2 Adaptability and Continuous . * Learning Resea rch Assistant | embrace change and continuously seek XYZ University opportunities to expand my skill set and knowledge. | am a fast learner, always 8 2017-2022 9 Baltimore, MD . oo. a ; eager to explore new technologies and Conducted quantitative and qualitative research studies to gather data. methodologies to stay ahead in the rapidly Assisted in data analysis and report writing. Collaborated with professors evolving field of business analytics. on research projects. * Collected and analyzed survey data resulting in the publication of a research paper ¢ Assisted in conducting focus groups and interviews to gather data for SKI LLS research projects * Contributed to data cleaning and coding process to ensure data accuracy and reliability Data analysis Statistical modeling Data visualization SQL Excel Power BI Python R www.enhancv.com Powered by (CX? Enhancy", "metadata": {"filename": "134f68fc1f1efe74.pdf", "original_category": "Business Analyst", "extraction_method": "ocr"}, "parsed_education": [], "extracted_skills": ["Python", "excel", "SQL", "Communication", "Excel", "Power BI", "teams", "decision-making", "R"], "parsed_summary": " MY LIFE A highly analytical and results-driven business analyst with 3 PH | LOSOPHY years of", "personal_info": {"phone": "8 2017-2022 9", "first_name": null, "last_name": null}}
{"cv_id": "13ca85f7792ef4f7", "target_role": "Business Analyst", "score": 5, "cv_text": "ROSE NATHERS Entry Level Business Analyst rosenathers@email.com (123) 456-7890 LinkedIn W ORK EXPERIENCE Business Analyst Intern Bainbridge, Inc. August 2020 - current Pittsburgh, PA Performed in-depth research and analysis to help 10+ Fortune 1000 companies stay ahead of their competition Compiled data using data visualization and Excel, working with 2 senior business analysts to infer meaningful insights that improved organizational processes for several companies, which saved a total of 90 man hours per month Participated in 100+ hours of in-house workshops and state- wide conferences to improve industry knowledge Contributed to presentation preparations, and offered discussion in client and stakeholder meetings Drafted client reports under the supervision of senior analysts, receiving 100% positive feedback for alignment to client goals Communicated strategies to analyst team, and received valuable feedback regarding approach to business observations Administrative Assistant GCSS Advisors February 2017 - August 2020 Pittsburgh, PA Greeted 100+ quests and clients each shift, directing them to appropriate offices and staff Responded to multi-line phone system, directing calls with wait times less than 90 seconds, and answered emails Managed customer accounts, and suggested improved organization method that reduced time spent finding information by 13% Supported 6 office advisors, overseeing their appointment calendars, booking accommodations, and typing memos Handled inventories, and ensured copy machine and printer remained functional, replacing toner and removing jams Maintained lobby appearance, sweeping, dusting, and rearranging furniture and entertainment selections Pittsburgh, PA CAREER OBJECTIVE Team-oriented critical thinker with intern experience and relevant undergraduate coursework. Motivated to join a group of seasoned business analysts and cross- functional teammates at Professional Technology Integration, where | anticipate growth and the chance to prove my abilities by reaching clients as a Spanish speaker. EDUCATION B.S. Business University of Pittsburgh September 2016 - April 2020 Pittsburgh, PA GPA: 3.7 Relevant courses « Intermediate programming ¢ Probability & Statistics « Linear Algebra Applied Econometrics Game Theory Calculus 1-3 SKILLS ¢ Modeling: Linear and logistic regressions Data Visualization: Excel, Google Sheets, Matplotlib, Tableau Problem Solving Research and Analytical Skills Bilingual (Spanish)", "metadata": {"filename": "13ca85f7792ef4f7.pdf", "original_category": "Business Analyst", "extraction_method": "ocr"}, "parsed_education": [{"degree": "B.S", "institution": null, "years": "2016", "field_of_study": "Unknown"}], "extracted_skills": ["Tableau", "Excel"], "parsed_summary": "ROSE NATHERS Entry Level Business Analyst rosenathers@email.com (123) 456-7890 LinkedIn W ORK", "personal_info": {"phone": "(123) 456-7890", "first_name": null, "last_name": null}}
{"cv_id": "13ca85f7792ef4f7", "target_role": "Data Scientist", "score": 1, "cv_text": "ROSE NATHERS Entry Level Business Analyst rosenathers@email.com (123) 456-7890 LinkedIn W ORK EXPERIENCE Business Analyst Intern Bainbridge, Inc. August 2020 - current Pittsburgh, PA Performed in-depth research and analysis to help 10+ Fortune 1000 companies stay ahead of their competition Compiled data using data visualization and Excel, working with 2 senior business analysts to infer meaningful insights that improved organizational processes for several companies, which saved a total of 90 man hours per month Participated in 100+ hours of in-house workshops and state- wide conferences to improve industry knowledge Contributed to presentation preparations, and offered discussion in client and stakeholder meetings Drafted client reports under the supervision of senior analysts, receiving 100% positive feedback for alignment to client goals Communicated strategies to analyst team, and received valuable feedback regarding approach to business observations Administrative Assistant GCSS Advisors February 2017 - August 2020 Pittsburgh, PA Greeted 100+ quests and clients each shift, directing them to appropriate offices and staff Responded to multi-line phone system, directing calls with wait times less than 90 seconds, and answered emails Managed customer accounts, and suggested improved organization method that reduced time spent finding information by 13% Supported 6 office advisors, overseeing their appointment calendars, booking accommodations, and typing memos Handled inventories, and ensured copy machine and printer remained functional, replacing toner and removing jams Maintained lobby appearance, sweeping, dusting, and rearranging furniture and entertainment selections Pittsburgh, PA CAREER OBJECTIVE Team-oriented critical thinker with intern experience and relevant undergraduate coursework. Motivated to join a group of seasoned business analysts and cross- functional teammates at Professional Technology Integration, where | anticipate growth and the chance to prove my abilities by reaching clients as a Spanish speaker. EDUCATION B.S. Business University of Pittsburgh September 2016 - April 2020 Pittsburgh, PA GPA: 3.7 Relevant courses « Intermediate programming ¢ Probability & Statistics « Linear Algebra Applied Econometrics Game Theory Calculus 1-3 SKILLS ¢ Modeling: Linear and logistic regressions Data Visualization: Excel, Google Sheets, Matplotlib, Tableau Problem Solving Research and Analytical Skills Bilingual (Spanish)", "metadata": {"filename": "13ca85f7792ef4f7.pdf", "original_category": "Business Analyst", "extraction_method": "ocr"}, "parsed_education": [{"degree": "B.S", "institution": null, "years": "2016", "field_of_study": "Unknown"}], "extracted_skills": ["Tableau", "Excel"], "parsed_summary": "ROSE NATHERS Entry Level Business Analyst rosenathers@email.com (123) 456-7890 LinkedIn W ORK", "personal_info": {"phone": "(123) 456-7890", "first_name": null, "last_name": null}}
{"cv_id": "13ca85f7792ef4f7", "target_role": "DevOps Engineer", "score": 0, "cv_text": "ROSE NATHERS Entry Level Business Analyst rosenathers@email.com (123) 456-7890 LinkedIn W ORK EXPERIENCE Business Analyst Intern Bainbridge, Inc. August 2020 - current Pittsburgh, PA Performed in-depth research and analysis to help 10+ Fortune 1000 companies stay ahead of their competition Compiled data using data visualization and Excel, working with 2 senior business analysts to infer meaningful insights that improved organizational processes for several companies, which saved a total of 90 man hours per month Participated in 100+ hours of in-house workshops and state- wide conferences to improve industry knowledge Contributed to presentation preparations, and offered discussion in client and stakeholder meetings Drafted client reports under the supervision of senior analysts, receiving 100% positive feedback for alignment to client goals Communicated strategies to analyst team, and received valuable feedback regarding approach to business observations Administrative Assistant GCSS Advisors February 2017 - August 2020 Pittsburgh, PA Greeted 100+ quests and clients each shift, directing them to appropriate offices and staff Responded to multi-line phone system, directing calls with wait times less than 90 seconds, and answered emails Managed customer accounts, and suggested improved organization method that reduced time spent finding information by 13% Supported 6 office advisors, overseeing their appointment calendars, booking accommodations, and typing memos Handled inventories, and ensured copy machine and printer remained functional, replacing toner and removing jams Maintained lobby appearance, sweeping, dusting, and rearranging furniture and entertainment selections Pittsburgh, PA CAREER OBJECTIVE Team-oriented critical thinker with intern experience and relevant undergraduate coursework. Motivated to join a group of seasoned business analysts and cross- functional teammates at Professional Technology Integration, where | anticipate growth and the chance to prove my abilities by reaching clients as a Spanish speaker. EDUCATION B.S. Business University of Pittsburgh September 2016 - April 2020 Pittsburgh, PA GPA: 3.7 Relevant courses « Intermediate programming ¢ Probability & Statistics « Linear Algebra Applied Econometrics Game Theory Calculus 1-3 SKILLS ¢ Modeling: Linear and logistic regressions Data Visualization: Excel, Google Sheets, Matplotlib, Tableau Problem Solving Research and Analytical Skills Bilingual (Spanish)", "metadata": {"filename": "13ca85f7792ef4f7.pdf", "original_category": "Business Analyst", "extraction_method": "ocr"}, "parsed_education": [{"degree": "B.S", "institution": null, "years": "2016", "field_of_study": "Unknown"}], "extracted_skills": ["Tableau", "Excel"], "parsed_summary": "ROSE NATHERS Entry Level Business Analyst rosenathers@email.com (123) 456-7890 LinkedIn W ORK", "personal_info": {"phone": "(123) 456-7890", "first_name": null, "last_name": null}}
{"cv_id": "13ca85f7792ef4f7", "target_role": "ETL Developer", "score": 0, "cv_text": "ROSE NATHERS Entry Level Business Analyst rosenathers@email.com (123) 456-7890 LinkedIn W ORK EXPERIENCE Business Analyst Intern Bainbridge, Inc. August 2020 - current Pittsburgh, PA Performed in-depth research and analysis to help 10+ Fortune 1000 companies stay ahead of their competition Compiled data using data visualization and Excel, working with 2 senior business analysts to infer meaningful insights that improved organizational processes for several companies, which saved a total of 90 man hours per month Participated in 100+ hours of in-house workshops and state- wide conferences to improve industry knowledge Contributed to presentation preparations, and offered discussion in client and stakeholder meetings Drafted client reports under the supervision of senior analysts, receiving 100% positive feedback for alignment to client goals Communicated strategies to analyst team, and received valuable feedback regarding approach to business observations Administrative Assistant GCSS Advisors February 2017 - August 2020 Pittsburgh, PA Greeted 100+ quests and clients each shift, directing them to appropriate offices and staff Responded to multi-line phone system, directing calls with wait times less than 90 seconds, and answered emails Managed customer accounts, and suggested improved organization method that reduced time spent finding information by 13% Supported 6 office advisors, overseeing their appointment calendars, booking accommodations, and typing memos Handled inventories, and ensured copy machine and printer remained functional, replacing toner and removing jams Maintained lobby appearance, sweeping, dusting, and rearranging furniture and entertainment selections Pittsburgh, PA CAREER OBJECTIVE Team-oriented critical thinker with intern experience and relevant undergraduate coursework. Motivated to join a group of seasoned business analysts and cross- functional teammates at Professional Technology Integration, where | anticipate growth and the chance to prove my abilities by reaching clients as a Spanish speaker. EDUCATION B.S. Business University of Pittsburgh September 2016 - April 2020 Pittsburgh, PA GPA: 3.7 Relevant courses « Intermediate programming ¢ Probability & Statistics « Linear Algebra Applied Econometrics Game Theory Calculus 1-3 SKILLS ¢ Modeling: Linear and logistic regressions Data Visualization: Excel, Google Sheets, Matplotlib, Tableau Problem Solving Research and Analytical Skills Bilingual (Spanish)", "metadata": {"filename": "13ca85f7792ef4f7.pdf", "original_category": "Business Analyst", "extraction_method": "ocr"}, "parsed_education": [{"degree": "B.S", "institution": null, "years": "2016", "field_of_study": "Unknown"}], "extracted_skills": ["Tableau", "Excel"], "parsed_summary": "ROSE NATHERS Entry Level Business Analyst rosenathers@email.com (123) 456-7890 LinkedIn W ORK", "personal_info": {"phone": "(123) 456-7890", "first_name": null, "last_name": null}}
{"cv_id": "13ca85f7792ef4f7", "target_role": "Java Developer", "score": 0, "cv_text": "ROSE NATHERS Entry Level Business Analyst rosenathers@email.com (123) 456-7890 LinkedIn W ORK EXPERIENCE Business Analyst Intern Bainbridge, Inc. August 2020 - current Pittsburgh, PA Performed in-depth research and analysis to help 10+ Fortune 1000 companies stay ahead of their competition Compiled data using data visualization and Excel, working with 2 senior business analysts to infer meaningful insights that improved organizational processes for several companies, which saved a total of 90 man hours per month Participated in 100+ hours of in-house workshops and state- wide conferences to improve industry knowledge Contributed to presentation preparations, and offered discussion in client and stakeholder meetings Drafted client reports under the supervision of senior analysts, receiving 100% positive feedback for alignment to client goals Communicated strategies to analyst team, and received valuable feedback regarding approach to business observations Administrative Assistant GCSS Advisors February 2017 - August 2020 Pittsburgh, PA Greeted 100+ quests and clients each shift, directing them to appropriate offices and staff Responded to multi-line phone system, directing calls with wait times less than 90 seconds, and answered emails Managed customer accounts, and suggested improved organization method that reduced time spent finding information by 13% Supported 6 office advisors, overseeing their appointment calendars, booking accommodations, and typing memos Handled inventories, and ensured copy machine and printer remained functional, replacing toner and removing jams Maintained lobby appearance, sweeping, dusting, and rearranging furniture and entertainment selections Pittsburgh, PA CAREER OBJECTIVE Team-oriented critical thinker with intern experience and relevant undergraduate coursework. Motivated to join a group of seasoned business analysts and cross- functional teammates at Professional Technology Integration, where | anticipate growth and the chance to prove my abilities by reaching clients as a Spanish speaker. EDUCATION B.S. Business University of Pittsburgh September 2016 - April 2020 Pittsburgh, PA GPA: 3.7 Relevant courses « Intermediate programming ¢ Probability & Statistics « Linear Algebra Applied Econometrics Game Theory Calculus 1-3 SKILLS ¢ Modeling: Linear and logistic regressions Data Visualization: Excel, Google Sheets, Matplotlib, Tableau Problem Solving Research and Analytical Skills Bilingual (Spanish)", "metadata": {"filename": "13ca85f7792ef4f7.pdf", "original_category": "Business Analyst", "extraction_method": "ocr"}, "parsed_education": [{"degree": "B.S", "institution": null, "years": "2016", "field_of_study": "Unknown"}], "extracted_skills": ["Tableau", "Excel"], "parsed_summary": "ROSE NATHERS Entry Level Business Analyst rosenathers@email.com (123) 456-7890 LinkedIn W ORK", "personal_info": {"phone": "(123) 456-7890", "first_name": null, "last_name": null}}
{"cv_id": "13ca85f7792ef4f7", "target_role": "Python Developer", "score": 0, "cv_text": "ROSE NATHERS Entry Level Business Analyst rosenathers@email.com (123) 456-7890 LinkedIn W ORK EXPERIENCE Business Analyst Intern Bainbridge, Inc. August 2020 - current Pittsburgh, PA Performed in-depth research and analysis to help 10+ Fortune 1000 companies stay ahead of their competition Compiled data using data visualization and Excel, working with 2 senior business analysts to infer meaningful insights that improved organizational processes for several companies, which saved a total of 90 man hours per month Participated in 100+ hours of in-house workshops and state- wide conferences to improve industry knowledge Contributed to presentation preparations, and offered discussion in client and stakeholder meetings Drafted client reports under the supervision of senior analysts, receiving 100% positive feedback for alignment to client goals Communicated strategies to analyst team, and received valuable feedback regarding approach to business observations Administrative Assistant GCSS Advisors February 2017 - August 2020 Pittsburgh, PA Greeted 100+ quests and clients each shift, directing them to appropriate offices and staff Responded to multi-line phone system, directing calls with wait times less than 90 seconds, and answered emails Managed customer accounts, and suggested improved organization method that reduced time spent finding information by 13% Supported 6 office advisors, overseeing their appointment calendars, booking accommodations, and typing memos Handled inventories, and ensured copy machine and printer remained functional, replacing toner and removing jams Maintained lobby appearance, sweeping, dusting, and rearranging furniture and entertainment selections Pittsburgh, PA CAREER OBJECTIVE Team-oriented critical thinker with intern experience and relevant undergraduate coursework. Motivated to join a group of seasoned business analysts and cross- functional teammates at Professional Technology Integration, where | anticipate growth and the chance to prove my abilities by reaching clients as a Spanish speaker. EDUCATION B.S. Business University of Pittsburgh September 2016 - April 2020 Pittsburgh, PA GPA: 3.7 Relevant courses « Intermediate programming ¢ Probability & Statistics « Linear Algebra Applied Econometrics Game Theory Calculus 1-3 SKILLS ¢ Modeling: Linear and logistic regressions Data Visualization: Excel, Google Sheets, Matplotlib, Tableau Problem Solving Research and Analytical Skills Bilingual (Spanish)", "metadata": {"filename": "13ca85f7792ef4f7.pdf", "original_category": "Business Analyst", "extraction_method": "ocr"}, "parsed_education": [{"degree": "B.S", "institution": null, "years": "2016", "field_of_study": "Unknown"}], "extracted_skills": ["Tableau", "Excel"], "parsed_summary": "ROSE NATHERS Entry Level Business Analyst rosenathers@email.com (123) 456-7890 LinkedIn W ORK", "personal_info": {"phone": "(123) 456-7890", "first_name": null, "last_name": null}}
{"cv_id": "13ca85f7792ef4f7", "target_role": "React Developer", "score": 0, "cv_text": "ROSE NATHERS Entry Level Business Analyst rosenathers@email.com (123) 456-7890 LinkedIn W ORK EXPERIENCE Business Analyst Intern Bainbridge, Inc. August 2020 - current Pittsburgh, PA Performed in-depth research and analysis to help 10+ Fortune 1000 companies stay ahead of their competition Compiled data using data visualization and Excel, working with 2 senior business analysts to infer meaningful insights that improved organizational processes for several companies, which saved a total of 90 man hours per month Participated in 100+ hours of in-house workshops and state- wide conferences to improve industry knowledge Contributed to presentation preparations, and offered discussion in client and stakeholder meetings Drafted client reports under the supervision of senior analysts, receiving 100% positive feedback for alignment to client goals Communicated strategies to analyst team, and received valuable feedback regarding approach to business observations Administrative Assistant GCSS Advisors February 2017 - August 2020 Pittsburgh, PA Greeted 100+ quests and clients each shift, directing them to appropriate offices and staff Responded to multi-line phone system, directing calls with wait times less than 90 seconds, and answered emails Managed customer accounts, and suggested improved organization method that reduced time spent finding information by 13% Supported 6 office advisors, overseeing their appointment calendars, booking accommodations, and typing memos Handled inventories, and ensured copy machine and printer remained functional, replacing toner and removing jams Maintained lobby appearance, sweeping, dusting, and rearranging furniture and entertainment selections Pittsburgh, PA CAREER OBJECTIVE Team-oriented critical thinker with intern experience and relevant undergraduate coursework. Motivated to join a group of seasoned business analysts and cross- functional teammates at Professional Technology Integration, where | anticipate growth and the chance to prove my abilities by reaching clients as a Spanish speaker. EDUCATION B.S. Business University of Pittsburgh September 2016 - April 2020 Pittsburgh, PA GPA: 3.7 Relevant courses « Intermediate programming ¢ Probability & Statistics « Linear Algebra Applied Econometrics Game Theory Calculus 1-3 SKILLS ¢ Modeling: Linear and logistic regressions Data Visualization: Excel, Google Sheets, Matplotlib, Tableau Problem Solving Research and Analytical Skills Bilingual (Spanish)", "metadata": {"filename": "13ca85f7792ef4f7.pdf", "original_category": "Business Analyst", "extraction_method": "ocr"}, "parsed_education": [{"degree": "B.S", "institution": null, "years": "2016", "field_of_study": "Unknown"}], "extracted_skills": ["Tableau", "Excel"], "parsed_summary": "ROSE NATHERS Entry Level Business Analyst rosenathers@email.com (123) 456-7890 LinkedIn W ORK", "personal_info": {"phone": "(123) 456-7890", "first_name": null, "last_name": null}}
{"cv_id": "13ca85f7792ef4f7", "target_role": "SQL Developer", "score": 2, "cv_text": "ROSE NATHERS Entry Level Business Analyst rosenathers@email.com (123) 456-7890 LinkedIn W ORK EXPERIENCE Business Analyst Intern Bainbridge, Inc. August 2020 - current Pittsburgh, PA Performed in-depth research and analysis to help 10+ Fortune 1000 companies stay ahead of their competition Compiled data using data visualization and Excel, working with 2 senior business analysts to infer meaningful insights that improved organizational processes for several companies, which saved a total of 90 man hours per month Participated in 100+ hours of in-house workshops and state- wide conferences to improve industry knowledge Contributed to presentation preparations, and offered discussion in client and stakeholder meetings Drafted client reports under the supervision of senior analysts, receiving 100% positive feedback for alignment to client goals Communicated strategies to analyst team, and received valuable feedback regarding approach to business observations Administrative Assistant GCSS Advisors February 2017 - August 2020 Pittsburgh, PA Greeted 100+ quests and clients each shift, directing them to appropriate offices and staff Responded to multi-line phone system, directing calls with wait times less than 90 seconds, and answered emails Managed customer accounts, and suggested improved organization method that reduced time spent finding information by 13% Supported 6 office advisors, overseeing their appointment calendars, booking accommodations, and typing memos Handled inventories, and ensured copy machine and printer remained functional, replacing toner and removing jams Maintained lobby appearance, sweeping, dusting, and rearranging furniture and entertainment selections Pittsburgh, PA CAREER OBJECTIVE Team-oriented critical thinker with intern experience and relevant undergraduate coursework. Motivated to join a group of seasoned business analysts and cross- functional teammates at Professional Technology Integration, where | anticipate growth and the chance to prove my abilities by reaching clients as a Spanish speaker. EDUCATION B.S. Business University of Pittsburgh September 2016 - April 2020 Pittsburgh, PA GPA: 3.7 Relevant courses « Intermediate programming ¢ Probability & Statistics « Linear Algebra Applied Econometrics Game Theory Calculus 1-3 SKILLS ¢ Modeling: Linear and logistic regressions Data Visualization: Excel, Google Sheets, Matplotlib, Tableau Problem Solving Research and Analytical Skills Bilingual (Spanish)", "metadata": {"filename": "13ca85f7792ef4f7.pdf", "original_category": "Business Analyst", "extraction_method": "ocr"}, "parsed_education": [{"degree": "B.S", "institution": null, "years": "2016", "field_of_study": "Unknown"}], "extracted_skills": ["Tableau", "Excel"], "parsed_summary": "ROSE NATHERS Entry Level Business Analyst rosenathers@email.com (123) 456-7890 LinkedIn W ORK", "personal_info": {"phone": "(123) 456-7890", "first_name": null, "last_name": null}}
{"cv_id": "13ca85f7792ef4f7", "target_role": "Web Developer", "score": 0, "cv_text": "ROSE NATHERS Entry Level Business Analyst rosenathers@email.com (123) 456-7890 LinkedIn W ORK EXPERIENCE Business Analyst Intern Bainbridge, Inc. August 2020 - current Pittsburgh, PA Performed in-depth research and analysis to help 10+ Fortune 1000 companies stay ahead of their competition Compiled data using data visualization and Excel, working with 2 senior business analysts to infer meaningful insights that improved organizational processes for several companies, which saved a total of 90 man hours per month Participated in 100+ hours of in-house workshops and state- wide conferences to improve industry knowledge Contributed to presentation preparations, and offered discussion in client and stakeholder meetings Drafted client reports under the supervision of senior analysts, receiving 100% positive feedback for alignment to client goals Communicated strategies to analyst team, and received valuable feedback regarding approach to business observations Administrative Assistant GCSS Advisors February 2017 - August 2020 Pittsburgh, PA Greeted 100+ quests and clients each shift, directing them to appropriate offices and staff Responded to multi-line phone system, directing calls with wait times less than 90 seconds, and answered emails Managed customer accounts, and suggested improved organization method that reduced time spent finding information by 13% Supported 6 office advisors, overseeing their appointment calendars, booking accommodations, and typing memos Handled inventories, and ensured copy machine and printer remained functional, replacing toner and removing jams Maintained lobby appearance, sweeping, dusting, and rearranging furniture and entertainment selections Pittsburgh, PA CAREER OBJECTIVE Team-oriented critical thinker with intern experience and relevant undergraduate coursework. Motivated to join a group of seasoned business analysts and cross- functional teammates at Professional Technology Integration, where | anticipate growth and the chance to prove my abilities by reaching clients as a Spanish speaker. EDUCATION B.S. Business University of Pittsburgh September 2016 - April 2020 Pittsburgh, PA GPA: 3.7 Relevant courses « Intermediate programming ¢ Probability & Statistics « Linear Algebra Applied Econometrics Game Theory Calculus 1-3 SKILLS ¢ Modeling: Linear and logistic regressions Data Visualization: Excel, Google Sheets, Matplotlib, Tableau Problem Solving Research and Analytical Skills Bilingual (Spanish)", "metadata": {"filename": "13ca85f7792ef4f7.pdf", "original_category": "Business Analyst", "extraction_method": "ocr"}, "parsed_education": [{"degree": "B.S", "institution": null, "years": "2016", "field_of_study": "Unknown"}], "extracted_skills": ["Tableau", "Excel"], "parsed_summary": "ROSE NATHERS Entry Level Business Analyst rosenathers@email.com (123) 456-7890 LinkedIn W ORK", "personal_info": {"phone": "(123) 456-7890", "first_name": null, "last_name": null}}
{"cv_id": "13ca85f7792ef4f7", "target_role": "SAP Developer", "score": 2, "cv_text": "ROSE NATHERS Entry Level Business Analyst rosenathers@email.com (123) 456-7890 LinkedIn W ORK EXPERIENCE Business Analyst Intern Bainbridge, Inc. August 2020 - current Pittsburgh, PA Performed in-depth research and analysis to help 10+ Fortune 1000 companies stay ahead of their competition Compiled data using data visualization and Excel, working with 2 senior business analysts to infer meaningful insights that improved organizational processes for several companies, which saved a total of 90 man hours per month Participated in 100+ hours of in-house workshops and state- wide conferences to improve industry knowledge Contributed to presentation preparations, and offered discussion in client and stakeholder meetings Drafted client reports under the supervision of senior analysts, receiving 100% positive feedback for alignment to client goals Communicated strategies to analyst team, and received valuable feedback regarding approach to business observations Administrative Assistant GCSS Advisors February 2017 - August 2020 Pittsburgh, PA Greeted 100+ quests and clients each shift, directing them to appropriate offices and staff Responded to multi-line phone system, directing calls with wait times less than 90 seconds, and answered emails Managed customer accounts, and suggested improved organization method that reduced time spent finding information by 13% Supported 6 office advisors, overseeing their appointment calendars, booking accommodations, and typing memos Handled inventories, and ensured copy machine and printer remained functional, replacing toner and removing jams Maintained lobby appearance, sweeping, dusting, and rearranging furniture and entertainment selections Pittsburgh, PA CAREER OBJECTIVE Team-oriented critical thinker with intern experience and relevant undergraduate coursework. Motivated to join a group of seasoned business analysts and cross- functional teammates at Professional Technology Integration, where | anticipate growth and the chance to prove my abilities by reaching clients as a Spanish speaker. EDUCATION B.S. Business University of Pittsburgh September 2016 - April 2020 Pittsburgh, PA GPA: 3.7 Relevant courses « Intermediate programming ¢ Probability & Statistics « Linear Algebra Applied Econometrics Game Theory Calculus 1-3 SKILLS ¢ Modeling: Linear and logistic regressions Data Visualization: Excel, Google Sheets, Matplotlib, Tableau Problem Solving Research and Analytical Skills Bilingual (Spanish)", "metadata": {"filename": "13ca85f7792ef4f7.pdf", "original_category": "Business Analyst", "extraction_method": "ocr"}, "parsed_education": [{"degree": "B.S", "institution": null, "years": "2016", "field_of_study": "Unknown"}], "extracted_skills": ["Tableau", "Excel"], "parsed_summary": "ROSE NATHERS Entry Level Business Analyst rosenathers@email.com (123) 456-7890 LinkedIn W ORK", "personal_info": {"phone": "(123) 456-7890", "first_name": null, "last_name": null}}
